Workbook
Name Mã_số_ca: #REF!
Name Vật_Tư: #REF!
Name Bang_dulieu: #REF!
Name Số_Lượng: #REF!
Name Ngày: #REF!
Name Tên_con_vật: #REF!
Name Gia_chủ: #REF!
Name Sđt: #REF!
Name Mã_Hàng: #REF!
Name Bệnh_lý: #REF!
Name Địa_chỉ: #REF!
Name Đơn_giá: #REF!

Sheet BC Thang
B1: CSDL khách hàng | E1: Số tiền CBC | F1: =SUMIFS(L4:L3085, I4:I3085, "CBC") -> 4070 | G1: Số ca CBC | I1: =countifs(I4:I3086,"CBC") -> 21 | L1: Total | M1: =O1-N1 -> 119414 | N1: =SUMIFS(M4:M3342, N4:N3342, "CK petshop thầy") -> 2816 | O1: =SUM(M4:M2974) -> 122230 | Q1: =SUM(Q4:Q2974) -> 122230
A3: Ngày | B3: MS ca | C3: SDT | D3: Gia chủ | E3: Địa chỉ | F3: Loài | G3: Tên thú | H3: TL(Kg) | I3: Bệnh lý/Thủ thuật/thuốc | J3: Phí thu | K3: Số lượng | L3: Thành tiền | M3: Tổng thu | N3: Người thu | O3: Chú ý | P3: Ngày ra viện | Q3: Tổng thu Tuần
A4: 45962 | D4: khách lẻ | E4: =vlookup($C4,CSDL!$A:$E,3,0) -> #N/A | F4: =vlookup($C4,CSDL!$A:$E,4,0) -> #N/A | G4: =vlookup($C4,CSDL!$A:$E,5,0) -> #N/A | I4: Tẩy giun nhỏ | J4: 20 | K4: 3 | L4: =K4*J4 -> 60 | M4: 60 | N4: Thầy
D5: khách lẻ | E5: =vlookup($C5,CSDL!$A:$E,3,0) -> #N/A | F5: =vlookup($C5,CSDL!$A:$E,4,0) -> #N/A | G5: =vlookup($C5,CSDL!$A:$E,5,0) -> #N/A | I5: Thuốc bán | J5: 30 | K5: 7 | L5: =K5*J5 -> 210 | M5: 250 | N5: CK thầy | O5: 1/11 - Nguyen Phan Ha My ct
D6: =vlookup($C6,CSDL!$A:$E,2,0) -> #N/A | E6: =vlookup($C6,CSDL!$A:$E,3,0) -> #N/A | F6: =vlookup($C6,CSDL!$A:$E,4,0) -> #N/A | G6: =vlookup($C6,CSDL!$A:$E,5,0) -> #N/A | I6: Tẩy giun nhỏ | J6: 40 | K6: 1 | L6: =K6*J6 -> 40
D7: khách lẻ | I7: Tẩy giun lớn | J7: 50 | K7: 1 | L7: =K7*J7 -> 50 | M7: 50 | N7: CK thầy | O7: 1/11 - Tran Thi Ny ct
B8: 1170 | C8: 0833 555 733 | D8: =vlookup($C8,CSDL!$A:$E,2,0) -> ANh Trí | E8: =vlookup($C8,CSDL!$A:$E,3,0) -> An NInh | F8: =vlookup($C8,CSDL!$A:$E,4,0) -> n | G8: =vlookup($C8,CSDL!$A:$E,5,0) -> Miu | I8: Chích thuốc nhỏ | J8: 120 | K8: 1 | L8: =K8*J8 -> 120 | M8: 120 | N8: CK thầy | O8: 1/11 - Minh Tri ct
B9: 1171 | C9: 0935 403 717 | D9: =vlookup($C9,CSDL!$A:$E,2,0) | E9: =vlookup($C9,CSDL!$A:$E,3,0) -> Ngõ 29/245A Bùi Thị Xuân | F9: =vlookup($C9,CSDL!$A:$E,4,0) -> Mèo | G9: =vlookup($C9,CSDL!$A:$E,5,0) | I9: Petshop | J9: =170+39 -> 209 | K9: 1 | L9: =K9*J9 -> 209 | M9: 219 | N9: CK petshop thầy | O9: 269k - 1/11 - Ho Vu Nhat ct
B10: 1171 | D10: =vlookup($C10,CSDL!$A:$E,2,0) -> #N/A | E10: =vlookup($C10,CSDL!$A:$E,3,0) -> #N/A | F10: =vlookup($C10,CSDL!$A:$E,4,0) -> #N/A | G10: =vlookup($C10,CSDL!$A:$E,5,0) -> #N/A | I10: Tẩy giun nhỏ | J10: 50 | K10: 1 | L10: =K10*J10 -> 50 | M10: 50 | N10: CK thầy
D11: khách lẻ | E11: =vlookup($C11,CSDL!$A:$E,3,0) -> #N/A | F11: =vlookup($C11,CSDL!$A:$E,4,0) -> #N/A | G11: =vlookup($C11,CSDL!$A:$E,5,0) -> #N/A | I11: Petshop | J11: 50 | K11: 1 | L11: =K11*J11 -> 50 | M11: 50 | N11: CK petshop thầy | O11: 1/11 - Tran Duc Anh Quan ct
B12: 1172 | C12: 0372 033 490 | D12: =vlookup($C12,CSDL!$A:$E,2,0) -> Em Thọ | E12: =vlookup($C12,CSDL!$A:$E,3,0) | F12: =vlookup($C12,CSDL!$A:$E,4,0) | G12: =vlookup($C12,CSDL!$A:$E,5,0) | I12: Lưu trú nhỏ | J12: 150 | K12: 3 | L12: =K12*J12 -> 450 | M12: 450 | N12: CK thầy | O12: 4/11 - Tran Dinh Huu Tho
A13: 45963 | B13: 1101 | C13: 0903 565 648 | D13: =vlookup($C13,CSDL!$A:$E,2,0) -> Sư Cô Thanh Nhã | E13: =vlookup($C13,CSDL!$A:$E,3,0) -> Quảng Trị | F13: =vlookup($C13,CSDL!$A:$E,4,0) -> Chó | G13: Bảo Bảo | L13: =K13*J13 -> 0 | M13: 4000 | N13: CK thầy | O13: 2/11 - Phan Thi Thanh Phuong ct
B14: 1101 | D14: =vlookup($C14,CSDL!$A:$E,2,0) -> #N/A | E14: =vlookup($C14,CSDL!$A:$E,3,0) -> #N/A | F14: =vlookup($C14,CSDL!$A:$E,4,0) -> #N/A | G14: =vlookup($C14,CSDL!$A:$E,5,0) -> #N/A | L14: =K14*J14 -> 0 | M14: 300 | N14: Ánh
B15: 1161 | C15: 0935 919 137 | D15: =vlookup($C15,CSDL!$A:$E,2,0) -> Anh Cường | E15: =vlookup($C15,CSDL!$A:$E,3,0) -> Hương Hồ | F15: =vlookup($C15,CSDL!$A:$E,4,0) -> Chó | G15: =vlookup($C15,CSDL!$A:$E,5,0) -> Nâu | L15: =K15*J15 -> 0 | M15: 640 | N15: CK thầy | O15: 2/11 - Bui Van Cuong
B16: 1173 | C16: 0903 584 535 | D16: =vlookup($C16,CSDL!$A:$E,2,0) -> Chị Ánh Nguyệt | E16: =vlookup($C16,CSDL!$A:$E,3,0) -> 40 Lý Thái Tổ | F16: =vlookup($C16,CSDL!$A:$E,4,0) -> Mèo | G16: =vlookup($C16,CSDL!$A:$E,5,0) -> Sumo | I16: Thuốc bán | J16: 35 | K16: 1 | L16: =K16*J16 -> 35 | M16: =2571-36 -> 2535 | N16: CK thầy | O16: 2571k - 2/11 - Tran Thi Anh Nguyet ct
B17: 1173 | D17: =vlookup($C17,CSDL!$A:$E,2,0) -> #N/A | E17: =vlookup($C17,CSDL!$A:$E,3,0) -> #N/A | F17: =vlookup($C17,CSDL!$A:$E,4,0) -> #N/A | G17: =vlookup($C17,CSDL!$A:$E,5,0) -> #N/A | I17: Lưu trú nhỏ | J17: 120 | K17: 3 | L17: =K17*J17 -> 360 | M17: 36 | N17: CK petshop thầy
B18: 1173 | D18: =vlookup($C18,CSDL!$A:$E,2,0) -> #N/A | E18: =vlookup($C18,CSDL!$A:$E,3,0) -> #N/A | F18: =vlookup($C18,CSDL!$A:$E,4,0) -> #N/A | G18: =vlookup($C18,CSDL!$A:$E,5,0) -> #N/A | I18: CBC | J18: 150 | K18: 1 | L18: =K18*J18 -> 150
B19: 1173 | D19: =vlookup($C19,CSDL!$A:$E,2,0) -> #N/A | E19: =vlookup($C19,CSDL!$A:$E,3,0) -> #N/A | F19: =vlookup($C19,CSDL!$A:$E,4,0) -> #N/A | G19: =vlookup($C19,CSDL!$A:$E,5,0) -> #N/A | I19: Sinh hóa máu | J19: 300 | K19: 1 | L19: =K19*J19 -> 300
B20: 1173 | D20: =vlookup($C20,CSDL!$A:$E,2,0) -> #N/A | E20: =vlookup($C20,CSDL!$A:$E,3,0) -> #N/A | F20: =vlookup($C20,CSDL!$A:$E,4,0) -> #N/A | G20: =vlookup($C20,CSDL!$A:$E,5,0) -> #N/A | I20: Thuốc FIP tiêm | J20: 1700 | K20: 1 | L20: =K20*J20 -> 1700
B21: 1173 | D21: =vlookup($C21,CSDL!$A:$E,2,0) -> #N/A | E21: =vlookup($C21,CSDL!$A:$E,3,0) -> #N/A | F21: =vlookup($C21,CSDL!$A:$E,4,0) -> #N/A | G21: =vlookup($C21,CSDL!$A:$E,5,0) -> #N/A | I21: Petshop | J21: 36 | K21: 1 | L21: =K21*J21 -> 36
A22: 45965 | B22: 1174 | C22: 0905 563 662 | D22: =vlookup($C22,CSDL!$A:$E,2,0) -> Anh Dũng | E22: =vlookup($C22,CSDL!$A:$E,3,0) -> 57 Lê Duẩn | F22: =vlookup($C22,CSDL!$A:$E,4,0) -> chó | G22: =vlookup($C22,CSDL!$A:$E,5,0) -> Ken | I22: Vaccine 7b chó | J22: 180 | K22: 1 | L22: =K22*J22 -> 180 | M22: 320 | N22: Ánh
B23: 1174 | D23: =vlookup($C23,CSDL!$A:$E,2,0) -> #N/A | E23: =vlookup($C23,CSDL!$A:$E,3,0) -> #N/A | F23: =vlookup($C23,CSDL!$A:$E,4,0) -> #N/A | G23: =vlookup($C23,CSDL!$A:$E,5,0) -> #N/A | I23: Chích thuốc nhỏ | J23: 100 | K23: 1 | L23: =K23*J23 -> 100
B24: 1174 | D24: =vlookup($C24,CSDL!$A:$E,2,0) -> #N/A | E24: =vlookup($C24,CSDL!$A:$E,3,0) -> #N/A | F24: =vlookup($C24,CSDL!$A:$E,4,0) -> #N/A | G24: =vlookup($C24,CSDL!$A:$E,5,0) -> #N/A | I24: Tẩy giun nhỏ | J24: 40 | K24: 1 | L24: =K24*J24 -> 40
D25: khách lẻ | I25: Men tiêu hoá | J25: 10 | K25: 1 | L25: =K25*J25 -> 10 | M25: 10 | N25: CK thầy | O25: 4/11- Huong Giang ct
B26: 1175 | C26: 0888 671 489 | D26: =vlookup($C26,CSDL!$A:$E,2,0) | E26: =vlookup($C26,CSDL!$A:$E,3,0) | F26: =vlookup($C26,CSDL!$A:$E,4,0) | G26: =vlookup($C26,CSDL!$A:$E,5,0) | I26: Hỏa Táng | J26: 1450 | K26: 1 | L26: =K26*J26 -> 1450 | M26: 1500 | N26: CK thầy | O26: 4/11 - Nguyen Ngoc Quy ct
B27: 1175 | D27: =vlookup($C27,CSDL!$A:$E,2,0) -> #N/A | E27: =vlookup($C27,CSDL!$A:$E,3,0) -> #N/A | F27: =vlookup($C27,CSDL!$A:$E,4,0) -> #N/A | G27: =vlookup($C27,CSDL!$A:$E,5,0) -> #N/A | L27: =K27*J27 -> 0 | M27: -50
B28: 1176 | C28: 0905 733 786 | D28: =vlookup($C28,CSDL!$A:$E,2,0) -> Em Bảo Uyên | E28: =vlookup($C28,CSDL!$A:$E,3,0) -> 180 Lý Nam Đế | F28: =vlookup($C28,CSDL!$A:$E,4,0) -> Chó | G28: =vlookup($C28,CSDL!$A:$E,5,0) -> Lạc | I28: Lưu điều trị nhỏ | J28: 150 | K28: 1 | L28: =K28*J28 -> 150 | M28: 150 | N28: CK thầy | O28: 29/11 - Bao Uyen ct
B29: 1177 | C29: 0934 769 696 | D29: =vlookup($C29,CSDL!$A:$E,2,0) -> Anh Vũ | E29: =vlookup($C29,CSDL!$A:$E,3,0) -> 25 Lương Quán | F29: =vlookup($C29,CSDL!$A:$E,4,0) -> Chó | G29: =vlookup($C29,CSDL!$A:$E,5,0) -> Đen | I29: Lưu trú nhỏ | J29: 200 | L29: =K29*J29 -> 0 | M29: 1000 | N29: CK thầy | O29: 4/11 - Bui Van Vu ct
B30: 1177 | M30: 3500 | N30: CK thầy | O30: 23/11 - Bui Van Vu ct
B31: 1178 | C31: 0796 052 617 | D31: =vlookup($C31,CSDL!$A:$E,2,0) -> Chị Thuý | E31: =vlookup($C31,CSDL!$A:$E,3,0) -> Lô E9 Hương Bình | F31: =vlookup($C31,CSDL!$A:$E,4,0) -> chó | I31: Chích thuốc nhỏ | J31: 150 | K31: 2 | L31: =K31*J31 -> 300 | M31: 150 | N31: Trà
B32: 1178 | D32: =vlookup($C32,CSDL!$A:$E,2,0) -> #N/A | E32: =vlookup($C32,CSDL!$A:$E,3,0) -> #N/A | F32: =vlookup($C32,CSDL!$A:$E,4,0) -> #N/A | G32: =vlookup($C32,CSDL!$A:$E,5,0) -> #N/A | I32: Tẩy giun nhỏ | J32: 10 | K32: 1 | L32: =K32*J32 -> 10 | M32: 285 | N32: CK thầy | O32: 7/11 - Diem Thuy ct
B33: 1178 | D33: =vlookup($C33,CSDL!$A:$E,2,0) -> #N/A | E33: =vlookup($C33,CSDL!$A:$E,3,0) -> #N/A | F33: =vlookup($C33,CSDL!$A:$E,4,0) -> #N/A | G33: =vlookup($C33,CSDL!$A:$E,5,0) -> #N/A | I33: Thuốc bán | J33: 25 | K33: 5 | L33: =K33*J33 -> 125
B34: 1179 | C34: 0944 208 167 | D34: =vlookup($C34,CSDL!$A:$E,2,0) -> Em Duy | E34: =vlookup($C34,CSDL!$A:$E,3,0) | F34: =vlookup($C34,CSDL!$A:$E,4,0) -> Chó | G34: =vlookup($C34,CSDL!$A:$E,5,0) -> Quýt | I34: Lưu điều trị nhỏ | J34: 150 | K34: 2 | L34: =K34*J34 -> 300 | M34: 500 | N34: CK thầy | O34: 4/11 - Truong Dien Huong ct
B35: 1179 | D35: =vlookup($C35,CSDL!$A:$E,2,0) -> #N/A | E35: =vlookup($C35,CSDL!$A:$E,3,0) -> #N/A | F35: =vlookup($C35,CSDL!$A:$E,4,0) -> #N/A | G35: =vlookup($C35,CSDL!$A:$E,5,0) -> #N/A | I35: Diệt ve Hantox | J35: 50 | K35: 1 | L35: =K35*J35 -> 50 | M35: -150
D36: Ngọc Anh | E36: =vlookup($C36,CSDL!$A:$E,3,0) -> #N/A | F36: =vlookup($C36,CSDL!$A:$E,4,0) -> #N/A | G36: =vlookup($C36,CSDL!$A:$E,5,0) -> #N/A | I36: Vaccine 7b chó | J36: 180 | K36: 1 | L36: =K36*J36 -> 180 | M36: 180 | N36: CK thầy | O36: 4/11 - Ngoc Anh - hẹn 25/11 tiêm 7b + dại
D37: khách lẻ | E37: =vlookup($C37,CSDL!$A:$E,3,0) -> #N/A | F37: =vlookup($C37,CSDL!$A:$E,4,0) -> #N/A | G37: =vlookup($C37,CSDL!$A:$E,5,0) -> #N/A | I37: Petshop | J37: 70 | K37: 1 | L37: =K37*J37 -> 70 | M37: 70 | N37: CK petshop thầy | O37: 4/11 - Vo Thi Kim Hang ct
B38: 1180 | C38: 0349 978 213 | D38: =vlookup($C38,CSDL!$A:$E,2,0) -> Diễm Quỳnh | E38: =vlookup($C38,CSDL!$A:$E,3,0) -> 2/5 Nguyễn Phúc thái | F38: Mèo | G38: Chó | H38: 2 | I38: FPV- | J38: 150 | K38: 1 | L38: =K38*J38 -> 150 | M38: 500 | N38: Trà
B39: 1180 | D39: =vlookup($C39,CSDL!$A:$E,2,0) -> #N/A | E39: =vlookup($C39,CSDL!$A:$E,3,0) -> #N/A | F39: =vlookup($C39,CSDL!$A:$E,4,0) -> #N/A | G39: =vlookup($C39,CSDL!$A:$E,5,0) -> #N/A | I39: Lưu điều trị nhỏ | J39: 150 | K39: 4 | L39: =K39*J39 -> 600 | M39: 400 | N39: CK thầy | O39: 7/11 - Tran tan Anh Khoa
B40: 1180 | D40: =vlookup($C40,CSDL!$A:$E,2,0) -> #N/A | E40: =vlookup($C40,CSDL!$A:$E,3,0) -> #N/A | F40: =vlookup($C40,CSDL!$A:$E,4,0) -> #N/A | G40: =vlookup($C40,CSDL!$A:$E,5,0) -> #N/A | I40: Thuốc bán | J40: 30 | K40: 5 | L40: =K40*J40 -> 150
B41: 1181 | C41: 0903 565 648 | D41: =vlookup($C41,CSDL!$A:$E,2,0) -> Sư Cô Thanh Nhã | E41: =vlookup($C41,CSDL!$A:$E,3,0) -> Quảng Trị | F41: =vlookup($C41,CSDL!$A:$E,4,0) -> Chó | G41: Bảo | I41: Thuốc bán | J41: 35 | K41: 7 | L41: =K41*J41 -> 245 | M41: 315 | N41: CK thầy | O41: 4/11 - Phan Thi Thanh Phuong ct
B42: 1181 | D42: =vlookup($C42,CSDL!$A:$E,2,0) -> #N/A | E42: =vlookup($C42,CSDL!$A:$E,3,0) -> #N/A | F42: =vlookup($C42,CSDL!$A:$E,4,0) -> #N/A | G42: =vlookup($C42,CSDL!$A:$E,5,0) -> #N/A | I42: Về nhà | J42: 70 | K42: 1 | L42: =K42*J42 -> 70
B43: 1182 | D43: khách lẻ | E43: =vlookup($C43,CSDL!$A:$E,3,0) -> #N/A | F43: =vlookup($C43,CSDL!$A:$E,4,0) -> #N/A | G43: =vlookup($C43,CSDL!$A:$E,5,0) -> #N/A | I43: Tắm chó nhỏ | J43: 200 | K43: 1 | L43: =K43*J43 -> 200 | M43: 230 | N43: Trà
B44: 1182 | D44: =vlookup($C44,CSDL!$A:$E,2,0) -> #N/A | E44: =vlookup($C44,CSDL!$A:$E,3,0) -> #N/A | F44: =vlookup($C44,CSDL!$A:$E,4,0) -> #N/A | G44: =vlookup($C44,CSDL!$A:$E,5,0) -> #N/A | I44: Về nhà | J44: 30 | K44: 1 | L44: =K44*J44 -> 30
A45: 45966 | B45: 1183 | C45: 0971 008 346 | D45: =vlookup($C45,CSDL!$A:$E,2,0) -> BSTY Trà | E45: =vlookup($C45,CSDL!$A:$E,3,0) | F45: =vlookup($C45,CSDL!$A:$E,4,0) | G45: =vlookup($C45,CSDL!$A:$E,5,0) | I45: Diệt ve Simparica <10 | J45: 180 | K45: 1 | L45: =K45*J45 -> 180 | M45: 1000 | N45: CK thầy | O45: 5/11 - Nguyen Thi Thu Tra ct
B46: 1183 | D46: =vlookup($C46,CSDL!$A:$E,2,0) -> #N/A | E46: =vlookup($C46,CSDL!$A:$E,3,0) -> #N/A | F46: =vlookup($C46,CSDL!$A:$E,4,0) -> #N/A | G46: =vlookup($C46,CSDL!$A:$E,5,0) -> #N/A | I46: Petshop | J46: 70 | K46: 1 | L46: =K46*J46 -> 70
B47: 1183 | D47: =vlookup($C47,CSDL!$A:$E,2,0) -> #N/A | E47: =vlookup($C47,CSDL!$A:$E,3,0) -> #N/A | F47: =vlookup($C47,CSDL!$A:$E,4,0) -> #N/A | G47: =vlookup($C47,CSDL!$A:$E,5,0) -> #N/A | I47: Thuốc bán | J47: 20 | L47: =K47*J47 -> 0
B48: 1183 | D48: =vlookup($C48,CSDL!$A:$E,2,0) -> #N/A | E48: =vlookup($C48,CSDL!$A:$E,3,0) -> #N/A | F48: =vlookup($C48,CSDL!$A:$E,4,0) -> #N/A | G48: =vlookup($C48,CSDL!$A:$E,5,0) -> #N/A | I48: Lưu trú nhỏ | L48: =K48*J48 -> 0
B49: 1183 | D49: =vlookup($C49,CSDL!$A:$E,2,0) -> #N/A | E49: =vlookup($C49,CSDL!$A:$E,3,0) -> #N/A | F49: =vlookup($C49,CSDL!$A:$E,4,0) -> #N/A | G49: =vlookup($C49,CSDL!$A:$E,5,0) -> #N/A | I49: Vaccine 7b chó | J49: 180 | K49: 1 | L49: =K49*J49 -> 180
B50: 1184 | C50: 0935 131 718 | D50: =vlookup($C50,CSDL!$A:$E,2,0) -> Chị Vân Anh | E50: =vlookup($C50,CSDL!$A:$E,3,0) -> 130 Trường Chinh | F50: =vlookup($C50,CSDL!$A:$E,4,0) -> Mèo | G50: Hóa | H50: 3 | I50: Lưu điều trị nhỏ | J50: 150 | K50: 5 | L50: =K50*J50 -> 750 | M50: 1050 | N50: CK thầy | O50: 5/11 - Le Ngoc Van Anh ct
B51: 1184 | D51: =vlookup($C51,CSDL!$A:$E,2,0) -> #N/A | E51: =vlookup($C51,CSDL!$A:$E,3,0) -> #N/A | F51: =vlookup($C51,CSDL!$A:$E,4,0) -> #N/A | G51: =vlookup($C51,CSDL!$A:$E,5,0) -> #N/A | I51: Thuốc bán | J51: 50 | K51: 5 | L51: =K51*J51 -> 250
B52: 1184 | D52: =vlookup($C52,CSDL!$A:$E,2,0) -> #N/A | E52: =vlookup($C52,CSDL!$A:$E,3,0) -> #N/A | F52: =vlookup($C52,CSDL!$A:$E,4,0) -> #N/A | G52: =vlookup($C52,CSDL!$A:$E,5,0) -> #N/A | I52: Về nhà | J52: 50 | K52: 1 | L52: =K52*J52 -> 50
D53: khách lẻ | E53: =vlookup($C53,CSDL!$A:$E,3,0) -> #N/A | F53: =vlookup($C53,CSDL!$A:$E,4,0) -> #N/A | G53: =vlookup($C53,CSDL!$A:$E,5,0) -> #N/A | I53: Petshop | J53: 70 | K53: 1 | L53: =K53*J53 -> 70 | M53: 70 | N53: CK petshop thầy | O53: 5/11 - Momo
B54: 1185 | D54: Chị Thúy | E54: =vlookup($C54,CSDL!$A:$E,3,0) -> #N/A | F54: =vlookup($C54,CSDL!$A:$E,4,0) -> #N/A | G54: =vlookup($C54,CSDL!$A:$E,5,0) -> #N/A | I54: Chích thuốc nhỏ | J54: 150 | K54: 1 | L54: =K54*J54 -> 150 | M54: 150 | N54: Trà
D55: khách lẻ | E55: =vlookup($C55,CSDL!$A:$E,3,0) -> #N/A | F55: =vlookup($C55,CSDL!$A:$E,4,0) -> #N/A | G55: =vlookup($C55,CSDL!$A:$E,5,0) -> #N/A | I55: Khám lâm sàng | J55: 50 | K55: 1 | L55: =K55*J55 -> 50 | M55: 50 | N55: Ánh
D56: khách lẻ | E56: =vlookup($C56,CSDL!$A:$E,3,0) -> #N/A | F56: =vlookup($C56,CSDL!$A:$E,4,0) -> #N/A | G56: =vlookup($C56,CSDL!$A:$E,5,0) -> #N/A | I56: Thuốc bán | J56: 25 | K56: 14 | L56: =K56*J56 -> 350 | M56: 350 | N56: CK thầy | O56: 5/11 - Truong Ngoc My Dung ct
B57: 1186 | C57: 0931 941 343 | D57: =vlookup($C57,CSDL!$A:$E,2,0) -> Minh Châu | E57: =vlookup($C57,CSDL!$A:$E,3,0) -> 16 k78 Phạm Thị Liên | F57: =vlookup($C57,CSDL!$A:$E,4,0) -> chó | G57: Gấu | I57: Vaccine 7b chó | J57: 180 | K57: 1 | L57: =K57*J57 -> 180 | M57: 280 | N57: CK thầy | O57: 295k - 5/11 - Tran Thi Minh Chau ct
B58: 1186 | D58: =vlookup($C58,CSDL!$A:$E,2,0) -> #N/A | E58: =vlookup($C58,CSDL!$A:$E,3,0) -> #N/A | F58: =vlookup($C58,CSDL!$A:$E,4,0) -> #N/A | G58: =vlookup($C58,CSDL!$A:$E,5,0) -> #N/A | I58: Vaccine Dại | J58: 100 | K58: 1 | L58: =K58*J58 -> 100 | M58: 15 | N58: CK petshop thầy
B59: 1186 | I59: Petshop | J59: 15 | K59: 1 | L59: =K59*J59 -> 15
D60: khách lẻ | E60: =vlookup($C60,CSDL!$A:$E,3,0) -> #N/A | F60: =vlookup($C60,CSDL!$A:$E,4,0) -> #N/A | G60: =vlookup($C60,CSDL!$A:$E,5,0) -> #N/A | I60: Thuốc bán | J60: 35 | K60: 14 | L60: =K60*J60 -> 490 | M60: 490 | N60: CK thầy | O60: 5/11 - Pham Thi Hoang Anh ct
B61: 1187 | C61: 0935 291 288 | D61: =vlookup($C61,CSDL!$A:$E,2,0) -> anh Hoàn | E61: =vlookup($C61,CSDL!$A:$E,3,0) -> 170 Lý Nam Đế | F61: =vlookup($C61,CSDL!$A:$E,4,0) -> chó | G61: Đốm | I61: Vaccine 7b chó | J61: 160 | K61: 1 | L61: =K61*J61 -> 160 | M61: 160 | N61: CK thầy | O61: 5/11 - vaccine cho Dom
A62: 45967 | D62: khách lẻ | E62: =vlookup($C62,CSDL!$A:$E,3,0) -> #N/A | F62: =vlookup($C62,CSDL!$A:$E,4,0) -> #N/A | G62: =vlookup($C62,CSDL!$A:$E,5,0) -> #N/A | I62: Petshop | J62: 80 | K62: 1 | L62: =K62*J62 -> 80 | M62: 80 | N62: CK petshop thầy | O62: 6/11 - Ho Vu Nhat ct
D63: khách lẻ | E63: =vlookup($C63,CSDL!$A:$E,3,0) -> #N/A | F63: =vlookup($C63,CSDL!$A:$E,4,0) -> #N/A | G63: =vlookup($C63,CSDL!$A:$E,5,0) -> #N/A | I63: Tẩy giun nhỏ | J63: 40 | K63: 1 | L63: =K63*J63 -> 40 | M63: 40 | N63: Tuấn
D64: khách lẻ | E64: =vlookup($C64,CSDL!$A:$E,3,0) -> #N/A | F64: =vlookup($C64,CSDL!$A:$E,4,0) -> #N/A | G64: =vlookup($C64,CSDL!$A:$E,5,0) -> #N/A | I64: Tẩy giun nhỏ | J64: 20 | K64: 1 | L64: =K64*J64 -> 20 | M64: 20 | N64: Ánh
D65: khách lẻ | E65: =vlookup($C65,CSDL!$A:$E,3,0) -> #N/A | F65: =vlookup($C65,CSDL!$A:$E,4,0) -> #N/A | G65: =vlookup($C65,CSDL!$A:$E,5,0) -> #N/A | I65: Chích thuốc nhỏ | J65: 150 | K65: 1 | L65: =K65*J65 -> 150 | M65: 150 | N65: CK thầy | O65: 6/11 - Nguyen Thi Diem Thuy ct
B66: 1188 | C66: 0779 434 164 | D66: =vlookup($C66,CSDL!$A:$E,2,0) -> Chị Thùy TRang | E66: =vlookup($C66,CSDL!$A:$E,3,0) -> Hồ VĂn Hiển | F66: =vlookup($C66,CSDL!$A:$E,4,0) -> CHó | G66: =vlookup($C66,CSDL!$A:$E,5,0) -> Đô | I66: PT hoạn chó nhỏ | J66: 400 | K66: 1 | L66: =K66*J66 -> 400 | M66: 670 | N66: CK thầy | O66: 21/11 -Nguyen Thi Diem Thuy ct
B67: 1188 | D67: =vlookup($C67,CSDL!$A:$E,2,0) -> #N/A | E67: =vlookup($C67,CSDL!$A:$E,3,0) -> #N/A | F67: =vlookup($C67,CSDL!$A:$E,4,0) -> #N/A | G67: =vlookup($C67,CSDL!$A:$E,5,0) -> #N/A | I67: Thuốc bán | J67: 100 | K67: 1 | L67: =K67*J67 -> 100
B68: 1188 | D68: =vlookup($C68,CSDL!$A:$E,2,0) -> #N/A | E68: =vlookup($C68,CSDL!$A:$E,3,0) -> #N/A | F68: =vlookup($C68,CSDL!$A:$E,4,0) -> #N/A | G68: =vlookup($C68,CSDL!$A:$E,5,0) -> #N/A | I68: Tắm chó nhỏ | J68: 100 | K68: 1 | L68: =K68*J68 -> 100
B69: 1189 | C69: 0935 260 770 | D69: =vlookup($C69,CSDL!$A:$E,2,0) -> Chị Ngọc | E69: =vlookup($C69,CSDL!$A:$E,3,0) | F69: =vlookup($C69,CSDL!$A:$E,4,0) -> Mèo | G69: =vlookup($C69,CSDL!$A:$E,5,0) -> Amy | I69: Vaccine mèo 4b | J69: 280 | K69: 1 | L69: =K69*J69 -> 280 | M69: 280 | N69: Ánh
A70: 45968 | D70: khách lẻ | E70: =vlookup($C70,CSDL!$A:$E,3,0) -> #N/A | F70: =vlookup($C70,CSDL!$A:$E,4,0) -> #N/A | G70: =vlookup($C70,CSDL!$A:$E,5,0) -> #N/A | I70: Men tiêu hoá | J70: 15 | K70: 1 | L70: =K70*J70 -> 15 | M70: 15 | N70: CK thầy | O70: 7/11 - Tong Thi Thuyen ct
B71: 1190 | C71: 0941 344 265 | D71: =vlookup($C71,CSDL!$A:$E,2,0) -> Dì Minh | E71: =vlookup($C71,CSDL!$A:$E,3,0) -> 55/4 Vạn Xuân | F71: =vlookup($C71,CSDL!$A:$E,4,0) -> chó | G71: =vlookup($C71,CSDL!$A:$E,5,0) -> Ky | I71: Lưu trú nhỏ | J71: 180 | K71: 3 | L71: =K71*J71 -> 540 | M71: 200 | N71: CK thầy | O71: 7/11 - Truong DInh Thinh ct
B72: 1190 | D72: =vlookup($C72,CSDL!$A:$E,2,0) -> #N/A | E72: =vlookup($C72,CSDL!$A:$E,3,0) -> #N/A | F72: =vlookup($C72,CSDL!$A:$E,4,0) -> #N/A | G72: =vlookup($C72,CSDL!$A:$E,5,0) -> #N/A | I72: Chích thuốc nhỏ | J72: 100 | K72: 1 | L72: =K72*J72 -> 100 | M72: 440 | N72: Tuấn
D73: khách lẻ | E73: =vlookup($C73,CSDL!$A:$E,3,0) -> #N/A | F73: =vlookup($C73,CSDL!$A:$E,4,0) -> #N/A | G73: =vlookup($C73,CSDL!$A:$E,5,0) -> #N/A | I73: Vaccine 7b chó | J73: 180 | K73: 1 | L73: =K73*J73 -> 180 | M73: 180 | N73: CK thầy | O73: 7/11 - Duong Thien Phuc ct
B74: 1191 | C74: 0327 745 030 | D74: =vlookup($C74,CSDL!$A:$E,2,0) -> Chị Hương Giang (Na) | E74: =vlookup($C74,CSDL!$A:$E,3,0) -> Nguyễn Phúc Chu | F74: =vlookup($C74,CSDL!$A:$E,4,0) -> Mèo | G74: =vlookup($C74,CSDL!$A:$E,5,0) -> Vàng | I74: FPV- | J74: 150 | K74: 1 | L74: =K74*J74 -> 150 | M74: 250 | N74: CK thầy | O74: 550k - 7/11 - Huong Giang
B75: 1191 | D75: =vlookup($C75,CSDL!$A:$E,2,0) -> #N/A | E75: =vlookup($C75,CSDL!$A:$E,3,0) -> #N/A | F75: =vlookup($C75,CSDL!$A:$E,4,0) -> #N/A | G75: =vlookup($C75,CSDL!$A:$E,5,0) -> #N/A | I75: Chích thuốc nhỏ | J75: 100 | K75: 3 | L75: =K75*J75 -> 300 | M75: 300 | N75: CK petshop thầy
B76: 1191 | D76: =vlookup($C76,CSDL!$A:$E,2,0) -> #N/A | E76: =vlookup($C76,CSDL!$A:$E,3,0) -> #N/A | F76: =vlookup($C76,CSDL!$A:$E,4,0) -> #N/A | G76: =vlookup($C76,CSDL!$A:$E,5,0) -> #N/A | I76: Petshop | J76: 350 | K76: 1 | L76: =K76*J76 -> 350 | M76: 100 | N76: CK thầy | O76: 150k - 8/11 - Huong Giang
B77: 1191 | D77: =vlookup($C77,CSDL!$A:$E,2,0) -> #N/A | E77: =vlookup($C77,CSDL!$A:$E,3,0) -> #N/A | F77: =vlookup($C77,CSDL!$A:$E,4,0) -> #N/A | G77: =vlookup($C77,CSDL!$A:$E,5,0) -> #N/A | L77: =K77*J77 -> 0 | M77: 50 | N77: CK petshop thầy
B78: 1191 | M78: 100 | N78: CK thầy | O78: 9/11 - Le Thi Huong Giang ct mèo
A79: 45969 | D79: khách lẻ | E79: =vlookup($C79,CSDL!$A:$E,3,0) -> #N/A | F79: =vlookup($C79,CSDL!$A:$E,4,0) -> #N/A | G79: =vlookup($C79,CSDL!$A:$E,5,0) -> #N/A | I79: Petshop | J79: 60 | K79: 1 | L79: =K79*J79 -> 60 | M79: 60 | N79: CK thầy | O79: 8/11 - Ho Nhat Ly ct
D80: khách lẻ | E80: =vlookup($C80,CSDL!$A:$E,3,0) -> #N/A | F80: =vlookup($C80,CSDL!$A:$E,4,0) -> #N/A | G80: =vlookup($C80,CSDL!$A:$E,5,0) -> #N/A | I80: Thuốc bán | J80: 60 | K80: 1 | L80: =K80*J80 -> 60 | M80: 60 | N80: Trà
B81: 1192 | D81: Peter Dương | E81: =vlookup($C81,CSDL!$A:$E,3,0) -> #N/A | F81: =vlookup($C81,CSDL!$A:$E,4,0) -> #N/A | G81: =vlookup($C81,CSDL!$A:$E,5,0) -> #N/A | I81: Thuốc bán | J81: 35 | K81: 14 | L81: =K81*J81 -> 490 | M81: 740 | N81: CK thầy | O81: 940 k - Duong Thien Phuc ct
B82: 1192 | D82: =vlookup($C82,CSDL!$A:$E,2,0) -> #N/A | E82: =vlookup($C82,CSDL!$A:$E,3,0) -> #N/A | F82: =vlookup($C82,CSDL!$A:$E,4,0) -> #N/A | G82: =vlookup($C82,CSDL!$A:$E,5,0) -> #N/A | I82: Thuốc tắm nấm nhỏ | J82: 250 | K82: 1 | L82: =K82*J82 -> 250 | M82: 200 | N82: CK petshop thầy
B83: 1192 | D83: =vlookup($C83,CSDL!$A:$E,2,0) -> #N/A | E83: =vlookup($C83,CSDL!$A:$E,3,0) -> #N/A | F83: =vlookup($C83,CSDL!$A:$E,4,0) -> #N/A | G83: =vlookup($C83,CSDL!$A:$E,5,0) -> #N/A | I83: Petshop | J83: 200 | K83: 1 | L83: =K83*J83 -> 200
D84: khách lẻ | E84: =vlookup($C84,CSDL!$A:$E,3,0) -> #N/A | F84: =vlookup($C84,CSDL!$A:$E,4,0) -> #N/A | G84: =vlookup($C84,CSDL!$A:$E,5,0) -> #N/A | I84: Tẩy giun nhỏ | J84: 20 | K84: 1 | L84: =K84*J84 -> 20 | M84: 20 | N84: Trà
D85: khách lẻ | E85: =vlookup($C85,CSDL!$A:$E,3,0) -> #N/A | F85: =vlookup($C85,CSDL!$A:$E,4,0) -> #N/A | G85: =vlookup($C85,CSDL!$A:$E,5,0) -> #N/A | I85: Tẩy giun nhỏ | L85: =K85*J85 -> 0
B86: 1193 | C86: 0906 566 226 | D86: =vlookup($C86,CSDL!$A:$E,2,0) -> Chị nhi | E86: =vlookup($C86,CSDL!$A:$E,3,0) -> 203 Chi Lăng | F86: =vlookup($C86,CSDL!$A:$E,4,0) -> Mèo | G86: =vlookup($C86,CSDL!$A:$E,5,0) | I86: Lưu trú nhỏ | J86: 100 | K86: 2 | L86: =K86*J86 -> 200 | M86: 200 | N86: CK thầy | O86: 8/11 -??
B87: 1194 | C87: 0905 109 559 | D87: =vlookup($C87,CSDL!$A:$E,2,0) -> Chị yến | E87: =vlookup($C87,CSDL!$A:$E,3,0) -> Nguyễn Văn Đào | F87: Mèo | I87: Siêu âm | J87: 100 | K87: 1 | L87: =K87*J87 -> 100 | M87: 350 | N87: CK thầy | O87: 8/11 - Yen ct
B88: 1194 | D88: =vlookup($C88,CSDL!$A:$E,2,0) -> #N/A | E88: =vlookup($C88,CSDL!$A:$E,3,0) -> #N/A | F88: =vlookup($C88,CSDL!$A:$E,4,0) -> #N/A | G88: =vlookup($C88,CSDL!$A:$E,5,0) -> #N/A | I88: Chích thuốc nhỏ | J88: 100 | K88: 1 | L88: =K88*J88 -> 100
B89: 1194 | D89: =vlookup($C89,CSDL!$A:$E,2,0) -> #N/A | E89: =vlookup($C89,CSDL!$A:$E,3,0) -> #N/A | F89: =vlookup($C89,CSDL!$A:$E,4,0) -> #N/A | G89: =vlookup($C89,CSDL!$A:$E,5,0) -> #N/A | I89: FPV- | J89: 150 | K89: 1 | L89: =K89*J89 -> 150
D90: khách lẻ | I90: Petshop | J90: 30 | K90: 1 | L90: =K90*J90 -> 30 | M90: 30 | N90: CK petshop thầy | O90: 8/11 - Nguyen Van Hieu ct
A91: Tuần 1 | Q91: =sum(M4:M91) -> 25820
A92: 45970 | B92: 1195 | C92: 0915 061 282 | D92: =vlookup($C92,CSDL!$A:$E,2,0) -> Anh Trung- c Hà Chung | E92: =vlookup($C92,CSDL!$A:$E,3,0) -> 25/250 Phan Bội Châu | F92: =vlookup($C92,CSDL!$A:$E,4,0) -> chó | G92: =vlookup($C92,CSDL!$A:$E,5,0) -> bà điên | I92: Siêu âm | J92: 0 | K92: 1 | L92: =K92*J92 -> 0 | M92: 0 | N92: Tuấn
B93: 1196 | C93: 0388 119 098 | D93: =vlookup($C93,CSDL!$A:$E,2,0) -> Chị Thu Hà | E93: =vlookup($C93,CSDL!$A:$E,3,0) | F93: =vlookup($C93,CSDL!$A:$E,4,0) -> Chó | G93: =vlookup($C93,CSDL!$A:$E,5,0) -> Bắp/Bầu/Bí | H93: 10 | I93: CBC | J93: 150 | K93: 3 | L93: =K93*J93 -> 450 | M93: 1000 | N93: CK thầy | O93: 9/11 - Nguyen Thu Ha ct
B94: 1196 | D94: =vlookup($C94,CSDL!$A:$E,2,0) -> #N/A | E94: =vlookup($C94,CSDL!$A:$E,3,0) -> #N/A | F94: =vlookup($C94,CSDL!$A:$E,4,0) -> #N/A | G94: =vlookup($C94,CSDL!$A:$E,5,0) -> #N/A | I94: Lưu điều trị nhỏ | J94: 510 | K94: 9 | L94: =K94*J94 -> 4590 | M94: 10900 | N94: CK thầy | O94: 19/11 - Nguyen Thu Ha ct
B95: 1196 | D95: =vlookup($C95,CSDL!$A:$E,2,0) -> #N/A | E95: =vlookup($C95,CSDL!$A:$E,3,0) -> #N/A | F95: =vlookup($C95,CSDL!$A:$E,4,0) -> #N/A | G95: =vlookup($C95,CSDL!$A:$E,5,0) -> #N/A | I95: Tẩy giun nhỏ | J95: 0 | K95: 1 | L95: =K95*J95 -> 0
B96: 1196 | D96: =vlookup($C96,CSDL!$A:$E,2,0) -> #N/A | E96: =vlookup($C96,CSDL!$A:$E,3,0) -> #N/A | F96: =vlookup($C96,CSDL!$A:$E,4,0) -> #N/A | G96: =vlookup($C96,CSDL!$A:$E,5,0) -> #N/A | I96: Tắm chó nhỏ | J96: 0 | K96: 1 | L96: =K96*J96 -> 0
B97: 1196 | D97: =vlookup($C97,CSDL!$A:$E,2,0) -> #N/A | E97: =vlookup($C97,CSDL!$A:$E,3,0) -> #N/A | F97: =vlookup($C97,CSDL!$A:$E,4,0) -> #N/A | G97: =vlookup($C97,CSDL!$A:$E,5,0) -> #N/A | I97: Chích KST máu | J97: 200 | K97: 6 | L97: =K97*J97 -> 1200
B98: 1196 | D98: =vlookup($C98,CSDL!$A:$E,2,0) -> #N/A | E98: =vlookup($C98,CSDL!$A:$E,3,0) -> #N/A | F98: =vlookup($C98,CSDL!$A:$E,4,0) -> #N/A | G98: =vlookup($C98,CSDL!$A:$E,5,0) -> #N/A | I98: Thuốc bán | J98: 50 | K98: =18*3 -> 54 | L98: =K98*J98 -> 2700
B99: 1196 | D99: =vlookup($C99,CSDL!$A:$E,2,0) -> #N/A | E99: =vlookup($C99,CSDL!$A:$E,3,0) -> #N/A | F99: =vlookup($C99,CSDL!$A:$E,4,0) -> #N/A | G99: =vlookup($C99,CSDL!$A:$E,5,0) -> #N/A | I99: Diệt ve Simparica 20,1-40 | J99: 350 | K99: 7 | L99: =K99*J99 -> 2450
B100: 1197 | C100: 0945 714 323 | D100: =vlookup($C100,CSDL!$A:$E,2,0) -> anh Duy | E100: =vlookup($C100,CSDL!$A:$E,3,0) -> 61 Phạm Thị Liên | F100: =vlookup($C100,CSDL!$A:$E,4,0) -> Mèo | G100: =vlookup($C100,CSDL!$A:$E,5,0) -> Tuyết | I100: PT hoạn mèo | J100: 500 | K100: 1 | L100: =K100*J100 -> 500 | M100: 600 | N100: CK thầy | O100: 640k - 9/11 - Hoang Huyen ct
B101: 1197 | D101: =vlookup($C101,CSDL!$A:$E,2,0) -> #N/A | E101: =vlookup($C101,CSDL!$A:$E,3,0) -> #N/A | F101: =vlookup($C101,CSDL!$A:$E,4,0) -> #N/A | G101: =vlookup($C101,CSDL!$A:$E,5,0) -> #N/A | I101: Thuốc bán | J101: 100 | K101: 1 | L101: =K101*J101 -> 100 | M101: 40 | N101: CK petshop thầy
...

Sheet CSDL
A1: =IFERROR(__xludf.DUMMYFUNCTION("importrange(""https://docs.google.com/spreadsheets/d/1s8yEsKu3EMT_o1gfopKM8FAT3y4j4rENhR6GH49MzHc/edit#gid=0"",""CSDL khach hang!A:E"")"),"")
A3: =IFERROR(__xludf.DUMMYFUNCTION("""COMPUTED_VALUE"""),"0914 125 773") -> 0914 125 773 | B3: =IFERROR(__xludf.DUMMYFUNCTION("""COMPUTED_VALUE"""),"Bác Quân") -> Bác Quân | C3: =IFERROR(__xludf.DUMMYFUNCTION("""COMPUTED_VALUE"""),"ngõ 69 k131 Trần Phú") -> ngõ 69 k131 Trần Phú | D3: =IFERROR(__xludf.DUMMYFUNCTION("""COMPUTED_VALUE"""),"chó") -> chó | E3: =IFERROR(__xludf.DUMMYFUNCTION("""COMPUTED_VALUE"""),"sóc") -> sóc
A4: =IFERROR(__xludf.DUMMYFUNCTION("""COMPUTED_VALUE"""),"0368 142 234") -> 0368 142 234 | B4: =IFERROR(__xludf.DUMMYFUNCTION("""COMPUTED_VALUE"""),"Chị Yến") -> Chị Yến | C4: =IFERROR(__xludf.DUMMYFUNCTION("""COMPUTED_VALUE"""),"C 1 chung cư Trường An") -> C 1 chung cư Trường An | D4: =IFERROR(__xludf.DUMMYFUNCTION("""COMPUTED_VALUE"""),"mèo") -> mèo
A5: =IFERROR(__xludf.DUMMYFUNCTION("""COMPUTED_VALUE"""),"0829 448 009") -> 0829 448 009 | B5: =IFERROR(__xludf.DUMMYFUNCTION("""COMPUTED_VALUE"""),"anh Huy") -> anh Huy | C5: =IFERROR(__xludf.DUMMYFUNCTION("""COMPUTED_VALUE"""),"30/6 Tôn Thất Tùng") -> 30/6 Tôn Thất Tùng | D5: =IFERROR(__xludf.DUMMYFUNCTION("""COMPUTED_VALUE"""),"mèo") -> mèo
A6: =IFERROR(__xludf.DUMMYFUNCTION("""COMPUTED_VALUE"""),"0819 038 058") -> 0819 038 058 | B6: =IFERROR(__xludf.DUMMYFUNCTION("""COMPUTED_VALUE"""),"em Bình") -> em Bình | D6: =IFERROR(__xludf.DUMMYFUNCTION("""COMPUTED_VALUE"""),"mèo") -> mèo | E6: =IFERROR(__xludf.DUMMYFUNCTION("""COMPUTED_VALUE"""),"bu") -> bu
A7: =IFERROR(__xludf.DUMMYFUNCTION("""COMPUTED_VALUE"""),"0775 527 554") -> 0775 527 554 | B7: =IFERROR(__xludf.DUMMYFUNCTION("""COMPUTED_VALUE"""),"chị Thúy") -> chị Thúy | C7: =IFERROR(__xludf.DUMMYFUNCTION("""COMPUTED_VALUE"""),"9/62 Nguyễn gia Thiều") -> 9/62 Nguyễn gia Thiều | D7: =IFERROR(__xludf.DUMMYFUNCTION("""COMPUTED_VALUE"""),"chó") -> chó | E7: =IFERROR(__xludf.DUMMYFUNCTION("""COMPUTED_VALUE"""),"lu") -> lu
A8: =IFERROR(__xludf.DUMMYFUNCTION("""COMPUTED_VALUE"""),"0973 067 961") -> 0973 067 961 | B8: =IFERROR(__xludf.DUMMYFUNCTION("""COMPUTED_VALUE"""),"Em Hoàng Lê Quân") -> Em Hoàng Lê Quân | C8: =IFERROR(__xludf.DUMMYFUNCTION("""COMPUTED_VALUE"""),"198 Phan chu Trinh") -> 198 Phan chu Trinh | D8: =IFERROR(__xludf.DUMMYFUNCTION("""COMPUTED_VALUE"""),"mèo") -> mèo | E8: =IFERROR(__xludf.DUMMYFUNCTION("""COMPUTED_VALUE"""),"ú") -> ú
A9: =IFERROR(__xludf.DUMMYFUNCTION("""COMPUTED_VALUE"""),"0905 817 329") -> 0905 817 329 | B9: =IFERROR(__xludf.DUMMYFUNCTION("""COMPUTED_VALUE"""),"Anh Phúc") -> Anh Phúc | C9: =IFERROR(__xludf.DUMMYFUNCTION("""COMPUTED_VALUE"""),"98 Minh Mạng") -> 98 Minh Mạng | D9: =IFERROR(__xludf.DUMMYFUNCTION("""COMPUTED_VALUE"""),"chó") -> chó | E9: =IFERROR(__xludf.DUMMYFUNCTION("""COMPUTED_VALUE"""),"nâu") -> nâu
A10: =IFERROR(__xludf.DUMMYFUNCTION("""COMPUTED_VALUE"""),"0772 407 863") -> 0772 407 863 | B10: =IFERROR(__xludf.DUMMYFUNCTION("""COMPUTED_VALUE"""),"Anh Hoàng") -> Anh Hoàng | D10: =IFERROR(__xludf.DUMMYFUNCTION("""COMPUTED_VALUE"""),"chó") -> chó | E10: =IFERROR(__xludf.DUMMYFUNCTION("""COMPUTED_VALUE"""),"phú quốc lai") -> phú quốc lai
A11: =IFERROR(__xludf.DUMMYFUNCTION("""COMPUTED_VALUE"""),"0385 748 754") -> 0385 748 754 | B11: =IFERROR(__xludf.DUMMYFUNCTION("""COMPUTED_VALUE"""),"Cô Dung") -> Cô Dung | C11: =IFERROR(__xludf.DUMMYFUNCTION("""COMPUTED_VALUE"""),"Trần phú") -> Trần phú | D11: =IFERROR(__xludf.DUMMYFUNCTION("""COMPUTED_VALUE"""),"chó") -> chó | E11: =IFERROR(__xludf.DUMMYFUNCTION("""COMPUTED_VALUE"""),"lisa") -> lisa
A12: =IFERROR(__xludf.DUMMYFUNCTION("""COMPUTED_VALUE"""),"0966 857 262") -> 0966 857 262 | B12: =IFERROR(__xludf.DUMMYFUNCTION("""COMPUTED_VALUE"""),"Chị Na") -> Chị Na | C12: =IFERROR(__xludf.DUMMYFUNCTION("""COMPUTED_VALUE"""),"k131 Trần Phú") -> k131 Trần Phú | D12: =IFERROR(__xludf.DUMMYFUNCTION("""COMPUTED_VALUE"""),"mèo") -> mèo | E12: =IFERROR(__xludf.DUMMYFUNCTION("""COMPUTED_VALUE"""),"gạo") -> gạo
A13: =IFERROR(__xludf.DUMMYFUNCTION("""COMPUTED_VALUE"""),"0708 730 799") -> 0708 730 799 | B13: =IFERROR(__xludf.DUMMYFUNCTION("""COMPUTED_VALUE"""),"em Nhung") -> em Nhung | D13: =IFERROR(__xludf.DUMMYFUNCTION("""COMPUTED_VALUE"""),"mèo") -> mèo | E13: =IFERROR(__xludf.DUMMYFUNCTION("""COMPUTED_VALUE"""),"tít") -> tít
A14: =IFERROR(__xludf.DUMMYFUNCTION("""COMPUTED_VALUE"""),"0985 511 469") -> 0985 511 469 | B14: =IFERROR(__xludf.DUMMYFUNCTION("""COMPUTED_VALUE"""),"chị Vy") -> chị Vy | C14: =IFERROR(__xludf.DUMMYFUNCTION("""COMPUTED_VALUE"""),"phong điền") -> phong điền | D14: =IFERROR(__xludf.DUMMYFUNCTION("""COMPUTED_VALUE"""),"chó") -> chó | E14: =IFERROR(__xludf.DUMMYFUNCTION("""COMPUTED_VALUE"""),"su") -> su
A15: =IFERROR(__xludf.DUMMYFUNCTION("""COMPUTED_VALUE"""),"0981 576 817") -> 0981 576 817 | B15: =IFERROR(__xludf.DUMMYFUNCTION("""COMPUTED_VALUE"""),"em Tuấn Anh") -> em Tuấn Anh | C15: =IFERROR(__xludf.DUMMYFUNCTION("""COMPUTED_VALUE"""),"63 xuân Diệu") -> 63 xuân Diệu | D15: =IFERROR(__xludf.DUMMYFUNCTION("""COMPUTED_VALUE"""),"mèo") -> mèo | E15: =IFERROR(__xludf.DUMMYFUNCTION("""COMPUTED_VALUE"""),"cơm") -> cơm
A16: =IFERROR(__xludf.DUMMYFUNCTION("""COMPUTED_VALUE"""),"0935 201 515") -> 0935 201 515 | B16: =IFERROR(__xludf.DUMMYFUNCTION("""COMPUTED_VALUE"""),"em Ngọc-con anh Mỹ") -> em Ngọc-con anh Mỹ | C16: =IFERROR(__xludf.DUMMYFUNCTION("""COMPUTED_VALUE"""),"vũ ngọc phan/nguyễn huệ") -> vũ ngọc phan/nguyễn huệ | D16: =IFERROR(__xludf.DUMMYFUNCTION("""COMPUTED_VALUE"""),"chó") -> chó | E16: =IFERROR(__xludf.DUMMYFUNCTION("""COMPUTED_VALUE"""),"đốm") -> đốm
A17: =IFERROR(__xludf.DUMMYFUNCTION("""COMPUTED_VALUE"""),"0395 530 843") -> 0395 530 843 | B17: =IFERROR(__xludf.DUMMYFUNCTION("""COMPUTED_VALUE"""),"Dì Trâm- bác Toàn ") -> Dì Trâm- bác Toàn | C17: =IFERROR(__xludf.DUMMYFUNCTION("""COMPUTED_VALUE"""),"8/16 Đoàn Hữu Trưng") -> 8/16 Đoàn Hữu Trưng | D17: =IFERROR(__xludf.DUMMYFUNCTION("""COMPUTED_VALUE"""),"mèo ") -> mèo | E17: =IFERROR(__xludf.DUMMYFUNCTION("""COMPUTED_VALUE"""),"bao/đùi gà") -> bao/đùi gà
A18: =IFERROR(__xludf.DUMMYFUNCTION("""COMPUTED_VALUE"""),"0393 221 804") -> 0393 221 804 | B18: =IFERROR(__xludf.DUMMYFUNCTION("""COMPUTED_VALUE"""),"em Mỹ Ngọc") -> em Mỹ Ngọc | C18: =IFERROR(__xludf.DUMMYFUNCTION("""COMPUTED_VALUE"""),"18/10 Nguyễn Trường Tộ") -> 18/10 Nguyễn Trường Tộ | D18: =IFERROR(__xludf.DUMMYFUNCTION("""COMPUTED_VALUE"""),"mèo") -> mèo | E18: =IFERROR(__xludf.DUMMYFUNCTION("""COMPUTED_VALUE"""),"chocolate") -> chocolate
A19: =IFERROR(__xludf.DUMMYFUNCTION("""COMPUTED_VALUE"""),"0795 326 380") -> 0795 326 380 | B19: =IFERROR(__xludf.DUMMYFUNCTION("""COMPUTED_VALUE"""),"em Hồ Thị Phương Thảo") -> em Hồ Thị Phương Thảo | C19: =IFERROR(__xludf.DUMMYFUNCTION("""COMPUTED_VALUE"""),"75 Hồ Đắc Di") -> 75 Hồ Đắc Di | D19: =IFERROR(__xludf.DUMMYFUNCTION("""COMPUTED_VALUE"""),"mèo") -> mèo | E19: =IFERROR(__xludf.DUMMYFUNCTION("""COMPUTED_VALUE"""),"Bạch Tuộc") -> Bạch Tuộc
A20: =IFERROR(__xludf.DUMMYFUNCTION("""COMPUTED_VALUE"""),"0367 150 406") -> 0367 150 406 | B20: =IFERROR(__xludf.DUMMYFUNCTION("""COMPUTED_VALUE"""),"Chú Dũng") -> Chú Dũng | C20: =IFERROR(__xludf.DUMMYFUNCTION("""COMPUTED_VALUE"""),"k227 Trần Phú") -> k227 Trần Phú | D20: =IFERROR(__xludf.DUMMYFUNCTION("""COMPUTED_VALUE"""),"chó") -> chó | E20: =IFERROR(__xludf.DUMMYFUNCTION("""COMPUTED_VALUE"""),"12kg") -> 12kg
A21: =IFERROR(__xludf.DUMMYFUNCTION("""COMPUTED_VALUE"""),"0915 061 282") -> 0915 061 282 | B21: =IFERROR(__xludf.DUMMYFUNCTION("""COMPUTED_VALUE"""),"Anh Trung- c Hà Chung") -> Anh Trung- c Hà Chung | C21: =IFERROR(__xludf.DUMMYFUNCTION("""COMPUTED_VALUE"""),"25/250 Phan Bội Châu") -> 25/250 Phan Bội Châu | D21: =IFERROR(__xludf.DUMMYFUNCTION("""COMPUTED_VALUE"""),"chó") -> chó | E21: =IFERROR(__xludf.DUMMYFUNCTION("""COMPUTED_VALUE"""),"bà điên") -> bà điên
A22: =IFERROR(__xludf.DUMMYFUNCTION("""COMPUTED_VALUE"""),"0914 219 823") -> 0914 219 823 | B22: =IFERROR(__xludf.DUMMYFUNCTION("""COMPUTED_VALUE"""),"Anh Huy") -> Anh Huy | C22: =IFERROR(__xludf.DUMMYFUNCTION("""COMPUTED_VALUE"""),"k1 Bảo Quốc") -> k1 Bảo Quốc | D22: =IFERROR(__xludf.DUMMYFUNCTION("""COMPUTED_VALUE"""),"vẹt") -> vẹt
A23: =IFERROR(__xludf.DUMMYFUNCTION("""COMPUTED_VALUE"""),"0343 787 737") -> 0343 787 737 | B23: =IFERROR(__xludf.DUMMYFUNCTION("""COMPUTED_VALUE"""),"Anh Tài") -> Anh Tài | C23: =IFERROR(__xludf.DUMMYFUNCTION("""COMPUTED_VALUE"""),"78B Phú Bài") -> 78B Phú Bài | D23: =IFERROR(__xludf.DUMMYFUNCTION("""COMPUTED_VALUE"""),"Mèo") -> Mèo
A24: =IFERROR(__xludf.DUMMYFUNCTION("""COMPUTED_VALUE"""),"0907 804 763") -> 0907 804 763 | B24: =IFERROR(__xludf.DUMMYFUNCTION("""COMPUTED_VALUE"""),"Anh Hồ Ngọc Tuấn ") -> Anh Hồ Ngọc Tuấn | C24: =IFERROR(__xludf.DUMMYFUNCTION("""COMPUTED_VALUE"""),"Vỹ Dạ") -> Vỹ Dạ | D24: =IFERROR(__xludf.DUMMYFUNCTION("""COMPUTED_VALUE"""),"chó") -> chó | E24: =IFERROR(__xludf.DUMMYFUNCTION("""COMPUTED_VALUE"""),"đậu hũ thúi") -> đậu hũ thúi
A25: =IFERROR(__xludf.DUMMYFUNCTION("""COMPUTED_VALUE"""),"0911 004 431") -> 0911 004 431 | B25: =IFERROR(__xludf.DUMMYFUNCTION("""COMPUTED_VALUE"""),"Em Lan Anh") -> Em Lan Anh | C25: =IFERROR(__xludf.DUMMYFUNCTION("""COMPUTED_VALUE"""),"k56 Đào Tấn") -> k56 Đào Tấn | D25: =IFERROR(__xludf.DUMMYFUNCTION("""COMPUTED_VALUE"""),"mèo") -> mèo
A26: =IFERROR(__xludf.DUMMYFUNCTION("""COMPUTED_VALUE"""),"0375 954 665") -> 0375 954 665 | B26: =IFERROR(__xludf.DUMMYFUNCTION("""COMPUTED_VALUE"""),"Anh Nghĩa") -> Anh Nghĩa | C26: =IFERROR(__xludf.DUMMYFUNCTION("""COMPUTED_VALUE"""),"193 Phan Đăng Lưu") -> 193 Phan Đăng Lưu | D26: =IFERROR(__xludf.DUMMYFUNCTION("""COMPUTED_VALUE"""),"chó") -> chó
A27: =IFERROR(__xludf.DUMMYFUNCTION("""COMPUTED_VALUE"""),"0914 145 264") -> 0914 145 264 | B27: =IFERROR(__xludf.DUMMYFUNCTION("""COMPUTED_VALUE"""),"Bác Quốc") -> Bác Quốc | C27: =IFERROR(__xludf.DUMMYFUNCTION("""COMPUTED_VALUE"""),"29/2/44 lê Ngô Cát") -> 29/2/44 lê Ngô Cát | D27: =IFERROR(__xludf.DUMMYFUNCTION("""COMPUTED_VALUE"""),"chó") -> chó
A28: =IFERROR(__xludf.DUMMYFUNCTION("""COMPUTED_VALUE"""),"0865 447 575") -> 0865 447 575 | B28: =IFERROR(__xludf.DUMMYFUNCTION("""COMPUTED_VALUE"""),"anh phan bá Đức") -> anh phan bá Đức | C28: =IFERROR(__xludf.DUMMYFUNCTION("""COMPUTED_VALUE"""),"29 hẻm 2 k44 lê ngô cát") -> 29 hẻm 2 k44 lê ngô cát | D28: =IFERROR(__xludf.DUMMYFUNCTION("""COMPUTED_VALUE"""),"chó") -> chó
A29: =IFERROR(__xludf.DUMMYFUNCTION("""COMPUTED_VALUE"""),"0386 164 608") -> 0386 164 608 | B29: =IFERROR(__xludf.DUMMYFUNCTION("""COMPUTED_VALUE"""),"Em Thiện Tâm") -> Em Thiện Tâm | C29: =IFERROR(__xludf.DUMMYFUNCTION("""COMPUTED_VALUE"""),"83k131 Trần Phú") -> 83k131 Trần Phú | D29: =IFERROR(__xludf.DUMMYFUNCTION("""COMPUTED_VALUE"""),"mèo") -> mèo | E29: =IFERROR(__xludf.DUMMYFUNCTION("""COMPUTED_VALUE"""),"bảnh") -> bảnh
A30: =IFERROR(__xludf.DUMMYFUNCTION("""COMPUTED_VALUE"""),"0374 558 914") -> 0374 558 914 | B30: =IFERROR(__xludf.DUMMYFUNCTION("""COMPUTED_VALUE"""),"Em Uyên Phương") -> Em Uyên Phương | C30: =IFERROR(__xludf.DUMMYFUNCTION("""COMPUTED_VALUE"""),"16 Dương Xuân Hạ") -> 16 Dương Xuân Hạ | D30: =IFERROR(__xludf.DUMMYFUNCTION("""COMPUTED_VALUE"""),"mèo") -> mèo | E30: =IFERROR(__xludf.DUMMYFUNCTION("""COMPUTED_VALUE"""),"mèo") -> mèo
A31: =IFERROR(__xludf.DUMMYFUNCTION("""COMPUTED_VALUE"""),"0837 052 752") -> 0837 052 752 | B31: =IFERROR(__xludf.DUMMYFUNCTION("""COMPUTED_VALUE"""),"em Quỳnh") -> em Quỳnh | C31: =IFERROR(__xludf.DUMMYFUNCTION("""COMPUTED_VALUE"""),"9c k131 Trần Phú") -> 9c k131 Trần Phú | D31: =IFERROR(__xludf.DUMMYFUNCTION("""COMPUTED_VALUE"""),"mèo") -> mèo | E31: =IFERROR(__xludf.DUMMYFUNCTION("""COMPUTED_VALUE"""),"tèo") -> tèo
A32: =IFERROR(__xludf.DUMMYFUNCTION("""COMPUTED_VALUE"""),"0932 412 231") -> 0932 412 231 | B32: =IFERROR(__xludf.DUMMYFUNCTION("""COMPUTED_VALUE"""),"Anh Huy") -> Anh Huy | C32: =IFERROR(__xludf.DUMMYFUNCTION("""COMPUTED_VALUE"""),"đh kinh tế huế") -> đh kinh tế huế | D32: =IFERROR(__xludf.DUMMYFUNCTION("""COMPUTED_VALUE"""),"chó") -> chó | E32: =IFERROR(__xludf.DUMMYFUNCTION("""COMPUTED_VALUE"""),"lượm") -> lượm
A33: =IFERROR(__xludf.DUMMYFUNCTION("""COMPUTED_VALUE"""),"0941 658 067") -> 0941 658 067 | B33: =IFERROR(__xludf.DUMMYFUNCTION("""COMPUTED_VALUE"""),"chị Lê Trang Nguyên") -> chị Lê Trang Nguyên | C33: =IFERROR(__xludf.DUMMYFUNCTION("""COMPUTED_VALUE"""),"52 Hàm Nghi") -> 52 Hàm Nghi | D33: =IFERROR(__xludf.DUMMYFUNCTION("""COMPUTED_VALUE"""),"chó") -> chó | E33: =IFERROR(__xludf.DUMMYFUNCTION("""COMPUTED_VALUE"""),"mỡ") -> mỡ
A34: =IFERROR(__xludf.DUMMYFUNCTION("""COMPUTED_VALUE"""),"0776 907 777") -> 0776 907 777 | B34: =IFERROR(__xludf.DUMMYFUNCTION("""COMPUTED_VALUE"""),"Chị Thủy") -> Chị Thủy | C34: =IFERROR(__xludf.DUMMYFUNCTION("""COMPUTED_VALUE"""),"117 Lương Nhữ hộc") -> 117 Lương Nhữ hộc | D34: =IFERROR(__xludf.DUMMYFUNCTION("""COMPUTED_VALUE"""),"mèo ") -> mèo
A35: =IFERROR(__xludf.DUMMYFUNCTION("""COMPUTED_VALUE"""),"0794 185 492") -> 0794 185 492 | B35: =IFERROR(__xludf.DUMMYFUNCTION("""COMPUTED_VALUE"""),"em Kim Anh") -> em Kim Anh | C35: =IFERROR(__xludf.DUMMYFUNCTION("""COMPUTED_VALUE"""),"Thiên Thai") -> Thiên Thai | D35: =IFERROR(__xludf.DUMMYFUNCTION("""COMPUTED_VALUE"""),"chó") -> chó | E35: =IFERROR(__xludf.DUMMYFUNCTION("""COMPUTED_VALUE"""),"bu bu") -> bu bu
A36: =IFERROR(__xludf.DUMMYFUNCTION("""COMPUTED_VALUE"""),"0914 614 253") -> 0914 614 253 | B36: =IFERROR(__xludf.DUMMYFUNCTION("""COMPUTED_VALUE"""),"Dì Kim Soa") -> Dì Kim Soa | C36: =IFERROR(__xludf.DUMMYFUNCTION("""COMPUTED_VALUE"""),"52a lê công hành") -> 52a lê công hành | D36: =IFERROR(__xludf.DUMMYFUNCTION("""COMPUTED_VALUE"""),"mèo") -> mèo
A37: =IFERROR(__xludf.DUMMYFUNCTION("""COMPUTED_VALUE"""),"0763 697 522") -> 0763 697 522 | B37: =IFERROR(__xludf.DUMMYFUNCTION("""COMPUTED_VALUE"""),"em Xuân Vy") -> em Xuân Vy | C37: =IFERROR(__xludf.DUMMYFUNCTION("""COMPUTED_VALUE"""),"32/69 Đặng Huy Trứ") -> 32/69 Đặng Huy Trứ | D37: =IFERROR(__xludf.DUMMYFUNCTION("""COMPUTED_VALUE"""),"mèo") -> mèo
A38: =IFERROR(__xludf.DUMMYFUNCTION("""COMPUTED_VALUE"""),"0394 533 206") -> 0394 533 206 | B38: =IFERROR(__xludf.DUMMYFUNCTION("""COMPUTED_VALUE"""),"Em Quang") -> Em Quang | C38: =IFERROR(__xludf.DUMMYFUNCTION("""COMPUTED_VALUE"""),"43/69/131 Trần Phú") -> 43/69/131 Trần Phú | D38: =IFERROR(__xludf.DUMMYFUNCTION("""COMPUTED_VALUE"""),"chó") -> chó | E38: =IFERROR(__xludf.DUMMYFUNCTION("""COMPUTED_VALUE"""),"mích") -> mích
A39: =IFERROR(__xludf.DUMMYFUNCTION("""COMPUTED_VALUE"""),"0836 133 468") -> 0836 133 468 | B39: =IFERROR(__xludf.DUMMYFUNCTION("""COMPUTED_VALUE"""),"Chị Khánh") -> Chị Khánh | C39: =IFERROR(__xludf.DUMMYFUNCTION("""COMPUTED_VALUE"""),"thích tịnh khiết") -> thích tịnh khiết | D39: =IFERROR(__xludf.DUMMYFUNCTION("""COMPUTED_VALUE"""),"chó") -> chó | E39: =IFERROR(__xludf.DUMMYFUNCTION("""COMPUTED_VALUE"""),"mỡ") -> mỡ
A40: =IFERROR(__xludf.DUMMYFUNCTION("""COMPUTED_VALUE"""),"0948 699 208") -> 0948 699 208 | B40: =IFERROR(__xludf.DUMMYFUNCTION("""COMPUTED_VALUE"""),"Chú Nguyễn Thu") -> Chú Nguyễn Thu | C40: =IFERROR(__xludf.DUMMYFUNCTION("""COMPUTED_VALUE"""),"29 Trần Đại Nghĩa -An Cựu") -> 29 Trần Đại Nghĩa -An Cựu | D40: =IFERROR(__xludf.DUMMYFUNCTION("""COMPUTED_VALUE"""),"chó") -> chó | E40: =IFERROR(__xludf.DUMMYFUNCTION("""COMPUTED_VALUE"""),"bi") -> bi
A41: =IFERROR(__xludf.DUMMYFUNCTION("""COMPUTED_VALUE"""),"0827 879 356") -> 0827 879 356 | B41: =IFERROR(__xludf.DUMMYFUNCTION("""COMPUTED_VALUE"""),"Cô Liên vợ Thầy Hải") -> Cô Liên vợ Thầy Hải | C41: =IFERROR(__xludf.DUMMYFUNCTION("""COMPUTED_VALUE"""),"Hương Hồ") -> Hương Hồ | D41: =IFERROR(__xludf.DUMMYFUNCTION("""COMPUTED_VALUE"""),"mèo") -> mèo
A42: =IFERROR(__xludf.DUMMYFUNCTION("""COMPUTED_VALUE"""),"0905 779 662") -> 0905 779 662 | B42: =IFERROR(__xludf.DUMMYFUNCTION("""COMPUTED_VALUE"""),"Anh bảo-tuấn") -> Anh bảo-tuấn | C42: =IFERROR(__xludf.DUMMYFUNCTION("""COMPUTED_VALUE""")," 100 nguyễn văn Đào") -> 100 nguyễn văn Đào | D42: =IFERROR(__xludf.DUMMYFUNCTION("""COMPUTED_VALUE"""),"chó") -> chó
A43: =IFERROR(__xludf.DUMMYFUNCTION("""COMPUTED_VALUE"""),"0932 553 902") -> 0932 553 902 | B43: =IFERROR(__xludf.DUMMYFUNCTION("""COMPUTED_VALUE"""),"Anh Doanh") -> Anh Doanh | C43: =IFERROR(__xludf.DUMMYFUNCTION("""COMPUTED_VALUE"""),"46 Kim Long") -> 46 Kim Long | D43: =IFERROR(__xludf.DUMMYFUNCTION("""COMPUTED_VALUE"""),"Chó") -> Chó | E43: =IFERROR(__xludf.DUMMYFUNCTION("""COMPUTED_VALUE"""),"Lucky") -> Lucky
A44: =IFERROR(__xludf.DUMMYFUNCTION("""COMPUTED_VALUE"""),"0353 524 689") -> 0353 524 689 | B44: =IFERROR(__xludf.DUMMYFUNCTION("""COMPUTED_VALUE"""),"Anh Lĩnh") -> Anh Lĩnh | C44: =IFERROR(__xludf.DUMMYFUNCTION("""COMPUTED_VALUE"""),"22B/93 Nguyễn Hoàng") -> 22B/93 Nguyễn Hoàng | D44: =IFERROR(__xludf.DUMMYFUNCTION("""COMPUTED_VALUE"""),"Chó") -> Chó | E44: =IFERROR(__xludf.DUMMYFUNCTION("""COMPUTED_VALUE"""),"Rock") -> Rock
A45: =IFERROR(__xludf.DUMMYFUNCTION("""COMPUTED_VALUE"""),"0923 923 394") -> 0923 923 394 | B45: =IFERROR(__xludf.DUMMYFUNCTION("""COMPUTED_VALUE"""),"Em Quân") -> Em Quân | C45: =IFERROR(__xludf.DUMMYFUNCTION("""COMPUTED_VALUE"""),"242 Bùi Thị Xuân") -> 242 Bùi Thị Xuân | D45: =IFERROR(__xludf.DUMMYFUNCTION("""COMPUTED_VALUE"""),"chó") -> chó
A46: =IFERROR(__xludf.DUMMYFUNCTION("""COMPUTED_VALUE"""),"0979 588 341") -> 0979 588 341 | B46: =IFERROR(__xludf.DUMMYFUNCTION("""COMPUTED_VALUE"""),"Chị Yến Nhi") -> Chị Yến Nhi | C46: =IFERROR(__xludf.DUMMYFUNCTION("""COMPUTED_VALUE"""),"Quảng Trị") -> Quảng Trị | D46: =IFERROR(__xludf.DUMMYFUNCTION("""COMPUTED_VALUE"""),"Chó") -> Chó
A47: =IFERROR(__xludf.DUMMYFUNCTION("""COMPUTED_VALUE"""),"0385 400 328") -> 0385 400 328 | B47: =IFERROR(__xludf.DUMMYFUNCTION("""COMPUTED_VALUE"""),"Vân Anh") -> Vân Anh | C47: =IFERROR(__xludf.DUMMYFUNCTION("""COMPUTED_VALUE"""),"12 Hồ Văn Hiến") -> 12 Hồ Văn Hiến | D47: =IFERROR(__xludf.DUMMYFUNCTION("""COMPUTED_VALUE"""),"chó") -> chó | E47: =IFERROR(__xludf.DUMMYFUNCTION("""COMPUTED_VALUE"""),"Đen") -> Đen
A48: =IFERROR(__xludf.DUMMYFUNCTION("""COMPUTED_VALUE"""),"0766 805 496") -> 0766 805 496 | B48: =IFERROR(__xludf.DUMMYFUNCTION("""COMPUTED_VALUE"""),"Em An") -> Em An | C48: =IFERROR(__xludf.DUMMYFUNCTION("""COMPUTED_VALUE"""),"5/22/149 Trần Phú") -> 5/22/149 Trần Phú | D48: =IFERROR(__xludf.DUMMYFUNCTION("""COMPUTED_VALUE"""),"mèo") -> mèo | E48: =IFERROR(__xludf.DUMMYFUNCTION("""COMPUTED_VALUE"""),"gạo") -> gạo
A49: =IFERROR(__xludf.DUMMYFUNCTION("""COMPUTED_VALUE"""),"0935 260 770") -> 0935 260 770 | B49: =IFERROR(__xludf.DUMMYFUNCTION("""COMPUTED_VALUE"""),"Chị Ngọc ") -> Chị Ngọc | D49: =IFERROR(__xludf.DUMMYFUNCTION("""COMPUTED_VALUE"""),"Mèo") -> Mèo | E49: =IFERROR(__xludf.DUMMYFUNCTION("""COMPUTED_VALUE"""),"Amy") -> Amy
A50: =IFERROR(__xludf.DUMMYFUNCTION("""COMPUTED_VALUE"""),"6/16") -> 6/16 | B50: =IFERROR(__xludf.DUMMYFUNCTION("""COMPUTED_VALUE"""),"Chị Phan Thị Phương") -> Chị Phan Thị Phương | C50: =IFERROR(__xludf.DUMMYFUNCTION("""COMPUTED_VALUE"""),"6/16 Đoàn Hữu Trưng") -> 6/16 Đoàn Hữu Trưng | D50: =IFERROR(__xludf.DUMMYFUNCTION("""COMPUTED_VALUE"""),"chó/mèo") -> chó/mèo
A51: =IFERROR(__xludf.DUMMYFUNCTION("""COMPUTED_VALUE"""),"0797 751 045") -> 0797 751 045 | B51: =IFERROR(__xludf.DUMMYFUNCTION("""COMPUTED_VALUE"""),"Em Châu") -> Em Châu | C51: =IFERROR(__xludf.DUMMYFUNCTION("""COMPUTED_VALUE"""),"32 Hàm Nghi") -> 32 Hàm Nghi | D51: =IFERROR(__xludf.DUMMYFUNCTION("""COMPUTED_VALUE"""),"Mèo") -> Mèo | E51: =IFERROR(__xludf.DUMMYFUNCTION("""COMPUTED_VALUE"""),"Xi") -> Xi
A52: =IFERROR(__xludf.DUMMYFUNCTION("""COMPUTED_VALUE"""),"0914 125 501") -> 0914 125 501 | B52: =IFERROR(__xludf.DUMMYFUNCTION("""COMPUTED_VALUE"""),"Thu Hiền") -> Thu Hiền | C52: =IFERROR(__xludf.DUMMYFUNCTION("""COMPUTED_VALUE"""),"43 Phan Anh") -> 43 Phan Anh | D52: =IFERROR(__xludf.DUMMYFUNCTION("""COMPUTED_VALUE"""),"Chó") -> Chó | E52: =IFERROR(__xludf.DUMMYFUNCTION("""COMPUTED_VALUE"""),"Bun") -> Bun
A53: =IFERROR(__xludf.DUMMYFUNCTION("""COMPUTED_VALUE"""),"0704 847 572") -> 0704 847 572 | B53: =IFERROR(__xludf.DUMMYFUNCTION("""COMPUTED_VALUE"""),"Quốc Huy") -> Quốc Huy | C53: =IFERROR(__xludf.DUMMYFUNCTION("""COMPUTED_VALUE"""),"13/63 Phạm Thị Liên") -> 13/63 Phạm Thị Liên | D53: =IFERROR(__xludf.DUMMYFUNCTION("""COMPUTED_VALUE"""),"Chó") -> Chó | E53: =IFERROR(__xludf.DUMMYFUNCTION("""COMPUTED_VALUE"""),"Vàng") -> Vàng
A54: =IFERROR(__xludf.DUMMYFUNCTION("""COMPUTED_VALUE"""),"0388 119 098") -> 0388 119 098 | B54: =IFERROR(__xludf.DUMMYFUNCTION("""COMPUTED_VALUE"""),"Chị Thu Hà") -> Chị Thu Hà | D54: =IFERROR(__xludf.DUMMYFUNCTION("""COMPUTED_VALUE"""),"Chó") -> Chó | E54: =IFERROR(__xludf.DUMMYFUNCTION("""COMPUTED_VALUE"""),"Bắp/Bầu/Bí") -> Bắp/Bầu/Bí
A55: =IFERROR(__xludf.DUMMYFUNCTION("""COMPUTED_VALUE"""),"0971 219 095") -> 0971 219 095 | B55: =IFERROR(__xludf.DUMMYFUNCTION("""COMPUTED_VALUE"""),"anh Dương") -> anh Dương | C55: =IFERROR(__xludf.DUMMYFUNCTION("""COMPUTED_VALUE"""),"phường Mỹ thượng") -> phường Mỹ thượng | D55: =IFERROR(__xludf.DUMMYFUNCTION("""COMPUTED_VALUE"""),"chó") -> chó
A56: =IFERROR(__xludf.DUMMYFUNCTION("""COMPUTED_VALUE"""),"0396 429 703") -> 0396 429 703 | B56: =IFERROR(__xludf.DUMMYFUNCTION("""COMPUTED_VALUE"""),"Anh Đạt") -> Anh Đạt | C56: =IFERROR(__xludf.DUMMYFUNCTION("""COMPUTED_VALUE"""),"minh mạng") -> minh mạng | D56: =IFERROR(__xludf.DUMMYFUNCTION("""COMPUTED_VALUE"""),"chó") -> chó | E56: =IFERROR(__xludf.DUMMYFUNCTION("""COMPUTED_VALUE"""),"nâu") -> nâu
A57: =IFERROR(__xludf.DUMMYFUNCTION("""COMPUTED_VALUE"""),"0336 519 015") -> 0336 519 015 | B57: =IFERROR(__xludf.DUMMYFUNCTION("""COMPUTED_VALUE"""),"Em Công Hào") -> Em Công Hào | C57: =IFERROR(__xludf.DUMMYFUNCTION("""COMPUTED_VALUE"""),"236 Lý Nam Đế") -> 236 Lý Nam Đế | D57: =IFERROR(__xludf.DUMMYFUNCTION("""COMPUTED_VALUE"""),"Mèo") -> Mèo | E57: =IFERROR(__xludf.DUMMYFUNCTION("""COMPUTED_VALUE"""),"Mun") -> Mun
A58: =IFERROR(__xludf.DUMMYFUNCTION("""COMPUTED_VALUE"""),"0962 137 147") -> 0962 137 147
A59: =IFERROR(__xludf.DUMMYFUNCTION("""COMPUTED_VALUE"""),"0911 911 158") -> 0911 911 158
A60: =IFERROR(__xludf.DUMMYFUNCTION("""COMPUTED_VALUE"""),"0337 623 641") -> 0337 623 641 | B60: =IFERROR(__xludf.DUMMYFUNCTION("""COMPUTED_VALUE"""),"Anh Hoàng Phúc") -> Anh Hoàng Phúc | C60: =IFERROR(__xludf.DUMMYFUNCTION("""COMPUTED_VALUE"""),"n69k131 Trần Phú") -> n69k131 Trần Phú | D60: =IFERROR(__xludf.DUMMYFUNCTION("""COMPUTED_VALUE"""),"chó") -> chó
A61: =IFERROR(__xludf.DUMMYFUNCTION("""COMPUTED_VALUE"""),"0932 192 150") -> 0932 192 150 | B61: =IFERROR(__xludf.DUMMYFUNCTION("""COMPUTED_VALUE"""),"Anh Thịnh") -> Anh Thịnh | C61: =IFERROR(__xludf.DUMMYFUNCTION("""COMPUTED_VALUE"""),"4/55 Vạn Xuân") -> 4/55 Vạn Xuân | D61: =IFERROR(__xludf.DUMMYFUNCTION("""COMPUTED_VALUE"""),"Mèo") -> Mèo | E61: =IFERROR(__xludf.DUMMYFUNCTION("""COMPUTED_VALUE"""),"Meo") -> Meo
A62: =IFERROR(__xludf.DUMMYFUNCTION("""COMPUTED_VALUE"""),"0975 935 435") -> 0975 935 435 | B62: =IFERROR(__xludf.DUMMYFUNCTION("""COMPUTED_VALUE"""),"Chị Thảo") -> Chị Thảo | C62: =IFERROR(__xludf.DUMMYFUNCTION("""COMPUTED_VALUE"""),"Nam Giao") -> Nam Giao | D62: =IFERROR(__xludf.DUMMYFUNCTION("""COMPUTED_VALUE"""),"chó") -> chó | E62: =IFERROR(__xludf.DUMMYFUNCTION("""COMPUTED_VALUE"""),"tin") -> tin
A63: =IFERROR(__xludf.DUMMYFUNCTION("""COMPUTED_VALUE"""),"0867 421 778") -> 0867 421 778 | B63: =IFERROR(__xludf.DUMMYFUNCTION("""COMPUTED_VALUE"""),"Em Như Quỳnh") -> Em Như Quỳnh | D63: =IFERROR(__xludf.DUMMYFUNCTION("""COMPUTED_VALUE"""),"Chó") -> Chó | E63: =IFERROR(__xludf.DUMMYFUNCTION("""COMPUTED_VALUE"""),"Ốc") -> Ốc
A64: =IFERROR(__xludf.DUMMYFUNCTION("""COMPUTED_VALUE"""),"0382 664 610") -> 0382 664 610 | B64: =IFERROR(__xludf.DUMMYFUNCTION("""COMPUTED_VALUE"""),"em nguyễn thị thúy hằng") -> em nguyễn thị thúy hằng | C64: =IFERROR(__xludf.DUMMYFUNCTION("""COMPUTED_VALUE"""),"15k65 đặng huy trứ") -> 15k65 đặng huy trứ | D64: =IFERROR(__xludf.DUMMYFUNCTION("""COMPUTED_VALUE"""),"mèo") -> mèo | E64: =IFERROR(__xludf.DUMMYFUNCTION("""COMPUTED_VALUE"""),"nguyệt thảo/thư di") -> nguyệt thảo/thư di
A65: =IFERROR(__xludf.DUMMYFUNCTION("""COMPUTED_VALUE"""),"0399 535 237") -> 0399 535 237 | B65: =IFERROR(__xludf.DUMMYFUNCTION("""COMPUTED_VALUE"""),"Em Huy") -> Em Huy | C65: =IFERROR(__xludf.DUMMYFUNCTION("""COMPUTED_VALUE"""),"k201 trần Phú") -> k201 trần Phú | D65: =IFERROR(__xludf.DUMMYFUNCTION("""COMPUTED_VALUE"""),"chó") -> chó | E65: =IFERROR(__xludf.DUMMYFUNCTION("""COMPUTED_VALUE"""),"thỏ") -> thỏ
A66: =IFERROR(__xludf.DUMMYFUNCTION("""COMPUTED_VALUE"""),"0919 960 233") -> 0919 960 233 | B66: =IFERROR(__xludf.DUMMYFUNCTION("""COMPUTED_VALUE"""),"chị Thi") -> chị Thi | C66: =IFERROR(__xludf.DUMMYFUNCTION("""COMPUTED_VALUE"""),"63 Võ Thị Sáu") -> 63 Võ Thị Sáu | D66: =IFERROR(__xludf.DUMMYFUNCTION("""COMPUTED_VALUE"""),"chó") -> chó
A67: =IFERROR(__xludf.DUMMYFUNCTION("""COMPUTED_VALUE"""),"0948 853 377") -> 0948 853 377 | B67: =IFERROR(__xludf.DUMMYFUNCTION("""COMPUTED_VALUE"""),"Dì Bình") -> Dì Bình | D67: =IFERROR(__xludf.DUMMYFUNCTION("""COMPUTED_VALUE"""),"Mèo") -> Mèo | E67: =IFERROR(__xludf.DUMMYFUNCTION("""COMPUTED_VALUE"""),"Rum") -> Rum
A68: =IFERROR(__xludf.DUMMYFUNCTION("""COMPUTED_VALUE"""),"0377 622 405") -> 0377 622 405 | B68: =IFERROR(__xludf.DUMMYFUNCTION("""COMPUTED_VALUE""")," anh Tuấn Kiệt") -> anh Tuấn Kiệt | C68: =IFERROR(__xludf.DUMMYFUNCTION("""COMPUTED_VALUE"""),"Thiên Thai") -> Thiên Thai | D68: =IFERROR(__xludf.DUMMYFUNCTION("""COMPUTED_VALUE"""),"chó") -> chó | E68: =IFERROR(__xludf.DUMMYFUNCTION("""COMPUTED_VALUE"""),"sữa") -> sữa
A69: =IFERROR(__xludf.DUMMYFUNCTION("""COMPUTED_VALUE"""),"0788 559 364") -> 0788 559 364 | B69: =IFERROR(__xludf.DUMMYFUNCTION("""COMPUTED_VALUE"""),"Thục Trinh") -> Thục Trinh | C69: =IFERROR(__xludf.DUMMYFUNCTION("""COMPUTED_VALUE"""),"13/42 Trần Quốc Toản") -> 13/42 Trần Quốc Toản | D69: =IFERROR(__xludf.DUMMYFUNCTION("""COMPUTED_VALUE"""),"Chó") -> Chó | E69: =IFERROR(__xludf.DUMMYFUNCTION("""COMPUTED_VALUE"""),"Tom") -> Tom
A70: =IFERROR(__xludf.DUMMYFUNCTION("""COMPUTED_VALUE"""),"0898 136 775") -> 0898 136 775 | B70: =IFERROR(__xludf.DUMMYFUNCTION("""COMPUTED_VALUE"""),"Anh Minh") -> Anh Minh | C70: =IFERROR(__xludf.DUMMYFUNCTION("""COMPUTED_VALUE"""),"k245 Phan Bội Châu") -> k245 Phan Bội Châu | D70: =IFERROR(__xludf.DUMMYFUNCTION("""COMPUTED_VALUE"""),"thỏ") -> thỏ
A71: =IFERROR(__xludf.DUMMYFUNCTION("""COMPUTED_VALUE"""),"0935 342 011") -> 0935 342 011 | B71: =IFERROR(__xludf.DUMMYFUNCTION("""COMPUTED_VALUE"""),"dì Nguyễn Ngọc Hà") -> dì Nguyễn Ngọc Hà | C71: =IFERROR(__xludf.DUMMYFUNCTION("""COMPUTED_VALUE"""),"45 Vũ Ngọc Phan") -> 45 Vũ Ngọc Phan | D71: =IFERROR(__xludf.DUMMYFUNCTION("""COMPUTED_VALUE"""),"chó") -> chó | E71: =IFERROR(__xludf.DUMMYFUNCTION("""COMPUTED_VALUE"""),"đậu") -> đậu
A72: =IFERROR(__xludf.DUMMYFUNCTION("""COMPUTED_VALUE"""),"0793 585 509") -> 0793 585 509 | B72: =IFERROR(__xludf.DUMMYFUNCTION("""COMPUTED_VALUE"""),"em Hồ Nguyệt Khang") -> em Hồ Nguyệt Khang | C72: =IFERROR(__xludf.DUMMYFUNCTION("""COMPUTED_VALUE"""),"162 Ngự Bình") -> 162 Ngự Bình | D72: =IFERROR(__xludf.DUMMYFUNCTION("""COMPUTED_VALUE"""),"mèo") -> mèo | E72: =IFERROR(__xludf.DUMMYFUNCTION("""COMPUTED_VALUE"""),"rocky") -> rocky
A73: =IFERROR(__xludf.DUMMYFUNCTION("""COMPUTED_VALUE"""),"0796 693 654") -> 0796 693 654 | B73: =IFERROR(__xludf.DUMMYFUNCTION("""COMPUTED_VALUE"""),"Dì Tâm ") -> Dì Tâm | C73: =IFERROR(__xludf.DUMMYFUNCTION("""COMPUTED_VALUE"""),"2/56 kiệt 131 Trần Phú") -> 2/56 kiệt 131 Trần Phú | D73: =IFERROR(__xludf.DUMMYFUNCTION("""COMPUTED_VALUE"""),"chó") -> chó
A74: =IFERROR(__xludf.DUMMYFUNCTION("""COMPUTED_VALUE"""),"0905 677 956") -> 0905 677 956 | B74: =IFERROR(__xludf.DUMMYFUNCTION("""COMPUTED_VALUE"""),"chị Diệu Trà") -> chị Diệu Trà | C74: =IFERROR(__xludf.DUMMYFUNCTION("""COMPUTED_VALUE"""),"22/17b/11 Thiên Thai") -> 22/17b/11 Thiên Thai | D74: =IFERROR(__xludf.DUMMYFUNCTION("""COMPUTED_VALUE"""),"chó") -> chó | E74: =IFERROR(__xludf.DUMMYFUNCTION("""COMPUTED_VALUE"""),"lé") -> lé
A75: =IFERROR(__xludf.DUMMYFUNCTION("""COMPUTED_VALUE"""),"0949 369 639") -> 0949 369 639 | B75: =IFERROR(__xludf.DUMMYFUNCTION("""COMPUTED_VALUE"""),"anh Trương Vĩnh Thọ") -> anh Trương Vĩnh Thọ | C75: =IFERROR(__xludf.DUMMYFUNCTION("""COMPUTED_VALUE"""),"29 Nguyễn Trường Tộ") -> 29 Nguyễn Trường Tộ | D75: =IFERROR(__xludf.DUMMYFUNCTION("""COMPUTED_VALUE"""),"mèo") -> mèo
A76: =IFERROR(__xludf.DUMMYFUNCTION("""COMPUTED_VALUE"""),"0905 259 034") -> 0905 259 034 | B76: =IFERROR(__xludf.DUMMYFUNCTION("""COMPUTED_VALUE"""),"Xuân Hương") -> Xuân Hương | C76: =IFERROR(__xludf.DUMMYFUNCTION("""COMPUTED_VALUE"""),"40 Hàm Nghi") -> 40 Hàm Nghi | D76: =IFERROR(__xludf.DUMMYFUNCTION("""COMPUTED_VALUE"""),"Mèo") -> Mèo
A77: =IFERROR(__xludf.DUMMYFUNCTION("""COMPUTED_VALUE"""),"0767 413 100") -> 0767 413 100 | B77: =IFERROR(__xludf.DUMMYFUNCTION("""COMPUTED_VALUE"""),"Chị Tuyến") -> Chị Tuyến | C77: =IFERROR(__xludf.DUMMYFUNCTION("""COMPUTED_VALUE"""),"k111 trần thái tông") -> k111 trần thái tông | D77: =IFERROR(__xludf.DUMMYFUNCTION("""COMPUTED_VALUE"""),"mèo") -> mèo
A78: =IFERROR(__xludf.DUMMYFUNCTION("""COMPUTED_VALUE"""),"0866 509 274") -> 0866 509 274 | B78: =IFERROR(__xludf.DUMMYFUNCTION("""COMPUTED_VALUE"""),"Anh Hưng") -> Anh Hưng | C78: =IFERROR(__xludf.DUMMYFUNCTION("""COMPUTED_VALUE"""),"hà nội") -> hà nội | D78: =IFERROR(__xludf.DUMMYFUNCTION("""COMPUTED_VALUE"""),"mèo") -> mèo
A79: =IFERROR(__xludf.DUMMYFUNCTION("""COMPUTED_VALUE"""),"0983 519 641") -> 0983 519 641 | B79: =IFERROR(__xludf.DUMMYFUNCTION("""COMPUTED_VALUE"""),"Anh Tăng") -> Anh Tăng | C79: =IFERROR(__xludf.DUMMYFUNCTION("""COMPUTED_VALUE"""),"Kiệt 69 Phạm Thị Liên") -> Kiệt 69 Phạm Thị Liên | D79: =IFERROR(__xludf.DUMMYFUNCTION("""COMPUTED_VALUE"""),"Chó") -> Chó
A80: =IFERROR(__xludf.DUMMYFUNCTION("""COMPUTED_VALUE"""),"0792 339 465") -> 0792 339 465 | B80: =IFERROR(__xludf.DUMMYFUNCTION("""COMPUTED_VALUE"""),"Khánh Hà") -> Khánh Hà | C80: =IFERROR(__xludf.DUMMYFUNCTION("""COMPUTED_VALUE"""),"10/42 Nguyễn Phúc Tần") -> 10/42 Nguyễn Phúc Tần | D80: =IFERROR(__xludf.DUMMYFUNCTION("""COMPUTED_VALUE"""),"Chó") -> Chó | E80: =IFERROR(__xludf.DUMMYFUNCTION("""COMPUTED_VALUE"""),"Khoai") -> Khoai
A81: =IFERROR(__xludf.DUMMYFUNCTION("""COMPUTED_VALUE"""),"0772 409 399") -> 0772 409 399 | B81: =IFERROR(__xludf.DUMMYFUNCTION("""COMPUTED_VALUE"""),"Chị Qúy") -> Chị Qúy | C81: =IFERROR(__xludf.DUMMYFUNCTION("""COMPUTED_VALUE"""),"14/92 Đặng Huy Trứ") -> 14/92 Đặng Huy Trứ | D81: =IFERROR(__xludf.DUMMYFUNCTION("""COMPUTED_VALUE"""),"Mèo") -> Mèo | E81: =IFERROR(__xludf.DUMMYFUNCTION("""COMPUTED_VALUE"""),"Tom") -> Tom
A82: =IFERROR(__xludf.DUMMYFUNCTION("""COMPUTED_VALUE"""),"0901 122 920") -> 0901 122 920 | B82: =IFERROR(__xludf.DUMMYFUNCTION("""COMPUTED_VALUE"""),"Chị Ben") -> Chị Ben | C82: =IFERROR(__xludf.DUMMYFUNCTION("""COMPUTED_VALUE"""),"138 Vạn Xuân") -> 138 Vạn Xuân | D82: =IFERROR(__xludf.DUMMYFUNCTION("""COMPUTED_VALUE"""),"Chó") -> Chó | E82: =IFERROR(__xludf.DUMMYFUNCTION("""COMPUTED_VALUE"""),"Nâu") -> Nâu
A83: =IFERROR(__xludf.DUMMYFUNCTION("""COMPUTED_VALUE"""),"0934 946 122") -> 0934 946 122 | B83: =IFERROR(__xludf.DUMMYFUNCTION("""COMPUTED_VALUE"""),"Anh Zet") -> Anh Zet | C83: =IFERROR(__xludf.DUMMYFUNCTION("""COMPUTED_VALUE"""),"8 Lê Tự Nhiên") -> 8 Lê Tự Nhiên | D83: =IFERROR(__xludf.DUMMYFUNCTION("""COMPUTED_VALUE"""),"Chó") -> Chó | E83: =IFERROR(__xludf.DUMMYFUNCTION("""COMPUTED_VALUE"""),"Đen") -> Đen
A84: =IFERROR(__xludf.DUMMYFUNCTION("""COMPUTED_VALUE"""),"0983 330 737") -> 0983 330 737 | B84: =IFERROR(__xludf.DUMMYFUNCTION("""COMPUTED_VALUE"""),"A Thiện") -> A Thiện | C84: =IFERROR(__xludf.DUMMYFUNCTION("""COMPUTED_VALUE"""),"lữu bảo") -> lữu bảo
A85: =IFERROR(__xludf.DUMMYFUNCTION("""COMPUTED_VALUE"""),"0905 862 700") -> 0905 862 700 | B85: =IFERROR(__xludf.DUMMYFUNCTION("""COMPUTED_VALUE"""),"Chị Duy Uyên") -> Chị Duy Uyên | C85: =IFERROR(__xludf.DUMMYFUNCTION("""COMPUTED_VALUE"""),"2/90 Nguyễn Huệ") -> 2/90 Nguyễn Huệ | D85: =IFERROR(__xludf.DUMMYFUNCTION("""COMPUTED_VALUE"""),"Mèo") -> Mèo
A86: =IFERROR(__xludf.DUMMYFUNCTION("""COMPUTED_VALUE"""),"0702 316 416") -> 0702 316 416 | B86: =IFERROR(__xludf.DUMMYFUNCTION("""COMPUTED_VALUE"""),"Chú Phúc") -> Chú Phúc | C86: =IFERROR(__xludf.DUMMYFUNCTION("""COMPUTED_VALUE"""),"110 Lê Duẩn") -> 110 Lê Duẩn | D86: =IFERROR(__xludf.DUMMYFUNCTION("""COMPUTED_VALUE"""),"Chó") -> Chó | E86: =IFERROR(__xludf.DUMMYFUNCTION("""COMPUTED_VALUE"""),"Lucky") -> Lucky
A87: =IFERROR(__xludf.DUMMYFUNCTION("""COMPUTED_VALUE"""),"0357 015 855") -> 0357 015 855 | B87: =IFERROR(__xludf.DUMMYFUNCTION("""COMPUTED_VALUE"""),"Minh Châu") -> Minh Châu | C87: =IFERROR(__xludf.DUMMYFUNCTION("""COMPUTED_VALUE"""),"21/68 Điện biên phủ") -> 21/68 Điện biên phủ | D87: =IFERROR(__xludf.DUMMYFUNCTION("""COMPUTED_VALUE"""),"mèo") -> mèo
A88: =IFERROR(__xludf.DUMMYFUNCTION("""COMPUTED_VALUE"""),"0779 407 337") -> 0779 407 337 | B88: =IFERROR(__xludf.DUMMYFUNCTION("""COMPUTED_VALUE"""),"Em Hiệp") -> Em Hiệp | C88: =IFERROR(__xludf.DUMMYFUNCTION("""COMPUTED_VALUE"""),"10/37/1 Hồ Văn Hiển") -> 10/37/1 Hồ Văn Hiển | D88: =IFERROR(__xludf.DUMMYFUNCTION("""COMPUTED_VALUE"""),"chó") -> chó | E88: =IFERROR(__xludf.DUMMYFUNCTION("""COMPUTED_VALUE"""),"bông") -> bông
A89: =IFERROR(__xludf.DUMMYFUNCTION("""COMPUTED_VALUE"""),"0773 520 660") -> 0773 520 660 | B89: =IFERROR(__xludf.DUMMYFUNCTION("""COMPUTED_VALUE"""),"Anh Minh") -> Anh Minh | C89: =IFERROR(__xludf.DUMMYFUNCTION("""COMPUTED_VALUE"""),"D266") -> D266 | D89: =IFERROR(__xludf.DUMMYFUNCTION("""COMPUTED_VALUE"""),"chó") -> chó | E89: =IFERROR(__xludf.DUMMYFUNCTION("""COMPUTED_VALUE"""),"mít") -> mít
A90: =IFERROR(__xludf.DUMMYFUNCTION("""COMPUTED_VALUE"""),"0916 347 518") -> 0916 347 518 | B90: =IFERROR(__xludf.DUMMYFUNCTION("""COMPUTED_VALUE"""),"Anh Nghĩa") -> Anh Nghĩa | C90: =IFERROR(__xludf.DUMMYFUNCTION("""COMPUTED_VALUE"""),"9/214 Ngự Bình") -> 9/214 Ngự Bình | D90: =IFERROR(__xludf.DUMMYFUNCTION("""COMPUTED_VALUE"""),"Chó") -> Chó | E90: =IFERROR(__xludf.DUMMYFUNCTION("""COMPUTED_VALUE"""),"Beo") -> Beo
A91: =IFERROR(__xludf.DUMMYFUNCTION("""COMPUTED_VALUE"""),"0788 667 231") -> 0788 667 231 | B91: =IFERROR(__xludf.DUMMYFUNCTION("""COMPUTED_VALUE"""),"Anh Minh") -> Anh Minh | C91: =IFERROR(__xludf.DUMMYFUNCTION("""COMPUTED_VALUE"""),"phường Phong Quảng-Quảng Điền") -> phường Phong Quảng-Quảng Điền | D91: =IFERROR(__xludf.DUMMYFUNCTION("""COMPUTED_VALUE"""),"chó") -> chó | E91: =IFERROR(__xludf.DUMMYFUNCTION("""COMPUTED_VALUE"""),"lucky") -> lucky
A92: =IFERROR(__xludf.DUMMYFUNCTION("""COMPUTED_VALUE"""),"0888 353 536") -> 0888 353 536 | B92: =IFERROR(__xludf.DUMMYFUNCTION("""COMPUTED_VALUE"""),"Anh Quân") -> Anh Quân | C92: =IFERROR(__xludf.DUMMYFUNCTION("""COMPUTED_VALUE"""),"56 Vạn Xuân") -> 56 Vạn Xuân | D92: =IFERROR(__xludf.DUMMYFUNCTION("""COMPUTED_VALUE"""),"chó") -> chó | E92: =IFERROR(__xludf.DUMMYFUNCTION("""COMPUTED_VALUE"""),"Milnar") -> Milnar
A93: =IFERROR(__xludf.DUMMYFUNCTION("""COMPUTED_VALUE"""),"0898 198 243") -> 0898 198 243 | B93: =IFERROR(__xludf.DUMMYFUNCTION("""COMPUTED_VALUE"""),"Phan Lệ Hằng") -> Phan Lệ Hằng | C93: =IFERROR(__xludf.DUMMYFUNCTION("""COMPUTED_VALUE"""),"3/29 Phạm Tu") -> 3/29 Phạm Tu | D93: =IFERROR(__xludf.DUMMYFUNCTION("""COMPUTED_VALUE"""),"Mèo") -> Mèo | E93: =IFERROR(__xludf.DUMMYFUNCTION("""COMPUTED_VALUE"""),"Mướp") -> Mướp
A94: =IFERROR(__xludf.DUMMYFUNCTION("""COMPUTED_VALUE"""),"0383 585 704") -> 0383 585 704 | B94: =IFERROR(__xludf.DUMMYFUNCTION("""COMPUTED_VALUE"""),"Em Bảo Uyên") -> Em Bảo Uyên | C94: =IFERROR(__xludf.DUMMYFUNCTION("""COMPUTED_VALUE"""),"An Cựu") -> An Cựu | D94: =IFERROR(__xludf.DUMMYFUNCTION("""COMPUTED_VALUE"""),"mèo") -> mèo
A95: =IFERROR(__xludf.DUMMYFUNCTION("""COMPUTED_VALUE"""),"0947 734 567") -> 0947 734 567 | B95: =IFERROR(__xludf.DUMMYFUNCTION("""COMPUTED_VALUE"""),"Anh Hương") -> Anh Hương
A96: =IFERROR(__xludf.DUMMYFUNCTION("""COMPUTED_VALUE"""),"0914 0525 75") -> 0914 0525 75 | B96: =IFERROR(__xludf.DUMMYFUNCTION("""COMPUTED_VALUE"""),"A Nhân") -> A Nhân | C96: =IFERROR(__xludf.DUMMYFUNCTION("""COMPUTED_VALUE"""),"Phú Lộc") -> Phú Lộc | D96: =IFERROR(__xludf.DUMMYFUNCTION("""COMPUTED_VALUE"""),"chó") -> chó | E96: =IFERROR(__xludf.DUMMYFUNCTION("""COMPUTED_VALUE"""),"beko") -> beko
A97: =IFERROR(__xludf.DUMMYFUNCTION("""COMPUTED_VALUE"""),"0392 447 998") -> 0392 447 998 | B97: =IFERROR(__xludf.DUMMYFUNCTION("""COMPUTED_VALUE"""),"Anh Hải") -> Anh Hải | C97: =IFERROR(__xludf.DUMMYFUNCTION("""COMPUTED_VALUE"""),"34/9 Nguyễn Hữu Dật") -> 34/9 Nguyễn Hữu Dật | D97: =IFERROR(__xludf.DUMMYFUNCTION("""COMPUTED_VALUE"""),"Chó") -> Chó | E97: =IFERROR(__xludf.DUMMYFUNCTION("""COMPUTED_VALUE"""),"Mập") -> Mập
A98: =IFERROR(__xludf.DUMMYFUNCTION("""COMPUTED_VALUE"""),"0935 266 777") -> 0935 266 777 | B98: =IFERROR(__xludf.DUMMYFUNCTION("""COMPUTED_VALUE"""),"Anh Hoàng") -> Anh Hoàng | C98: =IFERROR(__xludf.DUMMYFUNCTION("""COMPUTED_VALUE"""),"E50 Kim Long") -> E50 Kim Long | D98: =IFERROR(__xludf.DUMMYFUNCTION("""COMPUTED_VALUE"""),"Chó") -> Chó | E98: =IFERROR(__xludf.DUMMYFUNCTION("""COMPUTED_VALUE"""),"Joly") -> Joly
A99: =IFERROR(__xludf.DUMMYFUNCTION("""COMPUTED_VALUE"""),"0914 614 452") -> 0914 614 452 | B99: =IFERROR(__xludf.DUMMYFUNCTION("""COMPUTED_VALUE"""),"Bác Lịch ") -> Bác Lịch | C99: =IFERROR(__xludf.DUMMYFUNCTION("""COMPUTED_VALUE"""),"89 Nguyễn Phúc Thái") -> 89 Nguyễn Phúc Thái | D99: =IFERROR(__xludf.DUMMYFUNCTION("""COMPUTED_VALUE"""),"Chó") -> Chó | E99: =IFERROR(__xludf.DUMMYFUNCTION("""COMPUTED_VALUE"""),"Nô") -> Nô
A100: =IFERROR(__xludf.DUMMYFUNCTION("""COMPUTED_VALUE"""),"0774 508 864") -> 0774 508 864 | B100: =IFERROR(__xludf.DUMMYFUNCTION("""COMPUTED_VALUE"""),"Phương Lê") -> Phương Lê | C100: =IFERROR(__xludf.DUMMYFUNCTION("""COMPUTED_VALUE"""),"22/2/6 Phú Mộng") -> 22/2/6 Phú Mộng | D100: =IFERROR(__xludf.DUMMYFUNCTION("""COMPUTED_VALUE"""),"chó") -> chó | E100: =IFERROR(__xludf.DUMMYFUNCTION("""COMPUTED_VALUE"""),"Galaxy") -> Galaxy
A101: =IFERROR(__xludf.DUMMYFUNCTION("""COMPUTED_VALUE"""),"0935 120 206") -> 0935 120 206 | B101: =IFERROR(__xludf.DUMMYFUNCTION("""COMPUTED_VALUE"""),"Anh Thiện") -> Anh Thiện | C101: =IFERROR(__xludf.DUMMYFUNCTION("""COMPUTED_VALUE"""),"13/57 Nguyễn Hoàng") -> 13/57 Nguyễn Hoàng | D101: =IFERROR(__xludf.DUMMYFUNCTION("""COMPUTED_VALUE"""),"Chó") -> Chó
...

Sheet Danh muc Chi
C1: Chi hỗn hợp | E1: =G1-I1 -> 6498.5 | F1: Tổng | G1: =sum(G3:G226) -> 11202.5 | H1: Chi lưu kho | I1: =SUMIFS(G3:G596, F3:F596, "Thuoc dieu tri") + SUMIFS(G3:G596, F3:F596, "Vat tu") + SUMIFS(G3:G596, F3:F596, "Vaccine") -> 4704 | J1: =sum(J3:J226) -> 11202.5
A2: Ngày | B2: Nội dung | C2: Số lượng | D2: Đơn vị tính | E2: Đơn giá | F2: Thuộc hạng mục | G2: Số tiền | H2: Người chi | I2: Chú ý | J2: Tổng chi theo tuần/tháng
A3: 45965 | B3: Xăng xe Tuấn | C3: 1 | D3: lần | E3: 50 | F3: Xăng xe ca | G3: =C3*E3 -> 50 | H3: Tuấn
B4: giấy vs | C4: 2 | D4: lốc | E4: 40 | F4: Chi khac | G4: =C4*E4 -> 80 | H4: Trà
B5: tiền điện | C5: 1 | D5: hóa đơn | E5: 2308 | F5: Tien dien | G5: =C5*E5 -> 2308 | H5: Ánh
B6: internet | C6: 1 | D6: hóa đơn | E6: 195 | F6: Internet | G6: =C6*E6 -> 195 | H6: Ánh
A7: 45966 | B7: gan, phổi | C7: 5 | D7: kg | E7: 20 | F7: Thuc an cho thu luu tru | G7: =C7*E7 -> 100 | H7: Ánh
B8: hộp nhựa | C8: 1 | D8: bao | E8: 65 | F8: Hỏa táng | G8: =C8*E8 -> 65 | H8: Trà
A9: Tuần 1 | G9: =C9*E9 -> 0 | J9: =sum(G3:G8) -> 2798
A10: 45971 | B10: xn phong châu | C10: 1 | D10: hóa đơn | E10: 144 | F10: Xet nghiem | G10: =C10*E10 -> 144 | H10: Ánh
B11: gan, phổi | C11: 1 | D11: túi | E11: 140 | F11: Thuc an cho thu luu tru | G11: =C11*E11 -> 140 | H11: Ánh
B12: gạo | C12: 10 | D12: kg | E12: 14 | F12: Thuc an cho thu luu tru | G12: =C12*E12 -> 140 | H12: Ánh
B13: nhận hàng thầy | C13: 1 | D13: lần | E13: 35 | F13: Hàng của thầy | G13: =C13*E13 -> 35 | H13: Ánh
A14: 45972 | B14: xn phong châu | C14: 1 | D14: hóa đơn | E14: 48 | F14: Xet nghiem | G14: =C14*E14 -> 48 | H14: Ánh
B15: cephalexin | C15: 1 | D15: hộp | E15: 105 | F15: Thuoc dieu tri | G15: =C15*E15 -> 105 | H15: Ánh
B16: boganic | C16: 1 | D16: hộp | E16: 80 | F16: Thuoc dieu tri | G16: =C16*E16 -> 80 | H16: Ánh
B17: jasunny | C17: 1 | D17: hộp | E17: 315 | F17: Thuoc dieu tri | G17: =C17*E17 -> 315 | H17: Ánh
B18: men th | C18: 5 | D18: hộp | E18: 15 | F18: Thuoc dieu tri | G18: =C18*E18 -> 75 | H18: Ánh
B19: metro | C19: 1 | D19: hộp | E19: 27 | F19: Thuoc dieu tri | G19: =C19*E19 -> 27 | H19: Ánh
B20: vtm c | C20: 2 | D20: hộp | E20: 28 | F20: Thuoc dieu tri | G20: =C20*E20 -> 56 | H20: Ánh
B21: smecta | C21: 2 | D21: hộp | E21: 46 | F21: Thuoc dieu tri | G21: =C21*E21 -> 92 | H21: Ánh
B22: xylanh 3cc | C22: 2 | D22: hộp | E22: 62 | F22: Vat tu | G22: =C22*E22 -> 124 | H22: Ánh
B23: nước muối rửa | C23: 5 | D23: chai | E23: 5 | F23: Vat tu | G23: =C23*E23 -> 25 | H23: Ánh
A24: 45974 | B24: pate lon meo | C24: 1 | D24: lon | E24: 39.5 | F24: Thuc an cho thu luu tru | G24: =C24*E24 -> 39.5 | H24: Trà
B25: sữa bi-o | C25: 1 | D25: gói | E25: 26.5 | F25: Thuc an cho thu luu tru | G25: =C25*E25 -> 26.5 | H25: Trà
A26: 45976 | B26: gan, phổi | C26: 1 | D26: túi | E26: 140 | F26: Thuc an cho thu luu tru | G26: =C26*E26 -> 140 | H26: Tuấn
B27: pate lon mèo | C27: 1 | D27: lon | E27: 39.5 | F27: Thuc an cho thu luu tru | G27: =C27*E27 -> 39.5 | H27: Ánh
A28: 45977 | B28: xăng xe trà | C28: 1 | D28: lần | E28: 50 | F28: Xăng xe ca | G28: =C28*E28 -> 50 | H28: Trà
B29: hoa hỏa táng | C29: 1 | D29: bó | E29: 30 | F29: Hỏa táng | G29: =C29*E29 -> 30 | H29: Trà
A30: Tuần 2 | G30: =C30*E30 -> 0 | J30: =sum(G10:G29) -> 1731.5
A31: 45979 | B31: gạo | C31: 1 | D31: bao | E31: 100 | F31: Thuc an cho thu luu tru | G31: =C31*E31 -> 100 | H31: Trà
B32: nhận hàng thầy | C32: 1 | D32: lần | E32: 1092 | F32: Hàng của thầy | G32: =C32*E32 -> 1092 | H32: Ánh
B33: xăng xe Ánh | C33: 1 | D33: lần | E33: 30 | F33: Xăng xe ca | G33: =C33*E33 -> 30 | H33: Ánh
B34: men vi sinh | C34: 5 | D34: hộp | E34: =455/5 -> 91 | F34: Thuoc dieu tri | G34: =C34*E34 -> 455 | H34: Ánh
B35: gas | C35: 1 | D35: bình | E35: 390 | F35: Tien gas | G35: =C35*E35 -> 390 | H35: Ánh
B36: nước rửa chén | C36: 1 | D36: túi | E36: 32 | F36: Hoa chat | G36: =C36*E36 -> 32 | H36: Ánh
B37: hộp | C37: 1 | D37: bao | E37: 40 | F37: Vat tu | G37: =C37*E37 -> 40 | H37: Trà
B38: gan phổi | C38: 1 | D38: túi | E38: 90 | F38: Thuc an cho thu luu tru | G38: =C38*E38 -> 90 | H38: Ánh
B39: doxy | C39: 2 | D39: hộp | E39: 75 | F39: Thuoc dieu tri | G39: =C39*E39 -> 150 | H39: Ánh
B40: pred | C40: 2 | D40: hộp | E40: 55 | F40: Thuoc dieu tri | G40: =C40*E40 -> 110 | H40: Ánh
B41: boganic | C41: 2 | D41: hộp | E41: 80 | F41: Thuoc dieu tri | G41: =C41*E41 -> 160 | H41: Ánh
B42: xylanh 1cc | C42: 4 | D42: hộp | E42: 60 | F42: Vat tu | G42: =C42*E42 -> 240 | H42: Ánh
B43: nacl truyền | C43: 1 | D43: thùng | E43: 200 | F43: Thuoc dieu tri | G43: =C43*E43 -> 200 | H43: Ánh
B44: hương | C44: 1 | D44: bó | E44: 50 | F44: Chi khac | G44: =C44*E44 -> 50 | H44: Trà
A45: Tuần 3 | G45: =C45*E45 -> 0 | J45: =sum(G31:G44) -> 3139
A46: 45984 | B46: hàng thầy | C46: 1 | D46: lần | E46: 115 | F46: Hàng của thầy | G46: =C46*E46 -> 115 | H46: Tuấn
B47: xăng xe tuấn | C47: 1 | D47: lần | E47: 50 | F47: Xăng xe ca | G47: =C47*E47 -> 50 | H47: Tuấn
B48: gà, bí, khoai | C48: 1 | D48: túi | E48: 80 | F48: Thuc an cho thu luu tru | G48: =C48*E48 -> 80 | H48: Tuấn
B49: keo 502 | C49: 5 | D49: lọ | E49: 5 | F49: Hoa chat | G49: =C49*E49 -> 25 | H49: Ánh
B50: hoa hảo táng | C50: 1 | D50: bó | E50: 40 | F50: Hỏa táng | G50: =C50*E50 -> 40 | H50: Ánh
B51: thuốc fip | C51: 1 | D51: chai | E51: 400 | F51: Thuoc dieu tri | G51: =C51*E51 -> 400 | H51: Ánh
B52: găng tay nilon | C52: 10 | D52: gói | E52: 6 | F52: Chi khac | G52: =C52*E52 -> 60 | H52: Ánh
B53: túi zip | C53: 1 | D53: kg | E53: 65 | F53: Chi khac | G53: =C53*E53 -> 65 | H53: Ánh
B54: chà khay | C54: 2 | D54: cái | E54: 15 | F54: Chi khac | G54: =C54*E54 -> 30 | H54: Ánh
B55: dép | C55: 2 | D55: cái | E55: 20 | F55: Chi khac | G55: =C55*E55 -> 40 | H55: Ánh
B56: dép | C56: 3 | D56: cái | E56: 25 | F56: Chi khac | G56: =C56*E56 -> 75 | H56: Ánh
B57: gạo | C57: 10 | D57: kg | E57: 13.5 | F57: Thuc an cho thu luu tru | G57: =C57*E57 -> 135 | H57: Ánh
B58: bí, khoai | C58: 1 | D58: túi | E58: 43 | F58: Thuc an cho thu luu tru | G58: =C58*E58 -> 43 | H58: Ánh
... B65: ức gà | C65: 1 | D65: túi | E65: 43 | F65: Thuc an cho thu luu tru | G65: =C65*E65 -> 43 | H65: Ánh
B66: pin | C66: 1 | D66: cái | E66: 7 | F66: Chi khac | G66: =C66*E66 -> 7 | I66: sv P.Anh
B67: giấy vs | C67: 3 | D67: lốc | E67: 38 | F67: Chi khac | G67: =C67*E67 -> 114 | I67: sv Lộc
B68: găng tay cao su | C68: 10 | D68: hộp | E68: 48.2 | F68: Vat tu | G68: =C68*E68 -> 482 | H68: Ánh
B69: xăng xe ca ánh | C69: 1 | D69: lần | E69: 50 | F69: Xăng xe ca | G69: =C69*E69 -> 50 | H69: Ánh
B70: pate mèo lon | C70: 1 | D70: lon | E70: 40 | F70: Thuc an cho thu luu tru | G70: =C70*E70 -> 40 | H70: Trà
B71: pate chó lon | C71: 1 | D71: lon | E71: 31 | F71: Thuc an cho thu luu tru | G71: =C71*E71 -> 31 | H71: Ánh
B72: hương | C72: 1 | D72: bó | E72: 10 | F72: Hỏa táng | G72: =C72*E72 -> 10 | H72: Ánh
B73: sanpet | C73: 2 | D73: hộp | E73: 350 | F73: Thuoc dieu tri | G73: =C73*E73 -> 700 | H73: Thầy
B74: thuốc fip | C74: 1 | D74: chai | E74: 250 | F74: Thuoc dieu tri | G74: =C74*E74 -> 250 | H74: Ánh
A75: Tuần 4 | G75: =C75*E75 -> 0 | J75: =sum(G46:G75) -> 3534
G76: =C76*E76 -> 0
G77: =C77*E77 -> 0
G78: =C78*E78 -> 0
G79: =C79*E79 -> 0
G80: =C80*E80 -> 0
G81: =C81*E81 -> 0
G82: =C82*E82 -> 0
G83: =C83*E83 -> 0
G84: =C84*E84 -> 0
G85: =C85*E85 -> 0
G86: =C86*E86 -> 0
G87: =C87*E87 -> 0
... G273: =C273*E273 -> 0

Sheet Can doi thu chi
B1: Can doi thu chi | E1: Petshop
B2: Thu | C2: Chi tuần | D2: đã nhận | E2: Doanh thu tháng | F2: 6887196
A3: Tuần 1 | B3: ='BC Thang'!Q91 -> 25820 | C3: ='Danh muc Chi'!J9 -> 2798 | E3: Doanh thu thuần | F3: 6887196
A4: Tuần 2 | B4: ='BC Thang'!Q174 -> 42242 | C4: ='Danh muc Chi'!J30 -> 1731.5 | E4: Giá vốn | F4: 4535810
A5: Tuần 3 | B5: ='BC Thang'!Q298 -> 29855 | C5: ='Danh muc Chi'!J45 -> 3139 | E5: Lợi nhuận | F5: =F2-F4 -> 2351386
A6: Tuần 4 | B6: ='BC Thang'!Q428 -> 24313 | C6: ='Danh muc Chi'!J75 -> 3534 | F6: Thu petshop | G6: Chi petshop (xuất chuyển cơ sở)
A7: chuyển khoản petshop(báo cáo) | B7: =SuMIFS('BC Thang'!M4:M2974,'BC Thang'!N4:N2974,"CK petshop Thầy") -> 2816 | C7: ='Danh muc Chi'!J117 | E7: Tổng | F7: 6887 | G7: ='Chi petshop'!G1 -> 0
A8: Tổng | B8: =SUM(B3:B6)-B7 -> 119414 | C8: =SUM(C3:C7) -> 11202.5 | D8: =sum(D3:D6) -> 0 | E8: Chuyển khoản thầy (Petshop) | G8: =SuMIFS('BC Thang'!M4:M2974,'BC Thang'!N4:N2974,"CK petshop Thầy") -> 2816
A9: Thầy chi | B9: =SUMIFS('Danh muc Chi'!G3:G807,'Danh muc Chi'!H3:H807,"Thầy") -> 700 | E9: Tổng gửi thầy petshop | F9: =F7-G8 -> 4071
A10: Thầy nhận trực tiếp | C10: =SuMIFS('BC Thang'!M4:M2974,'BC Thang'!N4:N2974,"Thầy") -> 60
A11: Chuyển khoản thầy (khám chữa bệnh) | C11: =SuMIFS('BC Thang'!M4:M2974,'BC Thang'!N4:N2974,"CK Thầy") -> 95550
A13: Tiền nhà
A14: Tổng gửi thầy báo cáo | B14: =(B8+B9-C8-C10-C11-C13) -> 13301.5
A15: Gửi thầy cuối tháng Báo cáo + petshop | B15: =B14+F9 -> 17372.5 | C15: Chenh lech | D15: =C25-B15 -> -11.5
A16: 500 | B16: 17 | C16: =A16*B16 -> 8500
A17: 200 | B17: 13 | C17: =A17*B17 -> 2600
A18: 100 | B18: 57 | C18: =A18*B18 -> 5700
A19: 50 | B19: 11 | C19: =A19*B19 -> 550
A20: 20 | C20: =A20*B20 -> 0
A21: 10 | B21: 1 | C21: =A21*B21 -> 10
A22: 5 | C22: =A22*B22 -> 0
A23: 2 | C23: =A23*B23 -> 0
A24: 1 | B24: 1 | C24: =A24*B24 -> 1
A25: Nhận tiền mặt | B25: =SUM(B16:B24) -> 100 | C25: =sum(C16:C24) -> 17361

Sheet Chi petshop
G1: =sum(G3:G60) -> 0
A2: Ngày | B2: Nội dung petshop | C2: Số lượng | D2: Đơn vị tính | E2: Đơn giá | F2: Thuộc hạng mục | G2: Số tiền | H2: Người chi | I2: Chú ý | J2: Tổng chi theo tuần/tháng
F3: Petshop | G3: =C3*E3 -> 0
F4: Petshop | G4: =C4*E4 -> 0
F5: Petshop | G5: =C5*E5 -> 0
F6: Petshop | G6: =C6*E6 -> 0
F7: Petshop | G7: =C7*E7 -> 0
F8: Petshop | G8: =C8*E8 -> 0
F9: Petshop | G9: =C9*E9 -> 0
F10: Petshop | G10: =C10*E10 -> 0
F11: Petshop | G11: =C11*E11 -> 0
F12: Petshop | G12: =C12*E12 -> 0
F13: Petshop | G13: =C13*E13 -> 0
F14: Petshop | G14: =C14*E14 -> 0
... F948: Petshop | G948: =C948*E948 -> 0

Sheet BC Vat Tu
E1: SL Tồn đầu tháng | F1: =sum(F3:F333) -> 89110302 | G1: Nhập | L1: =sum(L3:L300) -> 3350466.7 | N1: Xuất chuyển CS | R1: =sum(R3:R300) -> 0 | T1: Tổng | U1: =sum(U3:U223) -> 15726210 | V1: =sum(V3:V310) -> 76734558
A2: =IFERROR(__xludf.DUMMYFUNCTION("importrange(""https://docs.google.com/spreadsheets/d/1ImCdkYhsUqsakZA8jNZp7UrWFPNTrMyfZQst-0aGkKM/edit#gid=510873834"",""Ma hang!A1:D500"")"),"Mã Hàng") -> Mã Hàng | B2: =IFERROR(__xludf.DUMMYFUNCTION("""COMPUTED_VALUE"""),"Tên hàng") -> Tên hàng | C2: =IFERROR(__xludf.DUMMYFUNCTION("""COMPUTED_VALUE"""),"Đơn vị Tính") -> Đơn vị Tính | D2: =IFERROR(__xludf.DUMMYFUNCTION("""COMPUTED_VALUE"""),"Giá nhập TB") -> Giá nhập TB | E2: 45962 | F2: Tiền tồn đầu tháng | G2: Tuần 1 | H2: Tuần 2 | I2: Tuần 3 | J2: Tuần 4 | K2: Tổng SL Nhập | L2: Tổng tiền nhập | M2: Tuần 1 | N2: Tuần 2 | O2: Tuần 3 | P2: Tuần 4 | Q2: Tổng SL Xuất | R2: Tổng tiền xuất | S2: Kiêm kê (tồn cuối) | T2: SL SD trong tháng | U2: Tiền SD trong tháng | V2: Số tiền tồn cuối
A3: =IFERROR(__xludf.DUMMYFUNCTION("""COMPUTED_VALUE"""),"APC") -> APC | B3: =IFERROR(__xludf.DUMMYFUNCTION("""COMPUTED_VALUE"""),"A chymotrypsin") -> A chymotrypsin | C3: =IFERROR(__xludf.DUMMYFUNCTION("""COMPUTED_VALUE"""),"Viên") -> Viên | D3: =IFERROR(__xludf.DUMMYFUNCTION("""COMPUTED_VALUE"""),250.0) -> 250 | E3: 435 | F3: =E3*$D3 -> 108750 | K3: =G3+H3+I3+J3 -> 0 | L3: =K3*$D3 -> 0 | Q3: =M3+N3+O3+P3 -> 0 | R3: =Q3*$D3 -> 0 | S3: =220+100+22 -> 342 | T3: =E3+K3-Q3-S3 -> 93 | U3: =T3*D3 -> 23250 | V3: =S3*$D3 -> 85500
A4: =IFERROR(__xludf.DUMMYFUNCTION("""COMPUTED_VALUE"""),"ACV") -> ACV | B4: =IFERROR(__xludf.DUMMYFUNCTION("""COMPUTED_VALUE"""),"Acyclovir 200") -> Acyclovir 200 | C4: =IFERROR(__xludf.DUMMYFUNCTION("""COMPUTED_VALUE"""),"Viên") -> Viên | D4: =IFERROR(__xludf.DUMMYFUNCTION("""COMPUTED_VALUE"""),2414.285714285714) -> 2414.2857 | E4: 34 | F4: =E4*$D4 -> 82085.714 | K4: =G4+H4+I4+J4 -> 0 | L4: =K4*$D4 -> 0 | Q4: =M4+N4+O4+P4 -> 0 | R4: =Q4*$D4 -> 0 | S4: 34 | T4: =E4+K4-Q4-S4 -> 0 | U4: =T4*D4 -> 0 | V4: =S4*$D4 -> 82085.714
A5: =IFERROR(__xludf.DUMMYFUNCTION("""COMPUTED_VALUE"""),"ADEVTM") -> ADEVTM | B5: =IFERROR(__xludf.DUMMYFUNCTION("""COMPUTED_VALUE"""),"AD3E Vitamin") -> AD3E Vitamin | C5: =IFERROR(__xludf.DUMMYFUNCTION("""COMPUTED_VALUE"""),"mL") -> mL | D5: =IFERROR(__xludf.DUMMYFUNCTION("""COMPUTED_VALUE"""),1400.0) -> 1400 | E5: 150 | F5: =E5*$D5 -> 210000 | K5: =G5+H5+I5+J5 -> 0 | L5: =K5*$D5 -> 0 | Q5: =M5+N5+O5+P5 -> 0 | R5: =Q5*$D5 -> 0 | S5: 150 | T5: =E5+K5-Q5-S5 -> 0 | U5: =T5*D5 -> 0 | V5: =S5*$D5 -> 210000
A6: =IFERROR(__xludf.DUMMYFUNCTION("""COMPUTED_VALUE"""),"TKADL") -> TKADL | B6: =IFERROR(__xludf.DUMMYFUNCTION("""COMPUTED_VALUE"""),"Adrenalin") -> Adrenalin | C6: =IFERROR(__xludf.DUMMYFUNCTION("""COMPUTED_VALUE"""),"Ống") -> Ống | D6: =IFERROR(__xludf.DUMMYFUNCTION("""COMPUTED_VALUE"""),3000.0) -> 3000 | E6: 61 | F6: =E6*$D6 -> 183000 | K6: =G6+H6+I6+J6 -> 0 | L6: =K6*$D6 -> 0 | Q6: =M6+N6+O6+P6 -> 0 | R6: =Q6*$D6 -> 0 | S6: 0 | T6: =E6+K6-Q6-S6 -> 61 | U6: =T6*D6 -> 183000 | V6: =S6*$D6 -> 0
A7: =IFERROR(__xludf.DUMMYFUNCTION("""COMPUTED_VALUE"""),"AMVTM") -> AMVTM | B7: =IFERROR(__xludf.DUMMYFUNCTION("""COMPUTED_VALUE"""),"Aminovit") -> Aminovit | C7: =IFERROR(__xludf.DUMMYFUNCTION("""COMPUTED_VALUE"""),"mL") -> mL | D7: =IFERROR(__xludf.DUMMYFUNCTION("""COMPUTED_VALUE"""),300.0) -> 300 | E7: 0 | F7: =E7*$D7 -> 0 | K7: =G7+H7+I7+J7 -> 0 | L7: =K7*$D7 -> 0 | Q7: =M7+N7+O7+P7 -> 0 | R7: =Q7*$D7 -> 0 | S7: 0 | T7: =E7+K7-Q7-S7 -> 0 | U7: =T7*D7 -> 0 | V7: =S7*$D7 -> 0
A8: =IFERROR(__xludf.DUMMYFUNCTION("""COMPUTED_VALUE"""),"AMOX") -> AMOX | B8: =IFERROR(__xludf.DUMMYFUNCTION("""COMPUTED_VALUE"""),"Amoxicilin 250ml") -> Amoxicilin 250ml | C8: =IFERROR(__xludf.DUMMYFUNCTION("""COMPUTED_VALUE"""),"mL") -> mL | D8: =IFERROR(__xludf.DUMMYFUNCTION("""COMPUTED_VALUE"""),0.0) -> 0 | E8: 50 | F8: =E8*$D8 -> 0 | K8: =G8+H8+I8+J8 -> 0 | L8: =K8*$D8 -> 0 | Q8: =M8+N8+O8+P8 -> 0 | R8: =Q8*$D8 -> 0 | S8: 50 | T8: =E8+K8-Q8-S8 -> 0 | U8: =T8*D8 -> 0 | V8: =S8*$D8 -> 0
A9: =IFERROR(__xludf.DUMMYFUNCTION("""COMPUTED_VALUE"""),"ATD") -> ATD | B9: =IFERROR(__xludf.DUMMYFUNCTION("""COMPUTED_VALUE"""),"Antiderm bôi ghẻ") -> Antiderm bôi ghẻ | C9: =IFERROR(__xludf.DUMMYFUNCTION("""COMPUTED_VALUE"""),"Tuýp") -> Tuýp | D9: =IFERROR(__xludf.DUMMYFUNCTION("""COMPUTED_VALUE"""),35000.0) -> 35000 | E9: 0 | F9: =E9*$D9 -> 0 | K9: =G9+H9+I9+J9 -> 0 | L9: =K9*$D9 -> 0 | Q9: =M9+N9+O9+P9 -> 0 | R9: =Q9*$D9 -> 0 | S9: 0 | T9: =E9+K9-Q9-S9 -> 0 | U9: =T9*D9 -> 0 | V9: =S9*$D9 -> 0
A10: =IFERROR(__xludf.DUMMYFUNCTION("""COMPUTED_VALUE"""),"APT") -> APT | B10: =IFERROR(__xludf.DUMMYFUNCTION("""COMPUTED_VALUE"""),"Áo phẫu thuật") -> Áo phẫu thuật | C10: =IFERROR(__xludf.DUMMYFUNCTION("""COMPUTED_VALUE"""),"Cái") -> Cái | D10: =IFERROR(__xludf.DUMMYFUNCTION("""COMPUTED_VALUE"""),300000.0) -> 300000 | E10: 54 | F10: =E10*$D10 -> 16200000 | K10: =G10+H10+I10+J10 -> 0 | L10: =K10*$D10 -> 0 | Q10: =M10+N10+O10+P10 -> 0 | R10: =Q10*$D10 -> 0 | S10: 50 | T10: =E10+K10-Q10-S10 -> 4 | U10: =T10*D10 -> 1200000 | V10: =S10*$D10 -> 15000000
A11: =IFERROR(__xludf.DUMMYFUNCTION("""COMPUTED_VALUE"""),"ATP") -> ATP | B11: =IFERROR(__xludf.DUMMYFUNCTION("""COMPUTED_VALUE"""),"Atropin") -> Atropin | C11: =IFERROR(__xludf.DUMMYFUNCTION("""COMPUTED_VALUE"""),"mL") -> mL | D11: =IFERROR(__xludf.DUMMYFUNCTION("""COMPUTED_VALUE"""),163.33333333333334) -> 163.33333 | E11: 168 | F11: =E11*$D11 -> 27440 | J11: 200 | K11: =G11+H11+I11+J11 -> 200 | L11: =K11*$D11 -> 32666.667 | Q11: =M11+N11+O11+P11 -> 0 | R11: =Q11*$D11 -> 0 | S11: =200+58+85 -> 343 | T11: =E11+K11-Q11-S11 -> 25 | U11: =T11*D11 -> 4083.3333 | V11: =S11*$D11 -> 56023.333
A12: =IFERROR(__xludf.DUMMYFUNCTION("""COMPUTED_VALUE"""),"AZT") -> AZT | B12: =IFERROR(__xludf.DUMMYFUNCTION("""COMPUTED_VALUE"""),"Azithromycin ") -> Azithromycin | C12: =IFERROR(__xludf.DUMMYFUNCTION("""COMPUTED_VALUE"""),"Gam") -> Gam | D12: =IFERROR(__xludf.DUMMYFUNCTION("""COMPUTED_VALUE"""),20000.0) -> 20000 | E12: 25 | F12: =E12*$D12 -> 500000 | K12: =G12+H12+I12+J12 -> 0 | L12: =K12*$D12 -> 0 | Q12: =M12+N12+O12+P12 -> 0 | R12: =Q12*$D12 -> 0 | S12: 25 | T12: =E12+K12-Q12-S12 -> 0 | U12: =T12*D12 -> 0 | V12: =S12*$D12 -> 500000
A13: =IFERROR(__xludf.DUMMYFUNCTION("""COMPUTED_VALUE"""),"AZT250") -> AZT250 | B13: =IFERROR(__xludf.DUMMYFUNCTION("""COMPUTED_VALUE"""),"Azithromycin 250mg") -> Azithromycin 250mg | C13: =IFERROR(__xludf.DUMMYFUNCTION("""COMPUTED_VALUE"""),"Viên") -> Viên | D13: =IFERROR(__xludf.DUMMYFUNCTION("""COMPUTED_VALUE"""),1950.0) -> 1950 | E13: 6 | F13: =E13*$D13 -> 11700 | K13: =G13+H13+I13+J13 -> 0 | L13: =K13*$D13 -> 0 | Q13: =M13+N13+O13+P13 -> 0 | R13: =Q13*$D13 -> 0 | S13: 6 | T13: =E13+K13-Q13-S13 -> 0 | U13: =T13*D13 -> 0 | V13: =S13*$D13 -> 11700
A14: =IFERROR(__xludf.DUMMYFUNCTION("""COMPUTED_VALUE"""),"AZT500") -> AZT500 | B14: =IFERROR(__xludf.DUMMYFUNCTION("""COMPUTED_VALUE"""),"Azithromycin 500mg") -> Azithromycin 500mg | C14: =IFERROR(__xludf.DUMMYFUNCTION("""COMPUTED_VALUE"""),"Viên") -> Viên | D14: =IFERROR(__xludf.DUMMYFUNCTION("""COMPUTED_VALUE"""),4683.166666666666) -> 4683.1667 | E14: 2 | F14: =E14*$D14 -> 9366.3333 | K14: =G14+H14+I14+J14 -> 0 | L14: =K14*$D14 -> 0 | Q14: =M14+N14+O14+P14 -> 0 | R14: =Q14*$D14 -> 0 | S14: 2 | T14: =E14+K14-Q14-S14 -> 0 | U14: =T14*D14 -> 0 | V14: =S14*$D14 -> 9366.3333
A15: =IFERROR(__xludf.DUMMYFUNCTION("""COMPUTED_VALUE"""),"BCL") -> BCL | B15: =IFERROR(__xludf.DUMMYFUNCTION("""COMPUTED_VALUE"""),"B complex") -> B complex | C15: =IFERROR(__xludf.DUMMYFUNCTION("""COMPUTED_VALUE"""),"ml") -> ml | D15: =IFERROR(__xludf.DUMMYFUNCTION("""COMPUTED_VALUE"""),300.0) -> 300 | E15: 160 | F15: =E15*$D15 -> 48000 | K15: =G15+H15+I15+J15 -> 0 | L15: =K15*$D15 -> 0 | Q15: =M15+N15+O15+P15 -> 0 | R15: =Q15*$D15 -> 0 | S15: 160 | T15: =E15+K15-Q15-S15 -> 0 | U15: =T15*D15 -> 0 | V15: =S15*$D15 -> 48000
A16: =IFERROR(__xludf.DUMMYFUNCTION("""COMPUTED_VALUE"""),"BCRT") -> BCRT | B16: =IFERROR(__xludf.DUMMYFUNCTION("""COMPUTED_VALUE"""),"Bàn chải rửa tay") -> Bàn chải rửa tay | C16: =IFERROR(__xludf.DUMMYFUNCTION("""COMPUTED_VALUE"""),"Cái") -> Cái | D16: =IFERROR(__xludf.DUMMYFUNCTION("""COMPUTED_VALUE"""),38000.0) -> 38000 | E16: 0 | F16: =E16*$D16 -> 0 | K16: =G16+H16+I16+J16 -> 0 | L16: =K16*$D16 -> 0 | Q16: =M16+N16+O16+P16 -> 0 | R16: =Q16*$D16 -> 0 | S16: 0 | T16: =E16+K16-Q16-S16 -> 0 | U16: =T16*D16 -> 0 | V16: =S16*$D16 -> 0
A17: =IFERROR(__xludf.DUMMYFUNCTION("""COMPUTED_VALUE"""),"BIOGTT") -> BIOGTT | B17: =IFERROR(__xludf.DUMMYFUNCTION("""COMPUTED_VALUE"""),"BIO Genta-Tylosin") -> BIO Genta-Tylosin | C17: =IFERROR(__xludf.DUMMYFUNCTION("""COMPUTED_VALUE"""),"mL") -> mL | D17: =IFERROR(__xludf.DUMMYFUNCTION("""COMPUTED_VALUE"""),1100.0) -> 1100 | E17: 71 | F17: =E17*$D17 -> 78100 | K17: =G17+H17+I17+J17 -> 0 | L17: =K17*$D17 -> 0 | Q17: =M17+N17+O17+P17 -> 0 | R17: =Q17*$D17 -> 0 | S17: 60 | T17: =E17+K17-Q17-S17 -> 11 | U17: =T17*D17 -> 12100 | V17: =S17*$D17 -> 66000
A18: =IFERROR(__xludf.DUMMYFUNCTION("""COMPUTED_VALUE"""),"OCTC") -> OCTC | B18: =IFERROR(__xludf.DUMMYFUNCTION("""COMPUTED_VALUE"""),"BIO Oxytocin") -> BIO Oxytocin | C18: =IFERROR(__xludf.DUMMYFUNCTION("""COMPUTED_VALUE"""),"mL") -> mL | D18: =IFERROR(__xludf.DUMMYFUNCTION("""COMPUTED_VALUE"""),600.0) -> 600 | E18: 40 | F18: =E18*$D18 -> 24000 | K18: =G18+H18+I18+J18 -> 0 | L18: =K18*$D18 -> 0 | Q18: =M18+N18+O18+P18 -> 0 | R18: =Q18*$D18 -> 0 | S18: 40 | T18: =E18+K18-Q18-S18 -> 0 | U18: =T18*D18 -> 0 | V18: =S18*$D18 -> 24000
A19: =IFERROR(__xludf.DUMMYFUNCTION("""COMPUTED_VALUE"""),"BS") -> BS | B19: =IFERROR(__xludf.DUMMYFUNCTION("""COMPUTED_VALUE"""),"BIO sone") -> BIO sone | C19: =IFERROR(__xludf.DUMMYFUNCTION("""COMPUTED_VALUE"""),"mL") -> mL | D19: =IFERROR(__xludf.DUMMYFUNCTION("""COMPUTED_VALUE"""),1300.0) -> 1300 | E19: 120 | F19: =E19*$D19 -> 156000 | K19: =G19+H19+I19+J19 -> 0 | L19: =K19*$D19 -> 0 | Q19: =M19+N19+O19+P19 -> 0 | R19: =Q19*$D19 -> 0 | S19: 120 | T19: =E19+K19-Q19-S19 -> 0 | U19: =T19*D19 -> 0 | V19: =S19*$D19 -> 156000
A20: =IFERROR(__xludf.DUMMYFUNCTION("""COMPUTED_VALUE"""),"VTMB12T") -> VTMB12T | B20: =IFERROR(__xludf.DUMMYFUNCTION("""COMPUTED_VALUE"""),"BIO-FER+B12") -> BIO-FER+B12 | C20: =IFERROR(__xludf.DUMMYFUNCTION("""COMPUTED_VALUE"""),"mL") -> mL | D20: =IFERROR(__xludf.DUMMYFUNCTION("""COMPUTED_VALUE"""),500.0) -> 500 | E20: 68 | F20: =E20*$D20 -> 34000 | K20: =G20+H20+I20+J20 -> 0 | L20: =K20*$D20 -> 0 | Q20: =M20+N20+O20+P20 -> 0 | R20: =Q20*$D20 -> 0 | S20: 60 | T20: =E20+K20-Q20-S20 -> 8 | U20: =T20*D20 -> 4000 | V20: =S20*$D20 -> 30000
A21: =IFERROR(__xludf.DUMMYFUNCTION("""COMPUTED_VALUE"""),"BTC") -> BTC | B21: =IFERROR(__xludf.DUMMYFUNCTION("""COMPUTED_VALUE"""),"Bột thạch cao") -> Bột thạch cao | C21: =IFERROR(__xludf.DUMMYFUNCTION("""COMPUTED_VALUE"""),"cuộn") -> cuộn | D21: =IFERROR(__xludf.DUMMYFUNCTION("""COMPUTED_VALUE"""),15000.0) -> 15000 | E21: 4 | F21: =E21*$D21 -> 60000 | K21: =G21+H21+I21+J21 -> 0 | L21: =K21*$D21 -> 0 | Q21: =M21+N21+O21+P21 -> 0 | R21: =Q21*$D21 -> 0 | S21: 4 | T21: =E21+K21-Q21-S21 -> 0 | U21: =T21*D21 -> 0 | V21: =S21*$D21 -> 60000
A22: =IFERROR(__xludf.DUMMYFUNCTION("""COMPUTED_VALUE"""),"BHXT") -> BHXT | B22: =IFERROR(__xludf.DUMMYFUNCTION("""COMPUTED_VALUE"""),"Bromhexine tiêm") -> Bromhexine tiêm | C22: =IFERROR(__xludf.DUMMYFUNCTION("""COMPUTED_VALUE"""),"mL") -> mL | D22: =IFERROR(__xludf.DUMMYFUNCTION("""COMPUTED_VALUE"""),1000.0) -> 1000 | E22: 140 | F22: =E22*$D22 -> 140000 | K22: =G22+H22+I22+J22 -> 0 | L22: =K22*$D22 -> 0 | Q22: =M22+N22+O22+P22 -> 0 | R22: =Q22*$D22 -> 0 | S22: 140 | T22: =E22+K22-Q22-S22 -> 0 | U22: =T22*D22 -> 0 | V22: =S22*$D22 -> 140000
A23: =IFERROR(__xludf.DUMMYFUNCTION("""COMPUTED_VALUE"""),"BHXU") -> BHXU | B23: =IFERROR(__xludf.DUMMYFUNCTION("""COMPUTED_VALUE"""),"Bromhexine uống") -> Bromhexine uống | C23: =IFERROR(__xludf.DUMMYFUNCTION("""COMPUTED_VALUE"""),"Viên") -> Viên | D23: =IFERROR(__xludf.DUMMYFUNCTION("""COMPUTED_VALUE"""),180.0) -> 180 | E23: 193 | F23: =E23*$D23 -> 34740 | K23: =G23+H23+I23+J23 -> 0 | L23: =K23*$D23 -> 0 | Q23: =M23+N23+O23+P23 -> 0 | R23: =Q23*$D23 -> 0 | S23: =136+49 -> 185 | T23: =E23+K23-Q23-S23 -> 8 | U23: =T23*D23 -> 1440 | V23: =S23*$D23 -> 33300
A24: =IFERROR(__xludf.DUMMYFUNCTION("""COMPUTED_VALUE"""),"CX") -> CX | B24: =IFERROR(__xludf.DUMMYFUNCTION("""COMPUTED_VALUE"""),"Canxi") -> Canxi | C24: =IFERROR(__xludf.DUMMYFUNCTION("""COMPUTED_VALUE"""),"Viên") -> Viên | D24: =IFERROR(__xludf.DUMMYFUNCTION("""COMPUTED_VALUE"""),230.0) -> 230 | E24: 13 | F24: =E24*$D24 -> 2990 | K24: =G24+H24+I24+J24 -> 0 | L24: =K24*$D24 -> 0 | Q24: =M24+N24+O24+P24 -> 0 | R24: =Q24*$D24 -> 0 | S24: 6 | T24: =E24+K24-Q24-S24 -> 7 | U24: =T24*D24 -> 1610 | V24: =S24*$D24 -> 1380
A25: =IFERROR(__xludf.DUMMYFUNCTION("""COMPUTED_VALUE"""),"CXT") -> CXT | B25: =IFERROR(__xludf.DUMMYFUNCTION("""COMPUTED_VALUE"""),"Canxi tiêm") -> Canxi tiêm | C25: =IFERROR(__xludf.DUMMYFUNCTION("""COMPUTED_VALUE"""),"mL") -> mL | D25: =IFERROR(__xludf.DUMMYFUNCTION("""COMPUTED_VALUE"""),425.0) -> 425 | E25: 25 | F25: =E25*$D25 -> 10625 | K25: =G25+H25+I25+J25 -> 0 | L25: =K25*$D25 -> 0 | Q25: =M25+N25+O25+P25 -> 0 | R25: =Q25*$D25 -> 0 | S25: 13 | T25: =E25+K25-Q25-S25 -> 12 | U25: =T25*D25 -> 5100 | V25: =S25*$D25 -> 5525
A26: =IFERROR(__xludf.DUMMYFUNCTION("""COMPUTED_VALUE"""),"CSTAN") -> CSTAN | B26: =IFERROR(__xludf.DUMMYFUNCTION("""COMPUTED_VALUE"""),"CasTran an thần") -> CasTran an thần | C26: =IFERROR(__xludf.DUMMYFUNCTION("""COMPUTED_VALUE"""),"mL") -> mL | D26: =IFERROR(__xludf.DUMMYFUNCTION("""COMPUTED_VALUE"""),1200.0) -> 1200 | E26: 0 | F26: =E26*$D26 -> 0 | K26: =G26+H26+I26+J26 -> 0 | L26: =K26*$D26 -> 0 | Q26: =M26+N26+O26+P26 -> 0 | R26: =Q26*$D26 -> 0 | S26: 0 | T26: =E26+K26-Q26-S26 -> 0 | U26: =T26*D26 -> 0 | V26: =S26*$D26 -> 0
A27: =IFERROR(__xludf.DUMMYFUNCTION("""COMPUTED_VALUE"""),"CTZ") -> CTZ | B27: =IFERROR(__xludf.DUMMYFUNCTION("""COMPUTED_VALUE"""),"Ceftriazone_Cefuroxim (KS pha tiêm)") -> Ceftriazone_Cefuroxim (KS pha tiêm) | C27: =IFERROR(__xludf.DUMMYFUNCTION("""COMPUTED_VALUE"""),"Gam") -> Gam | D27: =IFERROR(__xludf.DUMMYFUNCTION("""COMPUTED_VALUE"""),20000.0) -> 20000 | E27: 0 | F27: =E27*$D27 -> 0 | K27: =G27+H27+I27+J27 -> 0 | L27: =K27*$D27 -> 0 | Q27: =M27+N27+O27+P27 -> 0 | R27: =Q27*$D27 -> 0 | S27: 0 | T27: =E27+K27-Q27-S27 -> 0 | U27: =T27*D27 -> 0 | V27: =S27*$D27 -> 0
A28: =IFERROR(__xludf.DUMMYFUNCTION("""COMPUTED_VALUE"""),"CF500") -> CF500 | B28: =IFERROR(__xludf.DUMMYFUNCTION("""COMPUTED_VALUE"""),"Cephalexin 500") -> Cephalexin 500 | C28: =IFERROR(__xludf.DUMMYFUNCTION("""COMPUTED_VALUE"""),"Viên") -> Viên | D28: =IFERROR(__xludf.DUMMYFUNCTION("""COMPUTED_VALUE"""),1200.0) -> 1200 | E28: 184 | F28: =E28*$D28 -> 220800 | H28: 100 | K28: =G28+H28+I28+J28 -> 100 | L28: =K28*$D28 -> 120000 | Q28: =M28+N28+O28+P28 -> 0 | R28: =Q28*$D28 -> 0 | S28: 100 | T28: =E28+K28-Q28-S28 -> 184 | U28: =T28*D28 -> 220800 | V28: =S28*$D28 -> 120000
A29: =IFERROR(__xludf.DUMMYFUNCTION("""COMPUTED_VALUE"""),"CTRZ") -> CTRZ | B29: =IFERROR(__xludf.DUMMYFUNCTION("""COMPUTED_VALUE"""),"Cetirizin") -> Cetirizin | C29: =IFERROR(__xludf.DUMMYFUNCTION("""COMPUTED_VALUE"""),"Viên") -> Viên | D29: =IFERROR(__xludf.DUMMYFUNCTION("""COMPUTED_VALUE"""),200.0) -> 200 | E29: 85 | F29: =E29*$D29 -> 17000 | K29: =G29+H29+I29+J29 -> 0 | L29: =K29*$D29 -> 0 | Q29: =M29+N29+O29+P29 -> 0 | R29: =Q29*$D29 -> 0 | S29: 85 | T29: =E29+K29-Q29-S29 -> 0 | U29: =T29*D29 -> 0 | V29: =S29*$D29 -> 17000
A30: =IFERROR(__xludf.DUMMYFUNCTION("""COMPUTED_VALUE"""),"CDTT") -> CDTT | B30: =IFERROR(__xludf.DUMMYFUNCTION("""COMPUTED_VALUE"""),"Chai đựng thuốc tắm") -> Chai đựng thuốc tắm | C30: =IFERROR(__xludf.DUMMYFUNCTION("""COMPUTED_VALUE"""),"Chai") -> Chai | D30: =IFERROR(__xludf.DUMMYFUNCTION("""COMPUTED_VALUE"""),1200.0) -> 1200 | E30: 29 | F30: =E30*$D30 -> 34800 | K30: =G30+H30+I30+J30 -> 0 | L30: =K30*$D30 -> 0 | Q30: =M30+N30+O30+P30 -> 0 | R30: =Q30*$D30 -> 0 | S30: 15 | T30: =E30+K30-Q30-S30 -> 14 | U30: =T30*D30 -> 16800 | V30: =S30*$D30 -> 18000
A31: =IFERROR(__xludf.DUMMYFUNCTION("""COMPUTED_VALUE"""),"CKCG2/0") -> CKCG2/0 | B31: =IFERROR(__xludf.DUMMYFUNCTION("""COMPUTED_VALUE"""),"Chỉ catgut 2/0") -> Chỉ catgut 2/0 | C31: =IFERROR(__xludf.DUMMYFUNCTION("""COMPUTED_VALUE"""),"Sợi") -> Sợi | D31: =IFERROR(__xludf.DUMMYFUNCTION("""COMPUTED_VALUE"""),10000.0) -> 10000 | E31: 0 | F31: =E31*$D31 -> 0 | K31: =G31+H31+I31+J31 -> 0 | L31: =K31*$D31 -> 0 | Q31: =M31+N31+O31+P31 -> 0 | R31: =Q31*$D31 -> 0 | S31: 0 | T31: =E31+K31-Q31-S31 -> 0 | U31: =T31*D31 -> 0 | V31: =S31*$D31 -> 0
A32: =IFERROR(__xludf.DUMMYFUNCTION("""COMPUTED_VALUE"""),"CKCG3/0") -> CKCG3/0 | B32: =IFERROR(__xludf.DUMMYFUNCTION("""COMPUTED_VALUE"""),"Chỉ catgut 3/0") -> Chỉ catgut 3/0 | C32: =IFERROR(__xludf.DUMMYFUNCTION("""COMPUTED_VALUE"""),"Sợi") -> Sợi | D32: =IFERROR(__xludf.DUMMYFUNCTION("""COMPUTED_VALUE"""),10000.0) -> 10000 | E32: 0 | F32: =E32*$D32 -> 0 | K32: =G32+H32+I32+J32 -> 0 | L32: =K32*$D32 -> 0 | Q32: =M32+N32+O32+P32 -> 0 | R32: =Q32*$D32 -> 0 | S32: 0 | T32: =E32+K32-Q32-S32 -> 0 | U32: =T32*D32 -> 0 | V32: =S32*$D32 -> 0
A33: =IFERROR(__xludf.DUMMYFUNCTION("""COMPUTED_VALUE"""),"CKCG4/0") -> CKCG4/0 | B33: =IFERROR(__xludf.DUMMYFUNCTION("""COMPUTED_VALUE"""),"Chỉ catgut 4/0") -> Chỉ catgut 4/0 | C33: =IFERROR(__xludf.DUMMYFUNCTION("""COMPUTED_VALUE"""),"Sợi") -> Sợi | D33: =IFERROR(__xludf.DUMMYFUNCTION("""COMPUTED_VALUE"""),10000.0) -> 10000 | E33: 0 | F33: =E33*$D33 -> 0 | K33: =G33+H33+I33+J33 -> 0 | L33: =K33*$D33 -> 0 | Q33: =M33+N33+O33+P33 -> 0 | R33: =Q33*$D33 -> 0 | S33: 0 | T33: =E33+K33-Q33-S33 -> 0 | U33: =T33*D33 -> 0 | V33: =S33*$D33 -> 0
A34: =IFERROR(__xludf.DUMMYFUNCTION("""COMPUTED_VALUE"""),"CKCGKK") -> CKCGKK | B34: =IFERROR(__xludf.DUMMYFUNCTION("""COMPUTED_VALUE"""),"Chỉ catgut không kim") -> Chỉ catgut không kim | C34: =IFERROR(__xludf.DUMMYFUNCTION("""COMPUTED_VALUE"""),"Sợi") -> Sợi | D34: =IFERROR(__xludf.DUMMYFUNCTION("""COMPUTED_VALUE"""),2000.0) -> 2000 | E34: 0 | F34: =E34*$D34 -> 0 | K34: =G34+H34+I34+J34 -> 0 | L34: =K34*$D34 -> 0 | Q34: =M34+N34+O34+P34 -> 0 | R34: =Q34*$D34 -> 0 | S34: 0 | T34: =E34+K34-Q34-S34 -> 0 | U34: =T34*D34 -> 0 | V34: =S34*$D34 -> 0
A35: =IFERROR(__xludf.DUMMYFUNCTION("""COMPUTED_VALUE"""),"CKKTD") -> CKKTD | B35: =IFERROR(__xludf.DUMMYFUNCTION("""COMPUTED_VALUE"""),"Chỉ khâu không tiêu dù") -> Chỉ khâu không tiêu dù | C35: =IFERROR(__xludf.DUMMYFUNCTION("""COMPUTED_VALUE"""),"Mét") -> Mét | D35: =IFERROR(__xludf.DUMMYFUNCTION("""COMPUTED_VALUE"""),600.0) -> 600 | E35: 0 | F35: =E35*$D35 -> 0 | K35: =G35+H35+I35+J35 -> 0 | L35: =K35*$D35 -> 0 | Q35: =M35+N35+O35+P35 -> 0 | R35: =Q35*$D35 -> 0 | S35: 0 | T35: =E35+K35-Q35-S35 -> 0 | U35: =T35*D35 -> 0 | V35: =S35*$D35 -> 0
A36: =IFERROR(__xludf.DUMMYFUNCTION("""COMPUTED_VALUE"""),"VCRKK3/0") -> VCRKK3/0 | B36: =IFERROR(__xludf.DUMMYFUNCTION("""COMPUTED_VALUE"""),"Chỉ khâu Vicryl không kim 3/0") -> Chỉ khâu Vicryl không kim 3/0 | C36: =IFERROR(__xludf.DUMMYFUNCTION("""COMPUTED_VALUE"""),"Sợi") -> Sợi | D36: =IFERROR(__xludf.DUMMYFUNCTION("""COMPUTED_VALUE"""),4875.0) -> 4875 | E36: 0 | F36: =E36*$D36 -> 0 | K36: =G36+H36+I36+J36 -> 0 | L36: =K36*$D36 -> 0 | Q36: =M36+N36+O36+P36 -> 0 | R36: =Q36*$D36 -> 0 | S36: 0 | T36: =E36+K36-Q36-S36 -> 0 | U36: =T36*D36 -> 0 | V36: =S36*$D36 -> 0
A37: =IFERROR(__xludf.DUMMYFUNCTION("""COMPUTED_VALUE"""),"CKKT3/0KK") -> CKKT3/0KK | B37: =IFERROR(__xludf.DUMMYFUNCTION("""COMPUTED_VALUE"""),"Chỉ không tiêu 3/0 không kim") -> Chỉ không tiêu 3/0 không kim | C37: =IFERROR(__xludf.DUMMYFUNCTION("""COMPUTED_VALUE"""),"Sợi") -> Sợi | D37: =IFERROR(__xludf.DUMMYFUNCTION("""COMPUTED_VALUE"""),2000.0) -> 2000 | E37: 0 | F37: =E37*$D37 -> 0 | K37: =G37+H37+I37+J37 -> 0 | L37: =K37*$D37 -> 0 | Q37: =M37+N37+O37+P37 -> 0 | R37: =Q37*$D37 -> 0 | S37: 0 | T37: =E37+K37-Q37-S37 -> 0 | U37: =T37*D37 -> 0 | V37: =S37*$D37 -> 0
A38: =IFERROR(__xludf.DUMMYFUNCTION("""COMPUTED_VALUE"""),"CKNL10/0") -> CKNL10/0 | B38: =IFERROR(__xludf.DUMMYFUNCTION("""COMPUTED_VALUE"""),"Chỉ nilon 10/0") -> Chỉ nilon 10/0 | C38: =IFERROR(__xludf.DUMMYFUNCTION("""COMPUTED_VALUE"""),"Sợi") -> Sợi | D38: =IFERROR(__xludf.DUMMYFUNCTION("""COMPUTED_VALUE"""),60000.0) -> 60000 | E38: 0 | F38: =E38*$D38 -> 0 | K38: =G38+H38+I38+J38 -> 0 | L38: =K38*$D38 -> 0 | Q38: =M38+N38+O38+P38 -> 0 | R38: =Q38*$D38 -> 0 | S38: 0 | T38: =E38+K38-Q38-S38 -> 0 | U38: =T38*D38 -> 0 | V38: =S38*$D38 -> 0
A39: =IFERROR(__xludf.DUMMYFUNCTION("""COMPUTED_VALUE"""),"CKNL2/0") -> CKNL2/0 | B39: =IFERROR(__xludf.DUMMYFUNCTION("""COMPUTED_VALUE"""),"Chỉ nilon 2/0") -> Chỉ nilon 2/0 | C39: =IFERROR(__xludf.DUMMYFUNCTION("""COMPUTED_VALUE"""),"Sợi") -> Sợi | D39: =IFERROR(__xludf.DUMMYFUNCTION("""COMPUTED_VALUE"""),10000.0) -> 10000 | E39: 6 | F39: =E39*$D39 -> 60000 | K39: =G39+H39+I39+J39 -> 0 | L39: =K39*$D39 -> 0 | Q39: =M39+N39+O39+P39 -> 0 | R39: =Q39*$D39 -> 0 | S39: 6 | T39: =E39+K39-Q39-S39 -> 0 | U39: =T39*D39 -> 0 | V39: =S39*$D39 -> 60000
A40: =IFERROR(__xludf.DUMMYFUNCTION("""COMPUTED_VALUE"""),"CKNL3/0") -> CKNL3/0 | B40: =IFERROR(__xludf.DUMMYFUNCTION("""COMPUTED_VALUE"""),"Chỉ nilon 3/0") -> Chỉ nilon 3/0 | C40: =IFERROR(__xludf.DUMMYFUNCTION("""COMPUTED_VALUE"""),"Sợi") -> Sợi | D40: =IFERROR(__xludf.DUMMYFUNCTION("""COMPUTED_VALUE"""),10000.0) -> 10000 | E40: 0 | F40: =E40*$D40 -> 0 | K40: =G40+H40+I40+J40 -> 0 | L40: =K40*$D40 -> 0 | Q40: =M40+N40+O40+P40 -> 0 | R40: =Q40*$D40 -> 0 | S40: 0 | T40: =E40+K40-Q40-S40 -> 0 | U40: =T40*D40 -> 0 | V40: =S40*$D40 -> 0
A41: =IFERROR(__xludf.DUMMYFUNCTION("""COMPUTED_VALUE"""),"CKNL4/0") -> CKNL4/0 | B41: =IFERROR(__xludf.DUMMYFUNCTION("""COMPUTED_VALUE"""),"Chỉ nilon 4/0") -> Chỉ nilon 4/0 | C41: =IFERROR(__xludf.DUMMYFUNCTION("""COMPUTED_VALUE"""),"Sợi") -> Sợi | D41: =IFERROR(__xludf.DUMMYFUNCTION("""COMPUTED_VALUE"""),8333.0) -> 8333 | E41: 0 | F41: =E41*$D41 -> 0 | K41: =G41+H41+I41+J41 -> 0 | L41: =K41*$D41 -> 0 | Q41: =M41+N41+O41+P41 -> 0 | R41: =Q41*$D41 -> 0 | S41: 0 | T41: =E41+K41-Q41-S41 -> 0 | U41: =T41*D41 -> 0 | V41: =S41*$D41 -> 0
A42: =IFERROR(__xludf.DUMMYFUNCTION("""COMPUTED_VALUE"""),"CKNL5/0") -> CKNL5/0 | B42: =IFERROR(__xludf.DUMMYFUNCTION("""COMPUTED_VALUE"""),"Chỉ nilon 5/0") -> Chỉ nilon 5/0 | C42: =IFERROR(__xludf.DUMMYFUNCTION("""COMPUTED_VALUE"""),"Sợi") -> Sợi | D42: =IFERROR(__xludf.DUMMYFUNCTION("""COMPUTED_VALUE"""),60000.0) -> 60000 | E42: 0 | F42: =E42*$D42 -> 0 | K42: =G42+H42+I42+J42 -> 0 | L42: =K42*$D42 -> 0 | Q42: =M42+N42+O42+P42 -> 0 | R42: =Q42*$D42 -> 0 | S42: 0 | T42: =E42+K42-Q42-S42 -> 0 | U42: =T42*D42 -> 0 | V42: =S42*$D42 -> 0
A43: =IFERROR(__xludf.DUMMYFUNCTION("""COMPUTED_VALUE"""),"CKNL7/0") -> CKNL7/0 | B43: =IFERROR(__xludf.DUMMYFUNCTION("""COMPUTED_VALUE"""),"Chỉ nilon 7/0") -> Chỉ nilon 7/0 | C43: =IFERROR(__xludf.DUMMYFUNCTION("""COMPUTED_VALUE"""),"Sợi") -> Sợi | D43: =IFERROR(__xludf.DUMMYFUNCTION("""COMPUTED_VALUE"""),60000.0) -> 60000 | E43: 0 | F43: =E43*$D43 -> 0 | K43: =G43+H43+I43+J43 -> 0 | L43: =K43*$D43 -> 0 | Q43: =M43+N43+O43+P43 -> 0 | R43: =Q43*$D43 -> 0 | S43: 0 | T43: =E43+K43-Q43-S43 -> 0 | U43: =T43*D43 -> 0 | V43: =S43*$D43 -> 0
A44: =IFERROR(__xludf.DUMMYFUNCTION("""COMPUTED_VALUE"""),"CKTVCR0") -> CKTVCR0 | B44: =IFERROR(__xludf.DUMMYFUNCTION("""COMPUTED_VALUE"""),"Chỉ tiêu vircyl 0") -> Chỉ tiêu vircyl 0 | C44: =IFERROR(__xludf.DUMMYFUNCTION("""COMPUTED_VALUE"""),"Sợi") -> Sợi | D44: =IFERROR(__xludf.DUMMYFUNCTION("""COMPUTED_VALUE"""),20000.0) -> 20000 | E44: 4 | F44: =E44*$D44 -> 80000 | K44: =G44+H44+I44+J44 -> 0 | L44: =K44*$D44 -> 0 | Q44: =M44+N44+O44+P44 -> 0 | R44: =Q44*$D44 -> 0 | S44: 4 | T44: =E44+K44-Q44-S44 -> 0 | U44: =T44*D44 -> 0 | V44: =S44*$D44 -> 80000
A45: =IFERROR(__xludf.DUMMYFUNCTION("""COMPUTED_VALUE"""),"CKTVCR1") -> CKTVCR1 | B45: =IFERROR(__xludf.DUMMYFUNCTION("""COMPUTED_VALUE"""),"Chỉ tiêu vircyl 1") -> Chỉ tiêu vircyl 1 | C45: =IFERROR(__xludf.DUMMYFUNCTION("""COMPUTED_VALUE"""),"Sợi") -> Sợi | D45: =IFERROR(__xludf.DUMMYFUNCTION("""COMPUTED_VALUE"""),20000.0) -> 20000 | E45: 0 | F45: =E45*$D45 -> 0 | K45: =G45+H45+I45+J45 -> 0 | L45: =K45*$D45 -> 0 | Q45: =M45+N45+O45+P45 -> 0 | R45: =Q45*$D45 -> 0 | S45: 0 | T45: =E45+K45-Q45-S45 -> 0 | U45: =T45*D45 -> 0 | V45: =S45*$D45 -> 0
A46: =IFERROR(__xludf.DUMMYFUNCTION("""COMPUTED_VALUE"""),"CKTVCR2") -> CKTVCR2 | B46: =IFERROR(__xludf.DUMMYFUNCTION("""COMPUTED_VALUE"""),"Chỉ tiêu vircyl 2") -> Chỉ tiêu vircyl 2 | C46: =IFERROR(__xludf.DUMMYFUNCTION("""COMPUTED_VALUE"""),"Sợi") -> Sợi | D46: =IFERROR(__xludf.DUMMYFUNCTION("""COMPUTED_VALUE"""),20000.0) -> 20000 | E46: 0 | F46: =E46*$D46 -> 0 | K46: =G46+H46+I46+J46 -> 0 | L46: =K46*$D46 -> 0 | Q46: =M46+N46+O46+P46 -> 0 | R46: =Q46*$D46 -> 0 | S46: 0 | T46: =E46+K46-Q46-S46 -> 0 | U46: =T46*D46 -> 0 | V46: =S46*$D46 -> 0
A47: =IFERROR(__xludf.DUMMYFUNCTION("""COMPUTED_VALUE"""),"CKTVCR2/0") -> CKTVCR2/0 | B47: =IFERROR(__xludf.DUMMYFUNCTION("""COMPUTED_VALUE"""),"Chỉ tiêu vircyl 2/0") -> Chỉ tiêu vircyl 2/0 | C47: =IFERROR(__xludf.DUMMYFUNCTION("""COMPUTED_VALUE"""),"Sợi") -> Sợi | D47: =IFERROR(__xludf.DUMMYFUNCTION("""COMPUTED_VALUE"""),20000.0) -> 20000 | E47: 18 | F47: =E47*$D47 -> 360000 | K47: =G47+H47+I47+J47 -> 0 | L47: =K47*$D47 -> 0 | Q47: =M47+N47+O47+P47 -> 0 | R47: =Q47*$D47 -> 0 | S47: 12 | T47: =E47+K47-Q47-S47 -> 6 | U47: =T47*D47 -> 120000 | V47: =S47*$D47 -> 240000
A48: =IFERROR(__xludf.DUMMYFUNCTION("""COMPUTED_VALUE"""),"CKTVCR3/0") -> CKTVCR3/0 | B48: =IFERROR(__xludf.DUMMYFUNCTION("""COMPUTED_VALUE"""),"Chỉ tiêu vircyl 3/0") -> Chỉ tiêu vircyl 3/0 | C48: =IFERROR(__xludf.DUMMYFUNCTION("""COMPUTED_VALUE"""),"Sợi") -> Sợi | D48: =IFERROR(__xludf.DUMMYFUNCTION("""COMPUTED_VALUE"""),20000.0) -> 20000 | E48: 32 | F48: =E48*$D48 -> 640000 | K48: =G48+H48+I48+J48 -> 0 | L48: =K48*$D48 -> 0 | Q48: =M48+N48+O48+P48 -> 0 | R48: =Q48*$D48 -> 0 | S48: 22 | T48: =E48+K48-Q48-S48 -> 10 | U48: =T48*D48 -> 200000 | V48: =S48*$D48 -> 440000
A49: =IFERROR(__xludf.DUMMYFUNCTION("""COMPUTED_VALUE"""),"CKTVCR4/0") -> CKTVCR4/0 | B49: =IFERROR(__xludf.DUMMYFUNCTION("""COMPUTED_VALUE"""),"Chỉ tiêu vircyl 4/0") -> Chỉ tiêu vircyl 4/0 | C49: =IFERROR(__xludf.DUMMYFUNCTION("""COMPUTED_VALUE"""),"Sợi") -> Sợi | D49: =IFERROR(__xludf.DUMMYFUNCTION("""COMPUTED_VALUE"""),20000.0) -> 20000 | E49: 15 | F49: =E49*$D49 -> 300000 | K49: =G49+H49+I49+J49 -> 0 | L49: =K49*$D49 -> 0 | Q49: =M49+N49+O49+P49 -> 0 | R49: =Q49*$D49 -> 0 | S49: 8 | T49: =E49+K49-Q49-S49 -> 7 | U49: =T49*D49 -> 140000 | V49: =S49*$D49 -> 160000
A50: =IFERROR(__xludf.DUMMYFUNCTION("""COMPUTED_VALUE"""),"CKTVCR6/0") -> CKTVCR6/0 | B50: =IFERROR(__xludf.DUMMYFUNCTION("""COMPUTED_VALUE"""),"Chỉ tiêu vircyl 6/0") -> Chỉ tiêu vircyl 6/0 | C50: =IFERROR(__xludf.DUMMYFUNCTION("""COMPUTED_VALUE"""),"Sợi") -> Sợi | D50: =IFERROR(__xludf.DUMMYFUNCTION("""COMPUTED_VALUE"""),20000.0) -> 20000 | E50: 0 | F50: =E50*$D50 -> 0 | K50: =G50+H50+I50+J50 -> 0 | L50: =K50*$D50 -> 0 | Q50: =M50+N50+O50+P50 -> 0 | R50: =Q50*$D50 -> 0 | S50: 0 | T50: =E50+K50-Q50-S50 -> 0 | U50: =T50*D50 -> 0 | V50: =S50*$D50 -> 0
A51: =IFERROR(__xludf.DUMMYFUNCTION("""COMPUTED_VALUE"""),"CHDX") -> CHDX | B51: =IFERROR(__xludf.DUMMYFUNCTION("""COMPUTED_VALUE"""),"Chlorhexidine") -> Chlorhexidine | C51: =IFERROR(__xludf.DUMMYFUNCTION("""COMPUTED_VALUE"""),"ml") -> ml | D51: =IFERROR(__xludf.DUMMYFUNCTION("""COMPUTED_VALUE"""),145.0) -> 145 | E51: 6500 | F51: =E51*$D51 -> 942500 | K51: =G51+H51+I51+J51 -> 0 | L51: =K51*$D51 -> 0 | Q51: =M51+N51+O51+P51 -> 0 | R51: =Q51*$D51 -> 0 | S51: 5500 | T51: =E51+K51-Q51-S51 -> 1000 | U51: =T51*D51 -> 145000 | V51: =S51*$D51 -> 797500
A52: =IFERROR(__xludf.DUMMYFUNCTION("""COMPUTED_VALUE"""),"CHL") -> CHL | B52: =IFERROR(__xludf.DUMMYFUNCTION("""COMPUTED_VALUE"""),"Choliver") -> Choliver | C52: =IFERROR(__xludf.DUMMYFUNCTION("""COMPUTED_VALUE"""),"Viên") -> Viên | D52: =IFERROR(__xludf.DUMMYFUNCTION("""COMPUTED_VALUE"""),900.0) -> 900 | E52: 90 | F52: =E52*$D52 -> 81000 | H52: 100 | I52: 200 | K52: =G52+H52+I52+J52 -> 300 | L52: =K52*$D52 -> 270000 | Q52: =M52+N52+O52+P52 -> 0 | R52: =Q52*$D52 -> 0 | S52: 232 | T52: =E52+K52-Q52-S52 -> 158 | U52: =T52*D52 -> 142200 | V52: =S52*$D52 -> 208800
A53: =IFERROR(__xludf.DUMMYFUNCTION("""COMPUTED_VALUE"""),"CHMS") -> CHMS | B53: =IFERROR(__xludf.DUMMYFUNCTION("""COMPUTED_VALUE"""),"Chymosin") -> Chymosin | C53: =IFERROR(__xludf.DUMMYFUNCTION("""COMPUTED_VALUE"""),"mL") -> mL | D53: =IFERROR(__xludf.DUMMYFUNCTION("""COMPUTED_VALUE"""),600.0) -> 600 | E53: 165 | F53: =E53*$D53 -> 99000 | K53: =G53+H53+I53+J53 -> 0 | L53: =K53*$D53 -> 0 | Q53: =M53+N53+O53+P53 -> 0 | R53: =Q53*$D53 -> 0 | S53: 165 | T53: =E53+K53-Q53-S53 -> 0 | U53: =T53*D53 -> 0 | V53: =S53*$D53 -> 99000
A54: =IFERROR(__xludf.DUMMYFUNCTION("""COMPUTED_VALUE"""),"CMTD300") -> CMTD300 | B54: =IFERROR(__xludf.DUMMYFUNCTION("""COMPUTED_VALUE"""),"Cimetidine 300") -> Cimetidine 300 | C54: =IFERROR(__xludf.DUMMYFUNCTION("""COMPUTED_VALUE"""),"Viên") -> Viên | D54: =IFERROR(__xludf.DUMMYFUNCTION("""COMPUTED_VALUE"""),900.0) -> 900 | E54: =236+40 -> 276 | F54: =E54*$D54 -> 248400 | K54: =G54+H54+I54+J54 -> 0 | L54: =K54*$D54 -> 0 | Q54: =M54+N54+O54+P54 -> 0 | R54: =Q54*$D54 -> 0 | S54: =140+96 -> 236 | T54: =E54+K54-Q54-S54 -> 40 | U54: =T54*D54 -> 36000 | V54: =S54*$D54 -> 212400
A55: =IFERROR(__xludf.DUMMYFUNCTION("""COMPUTED_VALUE"""),"CPR500") -> CPR500 | B55: =IFERROR(__xludf.DUMMYFUNCTION("""COMPUTED_VALUE"""),"Ciprofloxacine 500") -> Ciprofloxacine 500 | C55: =IFERROR(__xludf.DUMMYFUNCTION("""COMPUTED_VALUE"""),"Viên") -> Viên | D55: =IFERROR(__xludf.DUMMYFUNCTION("""COMPUTED_VALUE"""),720.0) -> 720 | E55: =30+84 -> 114 | F55: =E55*$D55 -> 82080 | K55: =G55+H55+I55+J55 -> 0 | L55: =K55*$D55 -> 0 | Q55: =M55+N55+O55+P55 -> 0 | R55: =Q55*$D55 -> 0 | S55: =30+84 -> 114 | T55: =E55+K55-Q55-S55 -> 0 | U55: =T55*D55 -> 0 | V55: =S55*$D55 -> 82080
A56: =IFERROR(__xludf.DUMMYFUNCTION("""COMPUTED_VALUE"""),"CLDMC150") -> CLDMC150 | B56: =IFERROR(__xludf.DUMMYFUNCTION("""COMPUTED_VALUE"""),"Clindamycin 150 mg") -> Clindamycin 150 mg | C56: =IFERROR(__xludf.DUMMYFUNCTION("""COMPUTED_VALUE"""),"Viên") -> Viên | D56: =IFERROR(__xludf.DUMMYFUNCTION("""COMPUTED_VALUE"""),1600.0) -> 1600 | E56: 0 | F56: =E56*$D56 -> 0 | K56: =G56+H56+I56+J56 -> 0 | L56: =K56*$D56 -> 0 | Q56: =M56+N56+O56+P56 -> 0 | R56: =Q56*$D56 -> 0 | S56: 0 | T56: =E56+K56-Q56-S56 -> 0 | U56: =T56*D56 -> 0 | V56: =S56*$D56 -> 0
A57: =IFERROR(__xludf.DUMMYFUNCTION("""COMPUTED_VALUE"""),"CLRMB") -> CLRMB | B57: =IFERROR(__xludf.DUMMYFUNCTION("""COMPUTED_VALUE"""),"Cloramin B") -> Cloramin B | C57: =IFERROR(__xludf.DUMMYFUNCTION("""COMPUTED_VALUE"""),"Gam") -> Gam | D57: =IFERROR(__xludf.DUMMYFUNCTION("""COMPUTED_VALUE"""),200.0) -> 200 | E57: 0 | F57: =E57*$D57 -> 0 | K57: =G57+H57+I57+J57 -> 0 | L57: =K57*$D57 -> 0 | Q57: =M57+N57+O57+P57 -> 0 | R57: =Q57*$D57 -> 0 | S57: 0 | T57: =E57+K57-Q57-S57 -> 0 | U57: =T57*D57 -> 0 | V57: =S57*$D57 -> 0
A58: =IFERROR(__xludf.DUMMYFUNCTION("""COMPUTED_VALUE"""),"CLPLRM4") -> CLPLRM4 | B58: =IFERROR(__xludf.DUMMYFUNCTION("""COMPUTED_VALUE"""),"Clorpheniramin 4mg") -> Clorpheniramin 4mg | C58: =IFERROR(__xludf.DUMMYFUNCTION("""COMPUTED_VALUE"""),"Viên") -> Viên | D58: =IFERROR(__xludf.DUMMYFUNCTION("""COMPUTED_VALUE"""),85.0) -> 85 | E58: 130 | F58: =E58*$D58 -> 11050 | K58: =G58+H58+I58+J58 -> 0 | L58: =K58*$D58 -> 0 | Q58: =M58+N58+O58+P58 -> 0 | R58: =Q58*$D58 -> 0 | S58: 130 | T58: =E58+K58-Q58-S58 -> 0 | U58: =T58*D58 -> 0 | V58: =S58*$D58 -> 11050
A59: =IFERROR(__xludf.DUMMYFUNCTION("""COMPUTED_VALUE"""),"C90") -> C90 | B59: =IFERROR(__xludf.DUMMYFUNCTION("""COMPUTED_VALUE"""),"Cồn 90") -> Cồn 90 | C59: =IFERROR(__xludf.DUMMYFUNCTION("""COMPUTED_VALUE"""),"mL") -> mL | D59: =IFERROR(__xludf.DUMMYFUNCTION("""COMPUTED_VALUE"""),35.0) -> 35 | E59: 3000 | F59: =E59*$D59 -> 105000 | K59: =G59+H59+I59+J59 -> 0 | L59: =K59*$D59 -> 0 | Q59: =M59+N59+O59+P59 -> 0 | R59: =Q59*$D59 -> 0 | S59: 1000 | T59: =E59+K59-Q59-S59 -> 2000 | U59: =T59*D59 -> 70000 | V59: =S59*$D59 -> 35000
A60: =IFERROR(__xludf.DUMMYFUNCTION("""COMPUTED_VALUE"""),"CPVD") -> CPVD | B60: =IFERROR(__xludf.DUMMYFUNCTION("""COMPUTED_VALUE"""),"Cồn povidone") -> Cồn povidone | C60: =IFERROR(__xludf.DUMMYFUNCTION("""COMPUTED_VALUE"""),"mL") -> mL | D60: =IFERROR(__xludf.DUMMYFUNCTION("""COMPUTED_VALUE"""),110.0) -> 110 | E60: 100 | F60: =E60*$D60 -> 11000 | K60: =G60+H60+I60+J60 -> 0 | L60: =K60*$D60 -> 0 | Q60: =M60+N60+O60+P60 -> 0 | R60: =Q60*$D60 -> 0 | S60: 100 | T60: =E60+K60-Q60-S60 -> 0 | U60: =T60*D60 -> 0 | V60: =S60*$D60 -> 11000
A61: =IFERROR(__xludf.DUMMYFUNCTION("""COMPUTED_VALUE"""),"CTD") -> CTD | B61: =IFERROR(__xludf.DUMMYFUNCTION("""COMPUTED_VALUE"""),"Cồn tuyệt đối") -> Cồn tuyệt đối | C61: =IFERROR(__xludf.DUMMYFUNCTION("""COMPUTED_VALUE"""),"mL") -> mL | D61: =IFERROR(__xludf.DUMMYFUNCTION("""COMPUTED_VALUE"""),85.0) -> 85 | E61: 20 | F61: =E61*$D61 -> 1700 | K61: =G61+H61+I61+J61 -> 0 | L61: =K61*$D61 -> 0 | Q61: =M61+N61+O61+P61 -> 0 | R61: =Q61*$D61 -> 0 | S61: 0 | T61: =E61+K61-Q61-S61 -> 20 | U61: =T61*D61 -> 1700 | V61: =S61*$D61 -> 0
A62: =IFERROR(__xludf.DUMMYFUNCTION("""COMPUTED_VALUE"""),"DPT11") -> DPT11 | B62: =IFERROR(__xludf.DUMMYFUNCTION("""COMPUTED_VALUE"""),"Dao phẫu thuật 11") -> Dao phẫu thuật 11 | C62: =IFERROR(__xludf.DUMMYFUNCTION("""COMPUTED_VALUE"""),"Cái") -> Cái | D62: =IFERROR(__xludf.DUMMYFUNCTION("""COMPUTED_VALUE"""),950.0) -> 950 | E62: =188+21 -> 209 | F62: =E62*$D62 -> 198550 | K62: =G62+H62+I62+J62 -> 0 | L62: =K62*$D62 -> 0 | Q62: =M62+N62+O62+P62 -> 0 | R62: =Q62*$D62 -> 0 | S62: =150+38 -> 188 | T62: =E62+K62-Q62-S62 -> 21 | U62: =T62*D62 -> 19950 | V62: =S62*$D62 -> 178600
A63: =IFERROR(__xludf.DUMMYFUNCTION("""COMPUTED_VALUE"""),"DPT12") -> DPT12 | B63: =IFERROR(__xludf.DUMMYFUNCTION("""COMPUTED_VALUE"""),"Dao phẫu thuật 12") -> Dao phẫu thuật 12 | C63: =IFERROR(__xludf.DUMMYFUNCTION("""COMPUTED_VALUE"""),"Cái") -> Cái | D63: =IFERROR(__xludf.DUMMYFUNCTION("""COMPUTED_VALUE"""),950.0) -> 950 | E63: 0 | F63: =E63*$D63 -> 0 | K63: =G63+H63+I63+J63 -> 0 | L63: =K63*$D63 -> 0 | Q63: =M63+N63+O63+P63 -> 0 | R63: =Q63*$D63 -> 0 | S63: 0 | T63: =E63+K63-Q63-S63 -> 0 | U63: =T63*D63 -> 0 | V63: =S63*$D63 -> 0
A64: =IFERROR(__xludf.DUMMYFUNCTION("""COMPUTED_VALUE"""),"DPT15") -> DPT15 | B64: =IFERROR(__xludf.DUMMYFUNCTION("""COMPUTED_VALUE"""),"Dao phẫu thuật 15") -> Dao phẫu thuật 15 | C64: =IFERROR(__xludf.DUMMYFUNCTION("""COMPUTED_VALUE"""),"Cái") -> Cái | D64: =IFERROR(__xludf.DUMMYFUNCTION("""COMPUTED_VALUE"""),950.0) -> 950 | E64: 181 | F64: =E64*$D64 -> 171950 | K64: =G64+H64+I64+J64 -> 0 | L64: =K64*$D64 -> 0 | Q64: =M64+N64+O64+P64 -> 0 | R64: =Q64*$D64 -> 0 | S64: 171 | T64: =E64+K64-Q64-S64 -> 10 | U64: =T64*D64 -> 9500 | V64: =S64*$D64 -> 162450
A65: =IFERROR(__xludf.DUMMYFUNCTION("""COMPUTED_VALUE"""),"DPT21") -> DPT21 | B65: =IFERROR(__xludf.DUMMYFUNCTION("""COMPUTED_VALUE"""),"Dao phẫu thuật 21") -> Dao phẫu thuật 21 | C65: =IFERROR(__xludf.DUMMYFUNCTION("""COMPUTED_VALUE"""),"Cái") -> Cái | D65: =IFERROR(__xludf.DUMMYFUNCTION("""COMPUTED_VALUE"""),950.0) -> 950 | E65: 114 | F65: =E65*$D65 -> 108300 | K65: =G65+H65+I65+J65 -> 0 | L65: =K65*$D65 -> 0 | Q65: =M65+N65+O65+P65 -> 0 | R65: =Q65*$D65 -> 0 | S65: 123 | T65: =E65+K65-Q65-S65 -> -9 | U65: =T65*D65 -> -8550 | V65: =S65*$D65 -> 116850
A66: =IFERROR(__xludf.DUMMYFUNCTION("""COMPUTED_VALUE"""),"DTD") -> DTD | B66: =IFERROR(__xludf.DUMMYFUNCTION("""COMPUTED_VALUE"""),"Dây truyền dịch") -> Dây truyền dịch | C66: =IFERROR(__xludf.DUMMYFUNCTION("""COMPUTED_VALUE"""),"Cái") -> Cái | D66: =IFERROR(__xludf.DUMMYFUNCTION("""COMPUTED_VALUE"""),15000.0) -> 15000 | E66: =429+25 -> 454 | F66: =E66*$D66 -> 6810000 | K66: =G66+H66+I66+J66 -> 0 | L66: =K66*$D66 -> 0 | Q66: =M66+N66+O66+P66 -> 0 | R66: =Q66*$D66 -> 0 | S66: 429 | T66: =E66+K66-Q66-S66 -> 25 | U66: =T66*D66 -> 375000 | V66: =S66*$D66 -> 6435000
A67: =IFERROR(__xludf.DUMMYFUNCTION("""COMPUTED_VALUE"""),"DTM") -> DTM | B67: =IFERROR(__xludf.DUMMYFUNCTION("""COMPUTED_VALUE"""),"Dây truyền máu") -> Dây truyền máu | C67: =IFERROR(__xludf.DUMMYFUNCTION("""COMPUTED_VALUE"""),"Cái") -> Cái | D67: =IFERROR(__xludf.DUMMYFUNCTION("""COMPUTED_VALUE"""),4000.0) -> 4000 | E67: 0 | F67: =E67*$D67 -> 0 | K67: =G67+H67+I67+J67 -> 0 | L67: =K67*$D67 -> 0 | Q67: =M67+N67+O67+P67 -> 0 | R67: =Q67*$D67 -> 0 | S67: 0 | T67: =E67+K67-Q67-S67 -> 0 | U67: =T67*D67 -> 0 | V67: =S67*$D67 -> 0
A68: =IFERROR(__xludf.DUMMYFUNCTION("""COMPUTED_VALUE"""),"DPK") -> DPK | B68: =IFERROR(__xludf.DUMMYFUNCTION("""COMPUTED_VALUE"""),"Deparkin") -> Deparkin | C68: =IFERROR(__xludf.DUMMYFUNCTION("""COMPUTED_VALUE"""),"Viên") -> Viên | D68: =IFERROR(__xludf.DUMMYFUNCTION("""COMPUTED_VALUE"""),2500.0) -> 2500 | E68: 11 | F68: =E68*$D68 -> 27500 | K68: =G68+H68+I68+J68 -> 0 | L68: =K68*$D68 -> 0 | Q68: =M68+N68+O68+P68 -> 0 | R68: =Q68*$D68 -> 0 | S68: 11 | T68: =E68+K68-Q68-S68 -> 0 | U68: =T68*D68 -> 0 | V68: =S68*$D68 -> 27500
A69: =IFERROR(__xludf.DUMMYFUNCTION("""COMPUTED_VALUE"""),"DXS") -> DXS | B69: =IFERROR(__xludf.DUMMYFUNCTION("""COMPUTED_VALUE"""),"Dexasone") -> Dexasone | C69: =IFERROR(__xludf.DUMMYFUNCTION("""COMPUTED_VALUE"""),"mL") -> mL | D69: =IFERROR(__xludf.DUMMYFUNCTION("""COMPUTED_VALUE"""),250.0) -> 250 | E69: =70+79 -> 149 | F69: =E69*$D69 -> 37250 | K69: =G69+H69+I69+J69 -> 0 | L69: =K69*$D69 -> 0 | Q69: =M69+N69+O69+P69 -> 0 | R69: =Q69*$D69 -> 0 | S69: 70 | T69: =E69+K69-Q69-S69 -> 79 | U69: =T69*D69 -> 19750 | V69: =S69*$D69 -> 17500
A70: =IFERROR(__xludf.DUMMYFUNCTION("""COMPUTED_VALUE"""),"DVB") -> DVB | B70: =IFERROR(__xludf.DUMMYFUNCTION("""COMPUTED_VALUE"""),"Diệt ve bột") -> Diệt ve bột | C70: =IFERROR(__xludf.DUMMYFUNCTION("""COMPUTED_VALUE"""),"Gam") -> Gam | D70: =IFERROR(__xludf.DUMMYFUNCTION("""COMPUTED_VALUE"""),2000.0) -> 2000 | E70: 9 | F70: =E70*$D70 -> 18000 | K70: =G70+H70+I70+J70 -> 0 | L70: =K70*$D70 -> 0 | Q70: =M70+N70+O70+P70 -> 0 | R70: =Q70*$D70 -> 0 | S70: 9 | T70: =E70+K70-Q70-S70 -> 0 | U70: =T70*D70 -> 0 | V70: =S70*$D70 -> 18000
A71: =IFERROR(__xludf.DUMMYFUNCTION("""COMPUTED_VALUE"""),"DVX") -> DVX | B71: =IFERROR(__xludf.DUMMYFUNCTION("""COMPUTED_VALUE"""),"Diệt ve xanh") -> Diệt ve xanh | C71: =IFERROR(__xludf.DUMMYFUNCTION("""COMPUTED_VALUE"""),"mL") -> mL | D71: =IFERROR(__xludf.DUMMYFUNCTION("""COMPUTED_VALUE"""),641.6666666666666) -> 641.66667 | E71: 0 | F71: =E71*$D71 -> 0 | K71: =G71+H71+I71+J71 -> 0 | L71: =K71*$D71 -> 0 | Q71: =M71+N71+O71+P71 -> 0 | R71: 0 | T71: =E71+K71-Q71-S71 -> 0 | U71: =T71*D71 -> 0 | V71: =S71*$D71 -> 0
A72: =IFERROR(__xludf.DUMMYFUNCTION("""COMPUTED_VALUE"""),"DOC") -> DOC | B72: =IFERROR(__xludf.DUMMYFUNCTION("""COMPUTED_VALUE"""),"DOC") -> DOC | C72: =IFERROR(__xludf.DUMMYFUNCTION("""COMPUTED_VALUE"""),"mL") -> mL | D72: =IFERROR(__xludf.DUMMYFUNCTION("""COMPUTED_VALUE"""),1100.0) -> 1100 | E72: 173 | F72: =E72*$D72 -> 190300 | J72: 200 | K72: =G72+H72+I72+J72 -> 200 | L72: =K72*$D72 -> 220000 | Q72: =M72+N72+O72+P72 -> 0 | R72: =Q72*$D72 -> 0 | S72: =200+50+45 -> 295 | T72: =E72+K72-Q72-S72 -> 78 | U72: =T72*D72 -> 85800 | V72: =S72*$D72 -> 324500
A73: =IFERROR(__xludf.DUMMYFUNCTION("""COMPUTED_VALUE"""),"DRMT") -> DRMT | B73: =IFERROR(__xludf.DUMMYFUNCTION("""COMPUTED_VALUE"""),"Doramectin") -> Doramectin | C73: =IFERROR(__xludf.DUMMYFUNCTION("""COMPUTED_VALUE"""),"mL") -> mL | D73: =IFERROR(__xludf.DUMMYFUNCTION("""COMPUTED_VALUE"""),6600.0) -> 6600 | E73: 10 | F73: =E73*$D73 -> 66000 | K73: =G73+H73+I73+J73 -> 0 | L73: =K73*$D73 -> 0 | Q73: =M73+N73+O73+P73 -> 0 | R73: =Q73*$D73 -> 0 | S73: 10 | T73: =E73+K73-Q73-S73 -> 0 | U73: =T73*D73 -> 0 | V73: =S73*$D73 -> 66000
A74: =IFERROR(__xludf.DUMMYFUNCTION("""COMPUTED_VALUE"""),"DXL100") -> DXL100 | B74: =IFERROR(__xludf.DUMMYFUNCTION("""COMPUTED_VALUE"""),"Doxycycline 100mg") -> Doxycycline 100mg | C74: =IFERROR(__xludf.DUMMYFUNCTION("""COMPUTED_VALUE"""),"Viên") -> Viên | D74: =IFERROR(__xludf.DUMMYFUNCTION("""COMPUTED_VALUE"""),900.0) -> 900 | E74: =834+168 -> 1002 | F74: =E74*$D74 -> 901800 | I74: 200 | K74: =G74+H74+I74+J74 -> 200 | L74: =K74*$D74 -> 180000 | Q74: =M74+N74+O74+P74 -> 0 | R74: =Q74*$D74 -> 0 | S74: =500+36+250+48 -> 834 | T74: =E74+K74-Q74-S74 -> 368 | U74: =T74*D74 -> 331200 | V74: =S74*$D74 -> 750600
A75: =IFERROR(__xludf.DUMMYFUNCTION("""COMPUTED_VALUE"""),"DPL") -> DPL | B75: =IFERROR(__xludf.DUMMYFUNCTION("""COMPUTED_VALUE"""),"Duphalac") -> Duphalac | C75: =IFERROR(__xludf.DUMMYFUNCTION("""COMPUTED_VALUE"""),"Gói") -> Gói | D75: =IFERROR(__xludf.DUMMYFUNCTION("""COMPUTED_VALUE"""),4750.0) -> 4750 | E75: 14 | F75: =E75*$D75 -> 66500 | K75: =G75+H75+I75+J75 -> 0 | L75: =K75*$D75 -> 0 | Q75: =M75+N75+O75+P75 -> 0 | R75: =Q75*$D75 -> 0 | S75: 13 | T75: =E75+K75-Q75-S75 -> 1 | U75: =T75*D75 -> 4750 | V75: =S75*$D75 -> 61750
A76: =IFERROR(__xludf.DUMMYFUNCTION("""COMPUTED_VALUE"""),"FLDX") -> FLDX | B76: =IFERROR(__xludf.DUMMYFUNCTION("""COMPUTED_VALUE"""),"Flodixine") -> Flodixine | C76: =IFERROR(__xludf.DUMMYFUNCTION("""COMPUTED_VALUE"""),"mL") -> mL | D76: =IFERROR(__xludf.DUMMYFUNCTION("""COMPUTED_VALUE"""),1150.0) -> 1150 | E76: =85+49 -> 134 | F76: =E76*$D76 -> 154100 | K76: =G76+H76+I76+J76 -> 0 | L76: =K76*$D76 -> 0 | Q76: =M76+N76+O76+P76 -> 0 | R76: =Q76*$D76 -> 0 | S76: =55+40 -> 95 | T76: =E76+K76-Q76-S76 -> 39 | U76: =T76*D76 -> 44850 | V76: =S76*$D76 -> 109250
A77: =IFERROR(__xludf.DUMMYFUNCTION("""COMPUTED_VALUE"""),"FLFNC") -> FLFNC | B77: =IFERROR(__xludf.DUMMYFUNCTION("""COMPUTED_VALUE"""),"Flofenicol") -> Flofenicol | C77: =IFERROR(__xludf.DUMMYFUNCTION("""COMPUTED_VALUE"""),"mL") -> mL | D77: =IFERROR(__xludf.DUMMYFUNCTION("""COMPUTED_VALUE"""),1000.0) -> 1000 | E77: 200 | F77: =E77*$D77 -> 200000 | K77: =G77+H77+I77+J77 -> 0 | L77: =K77*$D77 -> 0 | Q77: =M77+N77+O77+P77 -> 0 | R77: =Q77*$D77 -> 0 | S77: 200 | T77: =E77+K77-Q77-S77 -> 0 | U77: =T77*D77 -> 0 | V77: =S77*$D77 -> 200000
A78: =IFERROR(__xludf.DUMMYFUNCTION("""COMPUTED_VALUE"""),"FRCMT") -> FRCMT | B78: =IFERROR(__xludf.DUMMYFUNCTION("""COMPUTED_VALUE"""),"Furosemid 40 mg tiêm") -> Furosemid 40 mg tiêm | C78: =IFERROR(__xludf.DUMMYFUNCTION("""COMPUTED_VALUE"""),"Ống") -> Ống | D78: =IFERROR(__xludf.DUMMYFUNCTION("""COMPUTED_VALUE"""),3400.0) -> 3400 | E78: 34 | F78: =E78*$D78 -> 115600 | K78: =G78+H78+I78+J78 -> 0 | L78: =K78*$D78 -> 0 | Q78: =M78+N78+O78+P78 -> 0 | R78: =Q78*$D78 -> 0 | S78: 32 | T78: =E78+K78-Q78-S78 -> 2 | U78: =T78*D78 -> 6800 | V78: =S78*$D78 -> 108800
A79: =IFERROR(__xludf.DUMMYFUNCTION("""COMPUTED_VALUE"""),"FRCMU") -> FRCMU | B79: =IFERROR(__xludf.DUMMYFUNCTION("""COMPUTED_VALUE"""),"Furosemid 40 mg uống") -> Furosemid 40 mg uống | C79: =IFERROR(__xludf.DUMMYFUNCTION("""COMPUTED_VALUE"""),"Viên") -> Viên | D79: =IFERROR(__xludf.DUMMYFUNCTION("""COMPUTED_VALUE"""),500.0) -> 500 | E79: =83+19 -> 102 | F79: =E79*$D79 -> 51000 | K79: =G79+H79+I79+J79 -> 0 | L79: =K79*$D79 -> 0 | Q79: =M79+N79+O79+P79 -> 0 | R79: =Q79*$D79 -> 0 | S79: =83+19 -> 102 | T79: =E79+K79-Q79-S79 -> 0 | U79: =T79*D79 -> 0 | V79: =S79*$D79 -> 51000
A80: =IFERROR(__xludf.DUMMYFUNCTION("""COMPUTED_VALUE"""),"GPT") -> GPT | B80: =IFERROR(__xludf.DUMMYFUNCTION("""COMPUTED_VALUE"""),"Gạc phẫu thuật") -> Gạc phẫu thuật | C80: =IFERROR(__xludf.DUMMYFUNCTION("""COMPUTED_VALUE"""),"Hộp") -> Hộp | D80: =IFERROR(__xludf.DUMMYFUNCTION("""COMPUTED_VALUE"""),300000.0) -> 300000 | E80: 2 | F80: =E80*$D80 -> 600000 | K80: =G80+H80+I80+J80 -> 0 | L80: =K80*$D80 -> 0 | Q80: =M80+N80+O80+P80 -> 0 | R80: =Q80*$D80 -> 0 | S80: 2 | T80: =E80+K80-Q80-S80 -> 0 | U80: =T80*D80 -> 0 | V80: =S80*$D80 -> 600000
A81: =IFERROR(__xludf.DUMMYFUNCTION("""COMPUTED_VALUE"""),"GPTOB") -> GPTOB | B81: =IFERROR(__xludf.DUMMYFUNCTION("""COMPUTED_VALUE"""),"Gạc phẫu thuật ổ bụng") -> Gạc phẫu thuật ổ bụng | C81: =IFERROR(__xludf.DUMMYFUNCTION("""COMPUTED_VALUE"""),"Gói") -> Gói | D81: =IFERROR(__xludf.DUMMYFUNCTION("""COMPUTED_VALUE"""),8000.0) -> 8000 | E81: 50 | F81: =E81*$D81 -> 400000 | K81: =G81+H81+I81+J81 -> 0 | L81: =K81*$D81 -> 0 | Q81: =M81+N81+O81+P81 -> 0 | R81: =Q81*$D81 -> 0 | T81: =E81+K81-Q81-S81 -> 50 | U81: =T81*D81 -> 400000 | V81: =S81*$D81 -> 0
A82: =IFERROR(__xludf.DUMMYFUNCTION("""COMPUTED_VALUE"""),"GTPT") -> GTPT | B82: =IFERROR(__xludf.DUMMYFUNCTION("""COMPUTED_VALUE"""),"Găng tay phẫu thuật") -> Găng tay phẫu thuật | C82: =IFERROR(__xludf.DUMMYFUNCTION("""COMPUTED_VALUE"""),"Đôi") -> Đôi | D82: =IFERROR(__xludf.DUMMYFUNCTION("""COMPUTED_VALUE"""),5400.0) -> 5400 | E82: 0 | F82: =E82*$D82 -> 0 | K82: =G82+H82+I82+J82 -> 0 | L82: =K82*$D82 -> 0 | Q82: =M82+N82+O82+P82 -> 0 | R82: =Q82*$D82 -> 0 | S82: 0 | T82: =E82+K82-Q82-S82 -> 0 | U82: =T82*D82 -> 0 | V82: =S82*$D82 -> 0
A83: =IFERROR(__xludf.DUMMYFUNCTION("""COMPUTED_VALUE"""),"GTT") -> GTT | B83: =IFERROR(__xludf.DUMMYFUNCTION("""COMPUTED_VALUE"""),"Găng tay thường") -> Găng tay thường | C83: =IFERROR(__xludf.DUMMYFUNCTION("""COMPUTED_VALUE"""),"Hộp") -> Hộp | D83: =IFERROR(__xludf.DUMMYFUNCTION("""COMPUTED_VALUE"""),65000.0) -> 65000 | E83: 9 | F83: =E83*$D83 -> 585000 | J83: 10 | K83: =G83+H83+I83+J83 -> 10 | L83: =K83*$D83 -> 650000 | Q83: =M83+N83+O83+P83 -> 0 | R83: =Q83*$D83 -> 0 | S83: 9 | T83: =E83+K83-Q83-S83 -> 10 | U83: =T83*D83 -> 650000 | V83: =S83*$D83 -> 585000
A84: =IFERROR(__xludf.DUMMYFUNCTION("""COMPUTED_VALUE"""),"GSA") -> GSA | B84: =IFERROR(__xludf.DUMMYFUNCTION("""COMPUTED_VALUE"""),"Gel siêu âm") -> Gel siêu âm | C84: =IFERROR(__xludf.DUMMYFUNCTION("""COMPUTED_VALUE"""),"Gam") -> Gam | D84: =IFERROR(__xludf.DUMMYFUNCTION("""COMPUTED_VALUE"""),30.0) -> 30 | E84: 4800 | F84: =E84*$D84 -> 144000 | K84: =G84+H84+I84+J84 -> 0 | L84: =K84*$D84 -> 0 | Q84: =M84+N84+O84+P84 -> 0 | R84: =Q84*$D84 -> 0 | S84: 4600 | T84: =E84+K84-Q84-S84 -> 200 | U84: =T84*D84 -> 6000 | V84: =S84*$D84 -> 138000
A85: =IFERROR(__xludf.DUMMYFUNCTION("""COMPUTED_VALUE"""),"GTMC4") -> GTMC4 | B85: =IFERROR(__xludf.DUMMYFUNCTION("""COMPUTED_VALUE"""),"Gentamycin 4%") -> Gentamycin 4% | C85: =IFERROR(__xludf.DUMMYFUNCTION("""COMPUTED_VALUE"""),"mL") -> mL | D85: =IFERROR(__xludf.DUMMYFUNCTION("""COMPUTED_VALUE"""),250.0) -> 250 | E85: 80 | F85: =E85*$D85 -> 20000 | K85: =G85+H85+I85+J85 -> 0 | L85: =K85*$D85 -> 0 | Q85: =M85+N85+O85+P85 -> 0 | R85: =Q85*$D85 -> 0 | S85: 80 | T85: =E85+K85-Q85-S85 -> 0 | U85: =T85*D85 -> 0 | V85: =S85*$D85 -> 20000
A86: =IFERROR(__xludf.DUMMYFUNCTION("""COMPUTED_VALUE"""),"GI") -> GI | B86: =IFERROR(__xludf.DUMMYFUNCTION("""COMPUTED_VALUE"""),"Giấy in") -> Giấy in | C86: =IFERROR(__xludf.DUMMYFUNCTION("""COMPUTED_VALUE"""),"Cuộn") -> Cuộn | D86: =IFERROR(__xludf.DUMMYFUNCTION("""COMPUTED_VALUE"""),5280.0) -> 5280 | E86: 20 | F86: =E86*$D86 -> 105600 | K86: =G86+H86+I86+J86 -> 0 | L86: =K86*$D86 -> 0 | Q86: =M86+N86+O86+P86 -> 0 | R86: =Q86*$D86 -> 0 | S86: 0 | T86: =E86+K86-Q86-S86 -> 20 | U86: =T86*D86 -> 105600 | V86: =S86*$D86 -> 0
A87: =IFERROR(__xludf.DUMMYFUNCTION("""COMPUTED_VALUE"""),"GL5") -> GL5 | B87: =IFERROR(__xludf.DUMMYFUNCTION("""COMPUTED_VALUE"""),"Glucose 5%") -> Glucose 5% | C87: =IFERROR(__xludf.DUMMYFUNCTION("""COMPUTED_VALUE"""),"Chai") -> Chai | D87: =IFERROR(__xludf.DUMMYFUNCTION("""COMPUTED_VALUE"""),12250.0) -> 12250 | E87: 28 | F87: =E87*$D87 -> 343000 | K87: =G87+H87+I87+J87 -> 0 | L87: =K87*$D87 -> 0 | Q87: =M87+N87+O87+P87 -> 0 | R87: =Q87*$D87 -> 0 | S87: 16 | T87: =E87+K87-Q87-S87 -> 12 | U87: =T87*D87 -> 147000 | V87: =S87*$D87 -> 196000
A88: =IFERROR(__xludf.DUMMYFUNCTION("""COMPUTED_VALUE"""),"HTX") -> HTX | B88: =IFERROR(__xludf.DUMMYFUNCTION("""COMPUTED_VALUE"""),"Hantox") -> Hantox | C88: =IFERROR(__xludf.DUMMYFUNCTION("""COMPUTED_VALUE"""),"mL") -> mL | D88: =IFERROR(__xludf.DUMMYFUNCTION("""COMPUTED_VALUE"""),500.0) -> 500 | E88: 700 | F88: =E88*$D88 -> 350000 | K88: =G88+H88+I88+J88 -> 0 | L88: =K88*$D88 -> 0 | Q88: =M88+N88+O88+P88 -> 0 | R88: =Q88*$D88 -> 0 | S88: =9*50 -> 450 | T88: =E88+K88-Q88-S88 -> 250 | U88: =T88*D88 -> 125000 | V88: =S88*$D88 -> 225000
A89: =IFERROR(__xludf.DUMMYFUNCTION("""COMPUTED_VALUE"""),"HCMSL1") -> HCMSL1 | B89: =IFERROR(__xludf.DUMMYFUNCTION("""COMPUTED_VALUE"""),"HC Diluent") -> HC Diluent | C89: =IFERROR(__xludf.DUMMYFUNCTION("""COMPUTED_VALUE"""),"Hộp") -> Hộp | D89: =IFERROR(__xludf.DUMMYFUNCTION("""COMPUTED_VALUE"""),900000.0) -> 900000 | E89: 0 | F89: =E89*$D89 -> 0 | K89: =G89+H89+I89+J89 -> 0 | L89: =K89*$D89 -> 0 | Q89: =M89+N89+O89+P89 -> 0 | R89: =Q89*$D89 -> 0 | S89: 0 | T89: =E89+K89-Q89-S89 -> 0 | U89: =T89*D89 -> 0 | V89: =S89*$D89 -> 0
A90: =IFERROR(__xludf.DUMMYFUNCTION("""COMPUTED_VALUE"""),"HCMSL3") -> HCMSL3 | B90: =IFERROR(__xludf.DUMMYFUNCTION("""COMPUTED_VALUE"""),"HC Ez cleaner") -> HC Ez cleaner | C90: =IFERROR(__xludf.DUMMYFUNCTION("""COMPUTED_VALUE"""),"Chai") -> Chai | D90: =IFERROR(__xludf.DUMMYFUNCTION("""COMPUTED_VALUE"""),600000.0) -> 600000 | E90: 0 | F90: =E90*$D90 -> 0 | K90: =G90+H90+I90+J90 -> 0 | L90: =K90*$D90 -> 0 | Q90: =M90+N90+O90+P90 -> 0 | R90: =Q90*$D90 -> 0 | S90: 0 | T90: =E90+K90-Q90-S90 -> 0 | U90: =T90*D90 -> 0 | V90: =S90*$D90 -> 0
A91: =IFERROR(__xludf.DUMMYFUNCTION("""COMPUTED_VALUE"""),"HCMSL2") -> HCMSL2 | B91: =IFERROR(__xludf.DUMMYFUNCTION("""COMPUTED_VALUE"""),"HC Lyse") -> HC Lyse | C91: =IFERROR(__xludf.DUMMYFUNCTION("""COMPUTED_VALUE"""),"Chai") -> Chai | D91: =IFERROR(__xludf.DUMMYFUNCTION("""COMPUTED_VALUE"""),900000.0) -> 900000 | E91: 0 | F91: =E91*$D91 -> 0 | K91: =G91+H91+I91+J91 -> 0 | L91: =K91*$D91 -> 0 | Q91: =M91+N91+O91+P91 -> 0 | R91: =Q91*$D91 -> 0 | S91: 0 | T91: =E91+K91-Q91-S91 -> 0 | U91: =T91*D91 -> 0 | V91: =S91*$D91 -> 0
A92: =IFERROR(__xludf.DUMMYFUNCTION("""COMPUTED_VALUE"""),"HISANTI") -> HISANTI | B92: =IFERROR(__xludf.DUMMYFUNCTION("""COMPUTED_VALUE"""),"Hisanti (chlopheramin)") -> Hisanti (chlopheramin) | C92: =IFERROR(__xludf.DUMMYFUNCTION("""COMPUTED_VALUE"""),"mL") -> mL | D92: =IFERROR(__xludf.DUMMYFUNCTION("""COMPUTED_VALUE"""),817.0) -> 817 | E92: 20 | F92: =E92*$D92 -> 16340 | K92: =G92+H92+I92+J92 -> 0 | L92: =K92*$D92 -> 0 | Q92: =M92+N92+O92+P92 -> 0 | R92: =Q92*$D92 -> 0 | S92: 25 | T92: =E92+K92-Q92-S92 -> -5 | U92: =T92*D92 -> -4085 | V92: =S92*$D92 -> 20425
A93: =IFERROR(__xludf.DUMMYFUNCTION("""COMPUTED_VALUE"""),"IMC") -> IMC | B93: =IFERROR(__xludf.DUMMYFUNCTION("""COMPUTED_VALUE"""),"Imochem 120 (imidocard)") -> Imochem 120 (imidocard) | C93: =IFERROR(__xludf.DUMMYFUNCTION("""COMPUTED_VALUE"""),"mL") -> mL | D93: =IFERROR(__xludf.DUMMYFUNCTION("""COMPUTED_VALUE"""),10100.0) -> 10100 | E93: 20 | F93: =E93*$D93 -> 202000 | K93: =G93+H93+I93+J93 -> 0 | L93: =K93*$D93 -> 0 | Q93: =M93+N93+O93+P93 -> 0 | R93: =Q93*$D93 -> 0 | S93: 20 | T93: =E93+K93-Q93-S93 -> 0 | U93: =T93*D93 -> 0 | V93: =S93*$D93 -> 202000
A94: =IFERROR(__xludf.DUMMYFUNCTION("""COMPUTED_VALUE"""),"ISL") -> ISL | B94: =IFERROR(__xludf.DUMMYFUNCTION("""COMPUTED_VALUE"""),"Insulin") -> Insulin | C94: =IFERROR(__xludf.DUMMYFUNCTION("""COMPUTED_VALUE"""),"mL") -> mL | D94: =IFERROR(__xludf.DUMMYFUNCTION("""COMPUTED_VALUE"""),1500.0) -> 1500 | E94: 0 | F94: =E94*$D94 -> 0 | K94: =G94+H94+I94+J94 -> 0 | L94: =K94*$D94 -> 0 | Q94: =M94+N94+O94+P94 -> 0 | R94: =Q94*$D94 -> 0 | S94: 0 | T94: =E94+K94-Q94-S94 -> 0 | U94: =T94*D94 -> 0 | V94: =S94*$D94 -> 0
A95: =IFERROR(__xludf.DUMMYFUNCTION("""COMPUTED_VALUE"""),"IVMT") -> IVMT | B95: =IFERROR(__xludf.DUMMYFUNCTION("""COMPUTED_VALUE"""),"Ivermectin") -> Ivermectin | C95: =IFERROR(__xludf.DUMMYFUNCTION("""COMPUTED_VALUE"""),"mL") -> mL | D95: =IFERROR(__xludf.DUMMYFUNCTION("""COMPUTED_VALUE"""),1300.0) -> 1300 | E95: 3 | F95: =E95*$D95 -> 3900 | K95: =G95+H95+I95+J95 -> 0 | L95: =K95*$D95 -> 0 | Q95: =M95+N95+O95+P95 -> 0 | R95: =Q95*$D95 -> 0 | S95: 10 | T95: =E95+K95-Q95-S95 -> -7 | U95: =T95*D95 -> -9100 | V95: =S95*$D95 -> 13000
A96: =IFERROR(__xludf.DUMMYFUNCTION("""COMPUTED_VALUE"""),"KALI10") -> KALI10 | B96: =IFERROR(__xludf.DUMMYFUNCTION("""COMPUTED_VALUE"""),"Kali clorid 10%") -> Kali clorid 10% | C96: =IFERROR(__xludf.DUMMYFUNCTION("""COMPUTED_VALUE"""),"Ống") -> Ống | D96: =IFERROR(__xludf.DUMMYFUNCTION("""COMPUTED_VALUE"""),4500.0) -> 4500 | E96: 7 | F96: =E96*$D96 -> 31500 | K96: =G96+H96+I96+J96 -> 0 | L96: =K96*$D96 -> 0 | Q96: =M96+N96+O96+P96 -> 0 | R96: =Q96*$D96 -> 0 | S96: 7 | T96: =E96+K96-Q96-S96 -> 0 | U96: =T96*D96 -> 0 | V96: =S96*$D96 -> 31500
A97: =IFERROR(__xludf.DUMMYFUNCTION("""COMPUTED_VALUE"""),"KDVT") -> KDVT | B97: =IFERROR(__xludf.DUMMYFUNCTION("""COMPUTED_VALUE"""),"Keo dán vết thương") -> Keo dán vết thương | C97: =IFERROR(__xludf.DUMMYFUNCTION("""COMPUTED_VALUE"""),"Cuộn") -> Cuộn | D97: =IFERROR(__xludf.DUMMYFUNCTION("""COMPUTED_VALUE"""),120000.0) -> 120000 | E97: 0 | F97: =E97*$D97 -> 0 | K97: =G97+H97+I97+J97 -> 0 | L97: =K97*$D97 -> 0 | Q97: =M97+N97+O97+P97 -> 0 | R97: =Q97*$D97 -> 0 | S97: 0 | T97: =E97+K97-Q97-S97 -> 0 | U97: =T97*D97 -> 0 | V97: =S97*$D97 -> 0
A98: =IFERROR(__xludf.DUMMYFUNCTION("""COMPUTED_VALUE"""),"KG") -> KG | B98: =IFERROR(__xludf.DUMMYFUNCTION("""COMPUTED_VALUE"""),"Keo giấy") -> Keo giấy | C98: =IFERROR(__xludf.DUMMYFUNCTION("""COMPUTED_VALUE"""),"Cuộn") -> Cuộn | D98: =IFERROR(__xludf.DUMMYFUNCTION("""COMPUTED_VALUE"""),6000.0) -> 6000 | E98: 6 | F98: =E98*$D98 -> 36000 | K98: =G98+H98+I98+J98 -> 0 | L98: =K98*$D98 -> 0 | Q98: =M98+N98+O98+P98 -> 0 | R98: =Q98*$D98 -> 0 | S98: 6 | T98: =E98+K98-Q98-S98 -> 0 | U98: =T98*D98 -> 0 | V98: =S98*$D98 -> 36000
A99: =IFERROR(__xludf.DUMMYFUNCTION("""COMPUTED_VALUE"""),"KUG") -> KUG | B99: =IFERROR(__xludf.DUMMYFUNCTION("""COMPUTED_VALUE"""),"Keo urgo") -> Keo urgo | C99: =IFERROR(__xludf.DUMMYFUNCTION("""COMPUTED_VALUE"""),"Cuộn") -> Cuộn | D99: =IFERROR(__xludf.DUMMYFUNCTION("""COMPUTED_VALUE"""),18000.0) -> 18000 | E99: 0 | F99: =E99*$D99 -> 0 | K99: =G99+H99+I99+J99 -> 0 | L99: =K99*$D99 -> 0 | Q99: =M99+N99+O99+P99 -> 0 | R99: =Q99*$D99 -> 0 | S99: 0 | T99: =E99+K99-Q99-S99 -> 0 | U99: =T99*D99 -> 0 | V99: =S99*$D99 -> 0
A100: =IFERROR(__xludf.DUMMYFUNCTION("""COMPUTED_VALUE"""),"KTM") -> KTM | B100: =IFERROR(__xludf.DUMMYFUNCTION("""COMPUTED_VALUE"""),"Ketamin") -> Ketamin | C100: =IFERROR(__xludf.DUMMYFUNCTION("""COMPUTED_VALUE"""),"mL") -> mL | D100: =IFERROR(__xludf.DUMMYFUNCTION("""COMPUTED_VALUE"""),30000.0) -> 30000 | E100: 42 | F100: =E100*$D100 -> 1260000 | K100: =G100+H100+I100+J100 -> 0 | L100: =K100*$D100 -> 0 | Q100: =M100+N100+O100+P100 -> 0 | R100: =Q100*$D100 -> 0 | S100: 40 | T100: =E100+K100-Q100-S100 -> 2 | U100: =T100*D100 -> 60000 | V100: =S100*$D100 -> 1200000
...

Sheet Hang muc chi
A1: =IFERROR(__xludf.DUMMYFUNCTION("importrange(""https://docs.google.com/spreadsheets/d/1ImCdkYhsUqsakZA8jNZp7UrWFPNTrMyfZQst-0aGkKM/edit#gid=0"",""Hang muc chi!A1:D25"")"),"Hạng mục chi") -> Hạng mục chi | B1: =IFERROR(__xludf.DUMMYFUNCTION("""COMPUTED_VALUE"""),"Người chi") -> Người chi | C1: =IFERROR(__xludf.DUMMYFUNCTION("""COMPUTED_VALUE"""),"Người Thu") -> Người Thu | D1: =IFERROR(__xludf.DUMMYFUNCTION("""COMPUTED_VALUE"""),"Loài") -> Loài
A2: =IFERROR(__xludf.DUMMYFUNCTION("""COMPUTED_VALUE"""),"Xet nghiem") -> Xet nghiem | B2: =IFERROR(__xludf.DUMMYFUNCTION("""COMPUTED_VALUE"""),"Đức") -> Đức | C2: =IFERROR(__xludf.DUMMYFUNCTION("""COMPUTED_VALUE"""),"Đức") -> Đức | D2: =IFERROR(__xludf.DUMMYFUNCTION("""COMPUTED_VALUE"""),"Chó") -> Chó
A3: =IFERROR(__xludf.DUMMYFUNCTION("""COMPUTED_VALUE"""),"Thuoc dieu tri") -> Thuoc dieu tri | B3: =IFERROR(__xludf.DUMMYFUNCTION("""COMPUTED_VALUE"""),"Tuyến") -> Tuyến | C3: =IFERROR(__xludf.DUMMYFUNCTION("""COMPUTED_VALUE"""),"Tuyến") -> Tuyến | D3: =IFERROR(__xludf.DUMMYFUNCTION("""COMPUTED_VALUE"""),"Mèo") -> Mèo
A4: =IFERROR(__xludf.DUMMYFUNCTION("""COMPUTED_VALUE"""),"Vat tu") -> Vat tu | B4: =IFERROR(__xludf.DUMMYFUNCTION("""COMPUTED_VALUE"""),"Nhung") -> Nhung | C4: =IFERROR(__xludf.DUMMYFUNCTION("""COMPUTED_VALUE"""),"Thầy") -> Thầy | D4: =IFERROR(__xludf.DUMMYFUNCTION("""COMPUTED_VALUE"""),"Thỏ") -> Thỏ
A5: =IFERROR(__xludf.DUMMYFUNCTION("""COMPUTED_VALUE"""),"Tien an") -> Tien an | B5: =IFERROR(__xludf.DUMMYFUNCTION("""COMPUTED_VALUE"""),"Thầy") -> Thầy | C5: =IFERROR(__xludf.DUMMYFUNCTION("""COMPUTED_VALUE"""),"Linh") -> Linh | D5: =IFERROR(__xludf.DUMMYFUNCTION("""COMPUTED_VALUE"""),"Gà") -> Gà
A6: =IFERROR(__xludf.DUMMYFUNCTION("""COMPUTED_VALUE"""),"Thuc an cho thu luu tru") -> Thuc an cho thu luu tru | B6: =IFERROR(__xludf.DUMMYFUNCTION("""COMPUTED_VALUE"""),"Linh") -> Linh | C6: =IFERROR(__xludf.DUMMYFUNCTION("""COMPUTED_VALUE"""),"K Trang") -> K Trang | D6: =IFERROR(__xludf.DUMMYFUNCTION("""COMPUTED_VALUE"""),"Chuột") -> Chuột
A7: =IFERROR(__xludf.DUMMYFUNCTION("""COMPUTED_VALUE"""),"Card dien thoai") -> Card dien thoai | B7: =IFERROR(__xludf.DUMMYFUNCTION("""COMPUTED_VALUE"""),"K Trang") -> K Trang | C7: =IFERROR(__xludf.DUMMYFUNCTION("""COMPUTED_VALUE"""),"CK thầy") -> CK thầy | D7: =IFERROR(__xludf.DUMMYFUNCTION("""COMPUTED_VALUE"""),"Bò sát") -> Bò sát
A8: =IFERROR(__xludf.DUMMYFUNCTION("""COMPUTED_VALUE"""),"Bao tri, thay the") -> Bao tri, thay the | B8: =IFERROR(__xludf.DUMMYFUNCTION("""COMPUTED_VALUE"""),"H Trang") -> H Trang | C8: =IFERROR(__xludf.DUMMYFUNCTION("""COMPUTED_VALUE"""),"CK petshop thầy") -> CK petshop thầy | D8: =IFERROR(__xludf.DUMMYFUNCTION("""COMPUTED_VALUE"""),"Khỉ") -> Khỉ
A9: =IFERROR(__xludf.DUMMYFUNCTION("""COMPUTED_VALUE"""),"Hoa chat") -> Hoa chat | B9: =IFERROR(__xludf.DUMMYFUNCTION("""COMPUTED_VALUE"""),"Hiến") -> Hiến | C9: =IFERROR(__xludf.DUMMYFUNCTION("""COMPUTED_VALUE"""),"Nhung") -> Nhung | D9: =IFERROR(__xludf.DUMMYFUNCTION("""COMPUTED_VALUE"""),"Chim") -> Chim
A10: =IFERROR(__xludf.DUMMYFUNCTION("""COMPUTED_VALUE"""),"Internet") -> Internet | B10: =IFERROR(__xludf.DUMMYFUNCTION("""COMPUTED_VALUE"""),"Lý") -> Lý | C10: =IFERROR(__xludf.DUMMYFUNCTION("""COMPUTED_VALUE"""),"H Trang") -> H Trang
A11: =IFERROR(__xludf.DUMMYFUNCTION("""COMPUTED_VALUE"""),"Vaccine") -> Vaccine | B11: =IFERROR(__xludf.DUMMYFUNCTION("""COMPUTED_VALUE"""),"Tiến") -> Tiến | C11: =IFERROR(__xludf.DUMMYFUNCTION("""COMPUTED_VALUE"""),"Hiến") -> Hiến
A12: =IFERROR(__xludf.DUMMYFUNCTION("""COMPUTED_VALUE"""),"Chi khac") -> Chi khac | B12: =IFERROR(__xludf.DUMMYFUNCTION("""COMPUTED_VALUE"""),"Hải") -> Hải | C12: =IFERROR(__xludf.DUMMYFUNCTION("""COMPUTED_VALUE"""),"Lý") -> Lý
A13: =IFERROR(__xludf.DUMMYFUNCTION("""COMPUTED_VALUE"""),"Tien dien") -> Tien dien | B13: =IFERROR(__xludf.DUMMYFUNCTION("""COMPUTED_VALUE"""),"Khang") -> Khang | C13: =IFERROR(__xludf.DUMMYFUNCTION("""COMPUTED_VALUE"""),"Lam") -> Lam
A14: =IFERROR(__xludf.DUMMYFUNCTION("""COMPUTED_VALUE"""),"Tien nuoc") -> Tien nuoc | B14: =IFERROR(__xludf.DUMMYFUNCTION("""COMPUTED_VALUE"""),"Ánh") -> Ánh | C14: =IFERROR(__xludf.DUMMYFUNCTION("""COMPUTED_VALUE"""),"HV") -> HV
A15: =IFERROR(__xludf.DUMMYFUNCTION("""COMPUTED_VALUE"""),"Tien gas") -> Tien gas | B15: =IFERROR(__xludf.DUMMYFUNCTION("""COMPUTED_VALUE"""),"Trà") -> Trà | C15: =IFERROR(__xludf.DUMMYFUNCTION("""COMPUTED_VALUE"""),"Hải") -> Hải
A16: =IFERROR(__xludf.DUMMYFUNCTION("""COMPUTED_VALUE"""),"Máy trợ thở") -> Máy trợ thở | B16: =IFERROR(__xludf.DUMMYFUNCTION("""COMPUTED_VALUE"""),"Tuấn") -> Tuấn | C16: =IFERROR(__xludf.DUMMYFUNCTION("""COMPUTED_VALUE"""),"Khang") -> Khang
A17: =IFERROR(__xludf.DUMMYFUNCTION("""COMPUTED_VALUE"""),"Hỏa táng") -> Hỏa táng | C17: =IFERROR(__xludf.DUMMYFUNCTION("""COMPUTED_VALUE"""),"Ánh") -> Ánh
A18: =IFERROR(__xludf.DUMMYFUNCTION("""COMPUTED_VALUE"""),"Xăng xe ca") -> Xăng xe ca | C18: =IFERROR(__xludf.DUMMYFUNCTION("""COMPUTED_VALUE"""),"Trà") -> Trà
A19: =IFERROR(__xludf.DUMMYFUNCTION("""COMPUTED_VALUE"""),"Hàng của thầy") -> Hàng của thầy | C19: =IFERROR(__xludf.DUMMYFUNCTION("""COMPUTED_VALUE"""),"Tuấn") -> Tuấn

Sheet DM benh
B1: Tổng | D1: =sum(D3:D94)*1000 -> 10046000
A2: =IFERROR(__xludf.DUMMYFUNCTION("importrange(""https://docs.google.com/spreadsheets/d/1ImCdkYhsUqsakZA8jNZp7UrWFPNTrMyfZQst-0aGkKM/edit#gid=0"",""Danh muc benh!A1:B500"")"),"Bệnh lý") -> Bệnh lý | B2: =IFERROR(__xludf.DUMMYFUNCTION("""COMPUTED_VALUE"""),"Giá gốc") -> Giá gốc | C2: Số lượng | D2: Thành tiền
A3: =IFERROR(__xludf.DUMMYFUNCTION("""COMPUTED_VALUE"""),"Anti-Derm bôi ghẻ") -> Anti-Derm bôi ghẻ | B3: =IFERROR(__xludf.DUMMYFUNCTION("""COMPUTED_VALUE"""),35.0) -> 35 | C3: =COUNTIF('BC Thang'!$I$4:$I$3085,$A3) -> 0 | D3: =B3*C3 -> 0
A4: =IFERROR(__xludf.DUMMYFUNCTION("""COMPUTED_VALUE"""),"Áo quần chó mèo") -> Áo quần chó mèo | C4: =COUNTIF('BC Thang'!$I$4:$I$3085,$A4) -> 0 | D4: =B4*C4 -> 0
A5: =IFERROR(__xludf.DUMMYFUNCTION("""COMPUTED_VALUE"""),"Bắn microchip") -> Bắn microchip | B5: =IFERROR(__xludf.DUMMYFUNCTION("""COMPUTED_VALUE"""),100.0) -> 100 | C5: =COUNTIF('BC Thang'!$I$4:$I$3085,$A5) -> 0 | D5: =B5*C5 -> 0
A6: =IFERROR(__xludf.DUMMYFUNCTION("""COMPUTED_VALUE"""),"Bó bột lớn") -> Bó bột lớn | B6: =IFERROR(__xludf.DUMMYFUNCTION("""COMPUTED_VALUE"""),52.0) -> 52 | C6: =COUNTIF('BC Thang'!$I$4:$I$3085,$A6) -> 0 | D6: =B6*C6 -> 0
A7: =IFERROR(__xludf.DUMMYFUNCTION("""COMPUTED_VALUE"""),"Bó bột nhỏ") -> Bó bột nhỏ | B7: =IFERROR(__xludf.DUMMYFUNCTION("""COMPUTED_VALUE"""),30.0) -> 30 | C7: =COUNTIF('BC Thang'!$I$4:$I$3085,$A7) -> 0 | D7: =B7*C7 -> 0
A8: =IFERROR(__xludf.DUMMYFUNCTION("""COMPUTED_VALUE"""),"Cạo lông lớn") -> Cạo lông lớn | B8: =IFERROR(__xludf.DUMMYFUNCTION("""COMPUTED_VALUE"""),34.0) -> 34 | C8: =COUNTIF('BC Thang'!$I$4:$I$3085,$A8) -> 1 | D8: =B8*C8 -> 34
A9: =IFERROR(__xludf.DUMMYFUNCTION("""COMPUTED_VALUE"""),"Cạo lông nhỏ") -> Cạo lông nhỏ | B9: =IFERROR(__xludf.DUMMYFUNCTION("""COMPUTED_VALUE"""),15.0) -> 15 | C9: =COUNTIF('BC Thang'!$I$4:$I$3085,$A9) -> 2 | D9: =B9*C9 -> 30
A10: =IFERROR(__xludf.DUMMYFUNCTION("""COMPUTED_VALUE"""),"Cắt móng") -> Cắt móng | B10: =IFERROR(__xludf.DUMMYFUNCTION("""COMPUTED_VALUE"""),5.0) -> 5 | C10: =COUNTIF('BC Thang'!$I$4:$I$3085,$A10) -> 0 | D10: =B10*C10 -> 0
A11: =IFERROR(__xludf.DUMMYFUNCTION("""COMPUTED_VALUE"""),"Cắt tỉa lông") -> Cắt tỉa lông | B11: =IFERROR(__xludf.DUMMYFUNCTION("""COMPUTED_VALUE"""),40.0) -> 40 | C11: =COUNTIF('BC Thang'!$I$4:$I$3085,$A11) -> 0 | D11: =B11*C11 -> 0
A12: =IFERROR(__xludf.DUMMYFUNCTION("""COMPUTED_VALUE"""),"Cấp cứu lớn") -> Cấp cứu lớn | B12: =IFERROR(__xludf.DUMMYFUNCTION("""COMPUTED_VALUE"""),70.0) -> 70 | C12: =COUNTIF('BC Thang'!$I$4:$I$3085,$A12) -> 0 | D12: =B12*C12 -> 0
A13: =IFERROR(__xludf.DUMMYFUNCTION("""COMPUTED_VALUE"""),"Cấp cứu nhỏ") -> Cấp cứu nhỏ | B13: =IFERROR(__xludf.DUMMYFUNCTION("""COMPUTED_VALUE"""),30.0) -> 30 | C13: =COUNTIF('BC Thang'!$I$4:$I$3085,$A13) -> 3 | D13: =B13*C13 -> 90
A14: =IFERROR(__xludf.DUMMYFUNCTION("""COMPUTED_VALUE"""),"Cấp cứu tụt Ca lớn") -> Cấp cứu tụt Ca lớn | B14: =IFERROR(__xludf.DUMMYFUNCTION("""COMPUTED_VALUE"""),34.0) -> 34 | C14: =COUNTIF('BC Thang'!$I$4:$I$3085,$A14) -> 0 | D14: =B14*C14 -> 0
A15: =IFERROR(__xludf.DUMMYFUNCTION("""COMPUTED_VALUE"""),"Cấp cứu tụt Ca nhỏ") -> Cấp cứu tụt Ca nhỏ | B15: =IFERROR(__xludf.DUMMYFUNCTION("""COMPUTED_VALUE"""),28.0) -> 28 | C15: =COUNTIF('BC Thang'!$I$4:$I$3085,$A15) -> 1 | D15: =B15*C15 -> 28
A16: =IFERROR(__xludf.DUMMYFUNCTION("""COMPUTED_VALUE"""),"CBC") -> CBC | B16: =IFERROR(__xludf.DUMMYFUNCTION("""COMPUTED_VALUE"""),10.0) -> 10 | C16: =COUNTIF('BC Thang'!$I$4:$I$3085,$A16) -> 21 | D16: =B16*C16 -> 210
A17: =IFERROR(__xludf.DUMMYFUNCTION("""COMPUTED_VALUE"""),"CDV-") -> CDV- | B17: =IFERROR(__xludf.DUMMYFUNCTION("""COMPUTED_VALUE"""),40.0) -> 40 | C17: =COUNTIF('BC Thang'!$I$4:$I$3085,$A17) -> 0 | D17: =B17*C17 -> 0
A18: =IFERROR(__xludf.DUMMYFUNCTION("""COMPUTED_VALUE"""),"CDV+") -> CDV+ | B18: =IFERROR(__xludf.DUMMYFUNCTION("""COMPUTED_VALUE"""),40.0) -> 40 | C18: =COUNTIF('BC Thang'!$I$4:$I$3085,$A18) -> 0 | D18: =B18*C18 -> 0
A19: =IFERROR(__xludf.DUMMYFUNCTION("""COMPUTED_VALUE"""),"Chích ghẻ") -> Chích ghẻ | B19: =IFERROR(__xludf.DUMMYFUNCTION("""COMPUTED_VALUE"""),10.0) -> 10 | C19: =COUNTIF('BC Thang'!$I$4:$I$3085,$A19) -> 0 | D19: =B19*C19 -> 0
A20: =IFERROR(__xludf.DUMMYFUNCTION("""COMPUTED_VALUE"""),"Chích KST máu") -> Chích KST máu | B20: =IFERROR(__xludf.DUMMYFUNCTION("""COMPUTED_VALUE"""),10.0) -> 10 | C20: =COUNTIF('BC Thang'!$I$4:$I$3085,$A20) -> 2 | D20: =B20*C20 -> 20
A21: =IFERROR(__xludf.DUMMYFUNCTION("""COMPUTED_VALUE"""),"Chích nhắc ghẻ") -> Chích nhắc ghẻ | B21: =IFERROR(__xludf.DUMMYFUNCTION("""COMPUTED_VALUE"""),10.0) -> 10 | C21: =COUNTIF('BC Thang'!$I$4:$I$3085,$A21) -> 0 | D21: =B21*C21 -> 0
A22: =IFERROR(__xludf.DUMMYFUNCTION("""COMPUTED_VALUE"""),"Chích nhắc KST máu") -> Chích nhắc KST máu | B22: =IFERROR(__xludf.DUMMYFUNCTION("""COMPUTED_VALUE"""),10.0) -> 10 | C22: =COUNTIF('BC Thang'!$I$4:$I$3085,$A22) -> 0 | D22: =B22*C22 -> 0
A23: =IFERROR(__xludf.DUMMYFUNCTION("""COMPUTED_VALUE"""),"Chích thuốc lớn") -> Chích thuốc lớn | B23: =IFERROR(__xludf.DUMMYFUNCTION("""COMPUTED_VALUE"""),15.0) -> 15 | C23: =COUNTIF('BC Thang'!$I$4:$I$3085,$A23) -> 1 | D23: =B23*C23 -> 15
A24: =IFERROR(__xludf.DUMMYFUNCTION("""COMPUTED_VALUE"""),"Chích thuốc nhỏ") -> Chích thuốc nhỏ | B24: =IFERROR(__xludf.DUMMYFUNCTION("""COMPUTED_VALUE"""),10.0) -> 10 | C24: =COUNTIF('BC Thang'!$I$4:$I$3085,$A24) -> 45 | D24: =B24*C24 -> 450
A25: =IFERROR(__xludf.DUMMYFUNCTION("""COMPUTED_VALUE"""),"Chọc bàng quang") -> Chọc bàng quang | B25: =IFERROR(__xludf.DUMMYFUNCTION("""COMPUTED_VALUE"""),15.0) -> 15 | C25: =COUNTIF('BC Thang'!$I$4:$I$3085,$A25) -> 0 | D25: =B25*C25 -> 0
A26: =IFERROR(__xludf.DUMMYFUNCTION("""COMPUTED_VALUE"""),"Chôn cất") -> Chôn cất | B26: =IFERROR(__xludf.DUMMYFUNCTION("""COMPUTED_VALUE"""),200.0) -> 200 | C26: =COUNTIF('BC Thang'!$I$4:$I$3085,$A26) -> 0 | D26: =B26*C26 -> 0
A27: =IFERROR(__xludf.DUMMYFUNCTION("""COMPUTED_VALUE"""),"Chụp phim") -> Chụp phim | B27: =IFERROR(__xludf.DUMMYFUNCTION("""COMPUTED_VALUE"""),70.0) -> 70 | C27: =COUNTIF('BC Thang'!$I$4:$I$3085,$A27) -> 10 | D27: =B27*C27 -> 700
A28: =IFERROR(__xludf.DUMMYFUNCTION("""COMPUTED_VALUE"""),"Chuyển lên NH") -> Chuyển lên NH | B28: =IFERROR(__xludf.DUMMYFUNCTION("""COMPUTED_VALUE"""),15.0) -> 15 | C28: =COUNTIF('BC Thang'!$I$4:$I$3085,$A28) -> 0 | D28: =B28*C28 -> 0
A29: =IFERROR(__xludf.DUMMYFUNCTION("""COMPUTED_VALUE"""),"CPV-") -> CPV- | B29: =IFERROR(__xludf.DUMMYFUNCTION("""COMPUTED_VALUE"""),40.0) -> 40 | C29: =COUNTIF('BC Thang'!$I$4:$I$3085,$A29) -> 2 | D29: =B29*C29 -> 80
A30: =IFERROR(__xludf.DUMMYFUNCTION("""COMPUTED_VALUE"""),"CPV+") -> CPV+ | B30: =IFERROR(__xludf.DUMMYFUNCTION("""COMPUTED_VALUE"""),40.0) -> 40 | C30: =COUNTIF('BC Thang'!$I$4:$I$3085,$A30) -> 2 | D30: =B30*C30 -> 80
A31: =IFERROR(__xludf.DUMMYFUNCTION("""COMPUTED_VALUE"""),"Dầu soi kính") -> Dầu soi kính | B31: =IFERROR(__xludf.DUMMYFUNCTION("""COMPUTED_VALUE"""),16.0) -> 16 | C31: =COUNTIF('BC Thang'!$I$4:$I$3085,$A31) -> 0 | D31: =B31*C31 -> 0
A32: =IFERROR(__xludf.DUMMYFUNCTION("""COMPUTED_VALUE"""),"Diệt ve bột") -> Diệt ve bột | B32: =IFERROR(__xludf.DUMMYFUNCTION("""COMPUTED_VALUE"""),13.0) -> 13 | C32: =COUNTIF('BC Thang'!$I$4:$I$3085,$A32) -> 0 | D32: =B32*C32 -> 0
A33: =IFERROR(__xludf.DUMMYFUNCTION("""COMPUTED_VALUE"""),"Diệt ve Hantox") -> Diệt ve Hantox | B33: =IFERROR(__xludf.DUMMYFUNCTION("""COMPUTED_VALUE"""),25.0) -> 25 | C33: =COUNTIF('BC Thang'!$I$4:$I$3085,$A33) -> 1 | D33: =B33*C33 -> 25
A34: =IFERROR(__xludf.DUMMYFUNCTION("""COMPUTED_VALUE"""),"Diệt ve Simparica <10") -> Diệt ve Simparica <10 | B34: =IFERROR(__xludf.DUMMYFUNCTION("""COMPUTED_VALUE"""),100.0) -> 100 | C34: =COUNTIF('BC Thang'!$I$4:$I$3085,$A34) -> 9 | D34: =B34*C34 -> 900
A35: =IFERROR(__xludf.DUMMYFUNCTION("""COMPUTED_VALUE"""),"Diệt ve Simparica 10,1-20") -> Diệt ve Simparica 10,1-20 | B35: =IFERROR(__xludf.DUMMYFUNCTION("""COMPUTED_VALUE"""),110.0) -> 110 | C35: =COUNTIF('BC Thang'!$I$4:$I$3085,$A35) -> 0 | D35: =B35*C35 -> 0
A36: =IFERROR(__xludf.DUMMYFUNCTION("""COMPUTED_VALUE"""),"Diệt ve Simparica 20,1-40") -> Diệt ve Simparica 20,1-40 | B36: =IFERROR(__xludf.DUMMYFUNCTION("""COMPUTED_VALUE"""),200.0) -> 200 | C36: =COUNTIF('BC Thang'!$I$4:$I$3085,$A36) -> 6 | D36: =B36*C36 -> 1200
A37: =IFERROR(__xludf.DUMMYFUNCTION("""COMPUTED_VALUE"""),"Diệt ve xanh") -> Diệt ve xanh | B37: =IFERROR(__xludf.DUMMYFUNCTION("""COMPUTED_VALUE"""),6.0) -> 6 | C37: =COUNTIF('BC Thang'!$I$4:$I$3085,$A37) -> 3 | D37: =B37*C37 -> 18
A38: =IFERROR(__xludf.DUMMYFUNCTION("""COMPUTED_VALUE"""),"Diệt ve xịt") -> Diệt ve xịt | C38: =COUNTIF('BC Thang'!$I$4:$I$3085,$A38) -> 0 | D38: =B38*C38 -> 0
A39: =IFERROR(__xludf.DUMMYFUNCTION("""COMPUTED_VALUE"""),"Duphalac") -> Duphalac | B39: =IFERROR(__xludf.DUMMYFUNCTION("""COMPUTED_VALUE"""),10.0) -> 10 | C39: =COUNTIF('BC Thang'!$I$4:$I$3085,$A39) -> 0 | D39: =B39*C39 -> 0
A40: =IFERROR(__xludf.DUMMYFUNCTION("""COMPUTED_VALUE"""),"Đỡ đẻ") -> Đỡ đẻ | B40: =IFERROR(__xludf.DUMMYFUNCTION("""COMPUTED_VALUE"""),32.0) -> 32 | C40: =COUNTIF('BC Thang'!$I$4:$I$3085,$A40) -> 0 | D40: =B40*C40 -> 0
A41: =IFERROR(__xludf.DUMMYFUNCTION("""COMPUTED_VALUE"""),"ĐT RLTH") -> ĐT RLTH | B41: =IFERROR(__xludf.DUMMYFUNCTION("""COMPUTED_VALUE"""),15.0) -> 15 | C41: =COUNTIF('BC Thang'!$I$4:$I$3085,$A41) -> 0 | D41: =B41*C41 -> 0
A42: =IFERROR(__xludf.DUMMYFUNCTION("""COMPUTED_VALUE"""),"Ecanis-") -> Ecanis- | B42: =IFERROR(__xludf.DUMMYFUNCTION("""COMPUTED_VALUE"""),70.0) -> 70 | C42: =COUNTIF('BC Thang'!$I$4:$I$3085,$A42) -> 0 | D42: =B42*C42 -> 0
A43: =IFERROR(__xludf.DUMMYFUNCTION("""COMPUTED_VALUE"""),"Ecanis+") -> Ecanis+ | B43: =IFERROR(__xludf.DUMMYFUNCTION("""COMPUTED_VALUE"""),70.0) -> 70 | C43: =COUNTIF('BC Thang'!$I$4:$I$3085,$A43) -> 0 | D43: =B43*C43 -> 0
A44: =IFERROR(__xludf.DUMMYFUNCTION("""COMPUTED_VALUE"""),"FPV-") -> FPV- | B44: =IFERROR(__xludf.DUMMYFUNCTION("""COMPUTED_VALUE"""),70.0) -> 70 | C44: =COUNTIF('BC Thang'!$I$4:$I$3085,$A44) -> 3 | D44: =B44*C44 -> 210
A45: =IFERROR(__xludf.DUMMYFUNCTION("""COMPUTED_VALUE"""),"FPV+") -> FPV+ | B45: =IFERROR(__xludf.DUMMYFUNCTION("""COMPUTED_VALUE"""),70.0) -> 70 | C45: =COUNTIF('BC Thang'!$I$4:$I$3085,$A45) -> 0 | D45: =B45*C45 -> 0
A46: =IFERROR(__xludf.DUMMYFUNCTION("""COMPUTED_VALUE"""),"Gây mê lớn") -> Gây mê lớn | B46: =IFERROR(__xludf.DUMMYFUNCTION("""COMPUTED_VALUE"""),30.0) -> 30 | C46: =COUNTIF('BC Thang'!$I$4:$I$3085,$A46) -> 0 | D46: =B46*C46 -> 0
A47: =IFERROR(__xludf.DUMMYFUNCTION("""COMPUTED_VALUE"""),"Gây mê nhỏ") -> Gây mê nhỏ | B47: =IFERROR(__xludf.DUMMYFUNCTION("""COMPUTED_VALUE"""),15.0) -> 15 | C47: =COUNTIF('BC Thang'!$I$4:$I$3085,$A47) -> 2 | D47: =B47*C47 -> 30
A48: =IFERROR(__xludf.DUMMYFUNCTION("""COMPUTED_VALUE"""),"Giấy kiểm dịch đi máy bay") -> Giấy kiểm dịch đi máy bay | B48: =IFERROR(__xludf.DUMMYFUNCTION("""COMPUTED_VALUE"""),250.0) -> 250 | C48: =COUNTIF('BC Thang'!$I$4:$I$3085,$A48) -> 0 | D48: =B48*C48 -> 0
A49: =IFERROR(__xludf.DUMMYFUNCTION("""COMPUTED_VALUE"""),"HCT") -> HCT | B49: =IFERROR(__xludf.DUMMYFUNCTION("""COMPUTED_VALUE"""),10.0) -> 10 | C49: =COUNTIF('BC Thang'!$I$4:$I$3085,$A49) -> 0 | D49: =B49*C49 -> 0
A50: =IFERROR(__xludf.DUMMYFUNCTION("""COMPUTED_VALUE"""),"Hoá chất truyền máu") -> Hoá chất truyền máu | B50: =IFERROR(__xludf.DUMMYFUNCTION("""COMPUTED_VALUE"""),50.0) -> 50 | C50: =COUNTIF('BC Thang'!$I$4:$I$3085,$A50) -> 0 | D50: =B50*C50 -> 0
A51: =IFERROR(__xludf.DUMMYFUNCTION("""COMPUTED_VALUE"""),"Hút dịch") -> Hút dịch | B51: =IFERROR(__xludf.DUMMYFUNCTION("""COMPUTED_VALUE"""),15.0) -> 15 | C51: =COUNTIF('BC Thang'!$I$4:$I$3085,$A51) -> 0 | D51: =B51*C51 -> 0
A52: =IFERROR(__xludf.DUMMYFUNCTION("""COMPUTED_VALUE"""),"Khai khí quản") -> Khai khí quản | B52: =IFERROR(__xludf.DUMMYFUNCTION("""COMPUTED_VALUE"""),30.0) -> 30 | C52: =COUNTIF('BC Thang'!$I$4:$I$3085,$A52) -> 0 | D52: =B52*C52 -> 0
A53: =IFERROR(__xludf.DUMMYFUNCTION("""COMPUTED_VALUE"""),"Khám lâm sàng") -> Khám lâm sàng | B53: =IFERROR(__xludf.DUMMYFUNCTION("""COMPUTED_VALUE"""),5.0) -> 5 | C53: =COUNTIF('BC Thang'!$I$4:$I$3085,$A53) -> 6 | D53: =B53*C53 -> 30
A54: =IFERROR(__xludf.DUMMYFUNCTION("""COMPUTED_VALUE"""),"Lấy cao răng") -> Lấy cao răng | B54: =IFERROR(__xludf.DUMMYFUNCTION("""COMPUTED_VALUE"""),32.0) -> 32 | C54: =COUNTIF('BC Thang'!$I$4:$I$3085,$A54) -> 0 | D54: =B54*C54 -> 0
A55: =IFERROR(__xludf.DUMMYFUNCTION("""COMPUTED_VALUE"""),"Lepto -") -> Lepto - | B55: =IFERROR(__xludf.DUMMYFUNCTION("""COMPUTED_VALUE"""),70.0) -> 70 | C55: =COUNTIF('BC Thang'!$I$4:$I$3085,$A55) -> 0 | D55: =B55*C55 -> 0
A56: =IFERROR(__xludf.DUMMYFUNCTION("""COMPUTED_VALUE"""),"Lepto +") -> Lepto + | B56: =IFERROR(__xludf.DUMMYFUNCTION("""COMPUTED_VALUE"""),70.0) -> 70 | C56: =COUNTIF('BC Thang'!$I$4:$I$3085,$A56) -> 0 | D56: =B56*C56 -> 0
A57: =IFERROR(__xludf.DUMMYFUNCTION("""COMPUTED_VALUE"""),"Loa cổ") -> Loa cổ | B57: =IFERROR(__xludf.DUMMYFUNCTION("""COMPUTED_VALUE"""),30.0) -> 30 | C57: =COUNTIF('BC Thang'!$I$4:$I$3085,$A57) -> 0 | D57: =B57*C57 -> 0
A58: =IFERROR(__xludf.DUMMYFUNCTION("""COMPUTED_VALUE"""),"Lưu điều trị lớn") -> Lưu điều trị lớn | B58: =IFERROR(__xludf.DUMMYFUNCTION("""COMPUTED_VALUE"""),300.0) -> 300 | C58: =COUNTIF('BC Thang'!$I$4:$I$3085,$A58) -> 1 | D58: =B58*C58 -> 300
A59: =IFERROR(__xludf.DUMMYFUNCTION("""COMPUTED_VALUE"""),"Lưu điều trị nhỏ") -> Lưu điều trị nhỏ | B59: =IFERROR(__xludf.DUMMYFUNCTION("""COMPUTED_VALUE"""),200.0) -> 200 | C59: =COUNTIF('BC Thang'!$I$4:$I$3085,$A59) -> 21 | D59: =B59*C59 -> 4200
A60: =IFERROR(__xludf.DUMMYFUNCTION("""COMPUTED_VALUE"""),"Lưu hậu phẫu lớn") -> Lưu hậu phẫu lớn | B60: =IFERROR(__xludf.DUMMYFUNCTION("""COMPUTED_VALUE"""),400.0) -> 400 | C60: =COUNTIF('BC Thang'!$I$4:$I$3085,$A60) -> 0 | D60: =B60*C60 -> 0
A61: =IFERROR(__xludf.DUMMYFUNCTION("""COMPUTED_VALUE"""),"Lưu hậu phẫu nhỏ") -> Lưu hậu phẫu nhỏ | B61: =IFERROR(__xludf.DUMMYFUNCTION("""COMPUTED_VALUE"""),200.0) -> 200 | C61: =COUNTIF('BC Thang'!$I$4:$I$3085,$A61) -> 2 | D61: =B61*C61 -> 400
A62: =IFERROR(__xludf.DUMMYFUNCTION("""COMPUTED_VALUE"""),"Lưu trú lớn") -> Lưu trú lớn | B62: =IFERROR(__xludf.DUMMYFUNCTION("""COMPUTED_VALUE"""),120.0) -> 120 | C62: =COUNTIF('BC Thang'!$I$4:$I$3085,$A62) -> 0 | D62: =B62*C62 -> 0
A63: =IFERROR(__xludf.DUMMYFUNCTION("""COMPUTED_VALUE"""),"Lưu trú nhỏ") -> Lưu trú nhỏ | B63: =IFERROR(__xludf.DUMMYFUNCTION("""COMPUTED_VALUE"""),60.0) -> 60 | C63: =COUNTIF('BC Thang'!$I$4:$I$3085,$A63) -> 7 | D63: =B63*C63 -> 420
A64: =IFERROR(__xludf.DUMMYFUNCTION("""COMPUTED_VALUE"""),"Mài răng") -> Mài răng | B64: =IFERROR(__xludf.DUMMYFUNCTION("""COMPUTED_VALUE"""),20.0) -> 20 | C64: =COUNTIF('BC Thang'!$I$4:$I$3085,$A64) -> 0 | D64: =B64*C64 -> 0
A65: =IFERROR(__xludf.DUMMYFUNCTION("""COMPUTED_VALUE"""),"Men tiêu hoá") -> Men tiêu hoá | B65: =IFERROR(__xludf.DUMMYFUNCTION("""COMPUTED_VALUE"""),3.0) -> 3 | C65: =COUNTIF('BC Thang'!$I$4:$I$3085,$A65) -> 11 | D65: =B65*C65 -> 33
A66: =IFERROR(__xludf.DUMMYFUNCTION("""COMPUTED_VALUE"""),"Nặn tuyến hôi") -> Nặn tuyến hôi | B66: =IFERROR(__xludf.DUMMYFUNCTION("""COMPUTED_VALUE"""),5.0) -> 5 | C66: =COUNTIF('BC Thang'!$I$4:$I$3085,$A66) -> 0 | D66: =B66*C66 -> 0
A67: =IFERROR(__xludf.DUMMYFUNCTION("""COMPUTED_VALUE"""),"Ngoài giờ") -> Ngoài giờ | B67: =IFERROR(__xludf.DUMMYFUNCTION("""COMPUTED_VALUE"""),10.0) -> 10 | C67: =COUNTIF('BC Thang'!$I$4:$I$3085,$A67) -> 1 | D67: =B67*C67 -> 10
A68: =IFERROR(__xludf.DUMMYFUNCTION("""COMPUTED_VALUE"""),"Thụt rửa trực tràng") -> Thụt rửa trực tràng | B68: =IFERROR(__xludf.DUMMYFUNCTION("""COMPUTED_VALUE"""),20.0) -> 20 | C68: =COUNTIF('BC Thang'!$I$4:$I$3085,$A68) -> 1 | D68: =B68*C68 -> 20
A69: =IFERROR(__xludf.DUMMYFUNCTION("""COMPUTED_VALUE"""),"Nhuộm soi máu") -> Nhuộm soi máu | B69: =IFERROR(__xludf.DUMMYFUNCTION("""COMPUTED_VALUE"""),15.0) -> 15 | C69: =COUNTIF('BC Thang'!$I$4:$I$3085,$A69) -> 0 | D69: =B69*C69 -> 0
A70: =IFERROR(__xludf.DUMMYFUNCTION("""COMPUTED_VALUE"""),"Petshop") -> Petshop | C70: =COUNTIF('BC Thang'!$I$4:$I$3085,$A70) -> 38 | D70: =B70*C70 -> 0
A71: =IFERROR(__xludf.DUMMYFUNCTION("""COMPUTED_VALUE"""),"PT bảo tồn mắt lớn ") -> PT bảo tồn mắt lớn | B71: =IFERROR(__xludf.DUMMYFUNCTION("""COMPUTED_VALUE"""),50.0) -> 50 | C71: =COUNTIF('BC Thang'!$I$4:$I$3085,$A71) -> 0 | D71: =B71*C71 -> 0
A72: =IFERROR(__xludf.DUMMYFUNCTION("""COMPUTED_VALUE"""),"PT bảo tồn mắt nhỏ") -> PT bảo tồn mắt nhỏ | B72: =IFERROR(__xludf.DUMMYFUNCTION("""COMPUTED_VALUE"""),25.0) -> 25 | C72: =COUNTIF('BC Thang'!$I$4:$I$3085,$A72) -> 0 | D72: =B72*C72 -> 0
A73: =IFERROR(__xludf.DUMMYFUNCTION("""COMPUTED_VALUE"""),"PT cắt đuôi lớn") -> PT cắt đuôi lớn | B73: =IFERROR(__xludf.DUMMYFUNCTION("""COMPUTED_VALUE"""),37.0) -> 37 | C73: =COUNTIF('BC Thang'!$I$4:$I$3085,$A73) -> 0 | D73: =B73*C73 -> 0
A74: =IFERROR(__xludf.DUMMYFUNCTION("""COMPUTED_VALUE"""),"PT cắt đuôi SS") -> PT cắt đuôi SS | B74: =IFERROR(__xludf.DUMMYFUNCTION("""COMPUTED_VALUE"""),10.0) -> 10 | C74: =COUNTIF('BC Thang'!$I$4:$I$3085,$A74) -> 1 | D74: =B74*C74 -> 10
A75: =IFERROR(__xludf.DUMMYFUNCTION("""COMPUTED_VALUE"""),"PT cắt mộng mắt") -> PT cắt mộng mắt | B75: =IFERROR(__xludf.DUMMYFUNCTION("""COMPUTED_VALUE"""),17.0) -> 17 | C75: =COUNTIF('BC Thang'!$I$4:$I$3085,$A75) -> 0 | D75: =B75*C75 -> 0
A76: =IFERROR(__xludf.DUMMYFUNCTION("""COMPUTED_VALUE"""),"PT cắt tai") -> PT cắt tai | B76: =IFERROR(__xludf.DUMMYFUNCTION("""COMPUTED_VALUE"""),40.0) -> 40 | C76: =COUNTIF('BC Thang'!$I$4:$I$3085,$A76) -> 0 | D76: =B76*C76 -> 0
A77: =IFERROR(__xludf.DUMMYFUNCTION("""COMPUTED_VALUE"""),"PT chết lưu thai") -> PT chết lưu thai | B77: =IFERROR(__xludf.DUMMYFUNCTION("""COMPUTED_VALUE"""),120.0) -> 120 | C77: =COUNTIF('BC Thang'!$I$4:$I$3085,$A77) -> 0 | D77: =B77*C77 -> 0
A78: =IFERROR(__xludf.DUMMYFUNCTION("""COMPUTED_VALUE"""),"PT chuyển giới chó") -> PT chuyển giới chó | B78: =IFERROR(__xludf.DUMMYFUNCTION("""COMPUTED_VALUE"""),163.0) -> 163 | C78: =COUNTIF('BC Thang'!$I$4:$I$3085,$A78) -> 0 | D78: =B78*C78 -> 0
A79: =IFERROR(__xludf.DUMMYFUNCTION("""COMPUTED_VALUE"""),"PT chuyển giới mèo") -> PT chuyển giới mèo | B79: =IFERROR(__xludf.DUMMYFUNCTION("""COMPUTED_VALUE"""),85.0) -> 85 | C79: =COUNTIF('BC Thang'!$I$4:$I$3085,$A79) -> 0 | D79: =B79*C79 -> 0
A80: =IFERROR(__xludf.DUMMYFUNCTION("""COMPUTED_VALUE"""),"PT hoạn chó lớn") -> PT hoạn chó lớn | B80: =IFERROR(__xludf.DUMMYFUNCTION("""COMPUTED_VALUE"""),105.0) -> 105 | C80: =COUNTIF('BC Thang'!$I$4:$I$3085,$A80) -> 1 | D80: =B80*C80 -> 105
A81: =IFERROR(__xludf.DUMMYFUNCTION("""COMPUTED_VALUE"""),"PT hoạn chó nhỏ") -> PT hoạn chó nhỏ | B81: =IFERROR(__xludf.DUMMYFUNCTION("""COMPUTED_VALUE"""),50.0) -> 50 | C81: =COUNTIF('BC Thang'!$I$4:$I$3085,$A81) -> 2 | D81: =B81*C81 -> 100
A82: =IFERROR(__xludf.DUMMYFUNCTION("""COMPUTED_VALUE"""),"PT hoạn mèo") -> PT hoạn mèo | B82: =IFERROR(__xludf.DUMMYFUNCTION("""COMPUTED_VALUE"""),36.0) -> 36 | C82: =COUNTIF('BC Thang'!$I$4:$I$3085,$A82) -> 6 | D82: =B82*C82 -> 216
A83: =IFERROR(__xludf.DUMMYFUNCTION("""COMPUTED_VALUE"""),"PT khác lớn") -> PT khác lớn | B83: =IFERROR(__xludf.DUMMYFUNCTION("""COMPUTED_VALUE"""),100.0) -> 100 | C83: =COUNTIF('BC Thang'!$I$4:$I$3085,$A83) -> 0 | D83: =B83*C83 -> 0
A84: =IFERROR(__xludf.DUMMYFUNCTION("""COMPUTED_VALUE"""),"PT khác nhỏ") -> PT khác nhỏ | B84: =IFERROR(__xludf.DUMMYFUNCTION("""COMPUTED_VALUE"""),50.0) -> 50 | C84: =COUNTIF('BC Thang'!$I$4:$I$3085,$A84) -> 1 | D84: =B84*C84 -> 50
A85: =IFERROR(__xludf.DUMMYFUNCTION("""COMPUTED_VALUE"""),"PT khoét mắt lớn") -> PT khoét mắt lớn | B85: =IFERROR(__xludf.DUMMYFUNCTION("""COMPUTED_VALUE"""),36.0) -> 36 | C85: =COUNTIF('BC Thang'!$I$4:$I$3085,$A85) -> 0 | D85: =B85*C85 -> 0
A86: =IFERROR(__xludf.DUMMYFUNCTION("""COMPUTED_VALUE"""),"PT khoét mắt nhỏ") -> PT khoét mắt nhỏ | B86: =IFERROR(__xludf.DUMMYFUNCTION("""COMPUTED_VALUE"""),20.0) -> 20 | C86: =COUNTIF('BC Thang'!$I$4:$I$3085,$A86) -> 0 | D86: =B86*C86 -> 0
A87: =IFERROR(__xludf.DUMMYFUNCTION("""COMPUTED_VALUE"""),"PT mổ đẻ chó nhỏ") -> PT mổ đẻ chó nhỏ | B87: =IFERROR(__xludf.DUMMYFUNCTION("""COMPUTED_VALUE"""),70.0) -> 70 | C87: =COUNTIF('BC Thang'!$I$4:$I$3085,$A87) -> 0 | D87: =B87*C87 -> 0
A88: =IFERROR(__xludf.DUMMYFUNCTION("""COMPUTED_VALUE"""),"PT mổ đẻ chó to") -> PT mổ đẻ chó to | B88: =IFERROR(__xludf.DUMMYFUNCTION("""COMPUTED_VALUE"""),100.0) -> 100 | C88: =COUNTIF('BC Thang'!$I$4:$I$3085,$A88) -> 0 | D88: =B88*C88 -> 0
A89: =IFERROR(__xludf.DUMMYFUNCTION("""COMPUTED_VALUE"""),"PT mổ đẻ mèo") -> PT mổ đẻ mèo | B89: =IFERROR(__xludf.DUMMYFUNCTION("""COMPUTED_VALUE"""),50.0) -> 50 | C89: =COUNTIF('BC Thang'!$I$4:$I$3085,$A89) -> 0 | D89: =B89*C89 -> 0
A90: =IFERROR(__xludf.DUMMYFUNCTION("""COMPUTED_VALUE"""),"PT tháo khớp") -> PT tháo khớp | B90: =IFERROR(__xludf.DUMMYFUNCTION("""COMPUTED_VALUE"""),63.0) -> 63 | C90: =COUNTIF('BC Thang'!$I$4:$I$3085,$A90) -> 0 | D90: =B90*C90 -> 0
A91: =IFERROR(__xludf.DUMMYFUNCTION("""COMPUTED_VALUE"""),"PT thiến chó lớn") -> PT thiến chó lớn | B91: =IFERROR(__xludf.DUMMYFUNCTION("""COMPUTED_VALUE"""),35.0) -> 35 | C91: =COUNTIF('BC Thang'!$I$4:$I$3085,$A91) -> 0 | D91: =B91*C91 -> 0
A92: =IFERROR(__xludf.DUMMYFUNCTION("""COMPUTED_VALUE"""),"PT thiến chó nhỏ") -> PT thiến chó nhỏ | B92: =IFERROR(__xludf.DUMMYFUNCTION("""COMPUTED_VALUE"""),17.0) -> 17 | C92: =COUNTIF('BC Thang'!$I$4:$I$3085,$A92) -> 0 | D92: =B92*C92 -> 0
A93: =IFERROR(__xludf.DUMMYFUNCTION("""COMPUTED_VALUE"""),"PT thiến mèo") -> PT thiến mèo | B93: =IFERROR(__xludf.DUMMYFUNCTION("""COMPUTED_VALUE"""),16.0) -> 16 | C93: =COUNTIF('BC Thang'!$I$4:$I$3085,$A93) -> 2 | D93: =B93*C93 -> 32
A94: =IFERROR(__xludf.DUMMYFUNCTION("""COMPUTED_VALUE"""),"PT viêm tử cung") -> PT viêm tử cung | B94: =IFERROR(__xludf.DUMMYFUNCTION("""COMPUTED_VALUE"""),140.0) -> 140 | C94: =COUNTIF('BC Thang'!$I$4:$I$3085,$A94) -> 0 | D94: =B94*C94 -> 0
A95: =IFERROR(__xludf.DUMMYFUNCTION("""COMPUTED_VALUE"""),"PT vùi mộng mắt") -> PT vùi mộng mắt | B95: =IFERROR(__xludf.DUMMYFUNCTION("""COMPUTED_VALUE"""),37.0) -> 37 | C95: =COUNTIF('BC Thang'!$I$4:$I$3085,$A95) -> 0 | D95: =B95*C95 -> 0
A96: =IFERROR(__xludf.DUMMYFUNCTION("""COMPUTED_VALUE"""),"PT xương lớn") -> PT xương lớn | B96: =IFERROR(__xludf.DUMMYFUNCTION("""COMPUTED_VALUE"""),500.0) -> 500 | C96: =COUNTIF('BC Thang'!$I$4:$I$3085,$A96) -> 0 | D96: =B96*C96 -> 0
A97: =IFERROR(__xludf.DUMMYFUNCTION("""COMPUTED_VALUE"""),"PT xương nhỏ") -> PT xương nhỏ | B97: =IFERROR(__xludf.DUMMYFUNCTION("""COMPUTED_VALUE"""),350.0) -> 350 | C97: =COUNTIF('BC Thang'!$I$4:$I$3085,$A97) -> 0 | D97: =B97*C97 -> 0
A98: =IFERROR(__xludf.DUMMYFUNCTION("""COMPUTED_VALUE"""),"PT sỏi lớn") -> PT sỏi lớn | B98: =IFERROR(__xludf.DUMMYFUNCTION("""COMPUTED_VALUE"""),500.0) -> 500 | C98: =COUNTIF('BC Thang'!$I$4:$I$3085,$A98) -> 0 | D98: =B98*C98 -> 0
A99: =IFERROR(__xludf.DUMMYFUNCTION("""COMPUTED_VALUE"""),"PT sỏi nhỏ") -> PT sỏi nhỏ | B99: =IFERROR(__xludf.DUMMYFUNCTION("""COMPUTED_VALUE"""),350.0) -> 350 | C99: =COUNTIF('BC Thang'!$I$4:$I$3085,$A99) -> 0 | D99: =B99*C99 -> 0
A100: =IFERROR(__xludf.DUMMYFUNCTION("""COMPUTED_VALUE"""),"Siêu âm") -> Siêu âm | B100: =IFERROR(__xludf.DUMMYFUNCTION("""COMPUTED_VALUE"""),10.0) -> 10 | C100: =COUNTIF('BC Thang'!$I$4:$I$3085,$A100) -> 10 | D100: =B100*C100 -> 100
...

Sheet Ma hang
A1: =IFERROR(__xludf.DUMMYFUNCTION("importrange(""https://docs.google.com/spreadsheets/d/1ImCdkYhsUqsakZA8jNZp7UrWFPNTrMyfZQst-0aGkKM/edit?gid=0#gid=0"",""Ma hang!A1:D500"")"),"Mã Hàng") -> Mã Hàng | B1: =IFERROR(__xludf.DUMMYFUNCTION("""COMPUTED_VALUE"""),"Tên hàng") -> Tên hàng | C1: =IFERROR(__xludf.DUMMYFUNCTION("""COMPUTED_VALUE"""),"Đơn vị Tính") -> Đơn vị Tính | D1: =IFERROR(__xludf.DUMMYFUNCTION("""COMPUTED_VALUE"""),"Giá nhập TB") -> Giá nhập TB
A2: =IFERROR(__xludf.DUMMYFUNCTION("""COMPUTED_VALUE"""),"APC") -> APC | B2: =IFERROR(__xludf.DUMMYFUNCTION("""COMPUTED_VALUE"""),"A chymotrypsin") -> A chymotrypsin | C2: =IFERROR(__xludf.DUMMYFUNCTION("""COMPUTED_VALUE"""),"Viên") -> Viên | D2: =IFERROR(__xludf.DUMMYFUNCTION("""COMPUTED_VALUE"""),250.0) -> 250
A3: =IFERROR(__xludf.DUMMYFUNCTION("""COMPUTED_VALUE"""),"ACV") -> ACV | B3: =IFERROR(__xludf.DUMMYFUNCTION("""COMPUTED_VALUE"""),"Acyclovir 200") -> Acyclovir 200 | C3: =IFERROR(__xludf.DUMMYFUNCTION("""COMPUTED_VALUE"""),"Viên") -> Viên | D3: =IFERROR(__xludf.DUMMYFUNCTION("""COMPUTED_VALUE"""),2414.285714285714) -> 2414.2857
A4: =IFERROR(__xludf.DUMMYFUNCTION("""COMPUTED_VALUE"""),"ADEVTM") -> ADEVTM | B4: =IFERROR(__xludf.DUMMYFUNCTION("""COMPUTED_VALUE"""),"AD3E Vitamin") -> AD3E Vitamin | C4: =IFERROR(__xludf.DUMMYFUNCTION("""COMPUTED_VALUE"""),"mL") -> mL | D4: =IFERROR(__xludf.DUMMYFUNCTION("""COMPUTED_VALUE"""),1400.0) -> 1400
A5: =IFERROR(__xludf.DUMMYFUNCTION("""COMPUTED_VALUE"""),"TKADL") -> TKADL | B5: =IFERROR(__xludf.DUMMYFUNCTION("""COMPUTED_VALUE"""),"Adrenalin") -> Adrenalin | C5: =IFERROR(__xludf.DUMMYFUNCTION("""COMPUTED_VALUE"""),"Ống") -> Ống | D5: =IFERROR(__xludf.DUMMYFUNCTION("""COMPUTED_VALUE"""),3000.0) -> 3000
A6: =IFERROR(__xludf.DUMMYFUNCTION("""COMPUTED_VALUE"""),"AMVTM") -> AMVTM | B6: =IFERROR(__xludf.DUMMYFUNCTION("""COMPUTED_VALUE"""),"Aminovit") -> Aminovit | C6: =IFERROR(__xludf.DUMMYFUNCTION("""COMPUTED_VALUE"""),"mL") -> mL | D6: =IFERROR(__xludf.DUMMYFUNCTION("""COMPUTED_VALUE"""),300.0) -> 300
A7: =IFERROR(__xludf.DUMMYFUNCTION("""COMPUTED_VALUE"""),"AMOX") -> AMOX | B7: =IFERROR(__xludf.DUMMYFUNCTION("""COMPUTED_VALUE"""),"Amoxicilin 250ml") -> Amoxicilin 250ml | C7: =IFERROR(__xludf.DUMMYFUNCTION("""COMPUTED_VALUE"""),"mL") -> mL | D7: =IFERROR(__xludf.DUMMYFUNCTION("""COMPUTED_VALUE"""),0.0) -> 0
A8: =IFERROR(__xludf.DUMMYFUNCTION("""COMPUTED_VALUE"""),"ATD") -> ATD | B8: =IFERROR(__xludf.DUMMYFUNCTION("""COMPUTED_VALUE"""),"Antiderm bôi ghẻ") -> Antiderm bôi ghẻ | C8: =IFERROR(__xludf.DUMMYFUNCTION("""COMPUTED_VALUE"""),"Tuýp") -> Tuýp | D8: =IFERROR(__xludf.DUMMYFUNCTION("""COMPUTED_VALUE"""),35000.0) -> 35000
A9: =IFERROR(__xludf.DUMMYFUNCTION("""COMPUTED_VALUE"""),"APT") -> APT | B9: =IFERROR(__xludf.DUMMYFUNCTION("""COMPUTED_VALUE"""),"Áo phẫu thuật") -> Áo phẫu thuật | C9: =IFERROR(__xludf.DUMMYFUNCTION("""COMPUTED_VALUE"""),"Cái") -> Cái | D9: =IFERROR(__xludf.DUMMYFUNCTION("""COMPUTED_VALUE"""),300000.0) -> 300000
A10: =IFERROR(__xludf.DUMMYFUNCTION("""COMPUTED_VALUE"""),"ATP") -> ATP | B10: =IFERROR(__xludf.DUMMYFUNCTION("""COMPUTED_VALUE"""),"Atropin") -> Atropin | C10: =IFERROR(__xludf.DUMMYFUNCTION("""COMPUTED_VALUE"""),"mL") -> mL | D10: =IFERROR(__xludf.DUMMYFUNCTION("""COMPUTED_VALUE"""),163.33333333333334) -> 163.33333
A11: =IFERROR(__xludf.DUMMYFUNCTION("""COMPUTED_VALUE"""),"AZT") -> AZT | B11: =IFERROR(__xludf.DUMMYFUNCTION("""COMPUTED_VALUE"""),"Azithromycin ") -> Azithromycin | C11: =IFERROR(__xludf.DUMMYFUNCTION("""COMPUTED_VALUE"""),"Gam") -> Gam | D11: =IFERROR(__xludf.DUMMYFUNCTION("""COMPUTED_VALUE"""),20000.0) -> 20000
A12: =IFERROR(__xludf.DUMMYFUNCTION("""COMPUTED_VALUE"""),"AZT250") -> AZT250 | B12: =IFERROR(__xludf.DUMMYFUNCTION("""COMPUTED_VALUE"""),"Azithromycin 250mg") -> Azithromycin 250mg | C12: =IFERROR(__xludf.DUMMYFUNCTION("""COMPUTED_VALUE"""),"Viên") -> Viên | D12: =IFERROR(__xludf.DUMMYFUNCTION("""COMPUTED_VALUE"""),1950.0) -> 1950
A13: =IFERROR(__xludf.DUMMYFUNCTION("""COMPUTED_VALUE"""),"AZT500") -> AZT500 | B13: =IFERROR(__xludf.DUMMYFUNCTION("""COMPUTED_VALUE"""),"Azithromycin 500mg") -> Azithromycin 500mg | C13: =IFERROR(__xludf.DUMMYFUNCTION("""COMPUTED_VALUE"""),"Viên") -> Viên | D13: =IFERROR(__xludf.DUMMYFUNCTION("""COMPUTED_VALUE"""),4683.166666666666) -> 4683.1667
A14: =IFERROR(__xludf.DUMMYFUNCTION("""COMPUTED_VALUE"""),"BCL") -> BCL | B14: =IFERROR(__xludf.DUMMYFUNCTION("""COMPUTED_VALUE"""),"B complex") -> B complex | C14: =IFERROR(__xludf.DUMMYFUNCTION("""COMPUTED_VALUE"""),"ml") -> ml | D14: =IFERROR(__xludf.DUMMYFUNCTION("""COMPUTED_VALUE"""),300.0) -> 300
A15: =IFERROR(__xludf.DUMMYFUNCTION("""COMPUTED_VALUE"""),"BCRT") -> BCRT | B15: =IFERROR(__xludf.DUMMYFUNCTION("""COMPUTED_VALUE"""),"Bàn chải rửa tay") -> Bàn chải rửa tay | C15: =IFERROR(__xludf.DUMMYFUNCTION("""COMPUTED_VALUE"""),"Cái") -> Cái | D15: =IFERROR(__xludf.DUMMYFUNCTION("""COMPUTED_VALUE"""),38000.0) -> 38000
A16: =IFERROR(__xludf.DUMMYFUNCTION("""COMPUTED_VALUE"""),"BIOGTT") -> BIOGTT | B16: =IFERROR(__xludf.DUMMYFUNCTION("""COMPUTED_VALUE"""),"BIO Genta-Tylosin") -> BIO Genta-Tylosin | C16: =IFERROR(__xludf.DUMMYFUNCTION("""COMPUTED_VALUE"""),"mL") -> mL | D16: =IFERROR(__xludf.DUMMYFUNCTION("""COMPUTED_VALUE"""),1100.0) -> 1100
A17: =IFERROR(__xludf.DUMMYFUNCTION("""COMPUTED_VALUE"""),"OCTC") -> OCTC | B17: =IFERROR(__xludf.DUMMYFUNCTION("""COMPUTED_VALUE"""),"BIO Oxytocin") -> BIO Oxytocin | C17: =IFERROR(__xludf.DUMMYFUNCTION("""COMPUTED_VALUE"""),"mL") -> mL | D17: =IFERROR(__xludf.DUMMYFUNCTION("""COMPUTED_VALUE"""),600.0) -> 600
A18: =IFERROR(__xludf.DUMMYFUNCTION("""COMPUTED_VALUE"""),"BS") -> BS | B18: =IFERROR(__xludf.DUMMYFUNCTION("""COMPUTED_VALUE"""),"BIO sone") -> BIO sone | C18: =IFERROR(__xludf.DUMMYFUNCTION("""COMPUTED_VALUE"""),"mL") -> mL | D18: =IFERROR(__xludf.DUMMYFUNCTION("""COMPUTED_VALUE"""),1300.0) -> 1300
A19: =IFERROR(__xludf.DUMMYFUNCTION("""COMPUTED_VALUE"""),"VTMB12T") -> VTMB12T | B19: =IFERROR(__xludf.DUMMYFUNCTION("""COMPUTED_VALUE"""),"BIO-FER+B12") -> BIO-FER+B12 | C19: =IFERROR(__xludf.DUMMYFUNCTION("""COMPUTED_VALUE"""),"mL") -> mL | D19: =IFERROR(__xludf.DUMMYFUNCTION("""COMPUTED_VALUE"""),500.0) -> 500
A20: =IFERROR(__xludf.DUMMYFUNCTION("""COMPUTED_VALUE"""),"BTC") -> BTC | B20: =IFERROR(__xludf.DUMMYFUNCTION("""COMPUTED_VALUE"""),"Bột thạch cao") -> Bột thạch cao | C20: =IFERROR(__xludf.DUMMYFUNCTION("""COMPUTED_VALUE"""),"cuộn") -> cuộn | D20: =IFERROR(__xludf.DUMMYFUNCTION("""COMPUTED_VALUE"""),15000.0) -> 15000
A21: =IFERROR(__xludf.DUMMYFUNCTION("""COMPUTED_VALUE"""),"BHXT") -> BHXT | B21: =IFERROR(__xludf.DUMMYFUNCTION("""COMPUTED_VALUE"""),"Bromhexine tiêm") -> Bromhexine tiêm | C21: =IFERROR(__xludf.DUMMYFUNCTION("""COMPUTED_VALUE"""),"mL") -> mL | D21: =IFERROR(__xludf.DUMMYFUNCTION("""COMPUTED_VALUE"""),1000.0) -> 1000
A22: =IFERROR(__xludf.DUMMYFUNCTION("""COMPUTED_VALUE"""),"BHXU") -> BHXU | B22: =IFERROR(__xludf.DUMMYFUNCTION("""COMPUTED_VALUE"""),"Bromhexine uống") -> Bromhexine uống | C22: =IFERROR(__xludf.DUMMYFUNCTION("""COMPUTED_VALUE"""),"Viên") -> Viên | D22: =IFERROR(__xludf.DUMMYFUNCTION("""COMPUTED_VALUE"""),180.0) -> 180
A23: =IFERROR(__xludf.DUMMYFUNCTION("""COMPUTED_VALUE"""),"CX") -> CX | B23: =IFERROR(__xludf.DUMMYFUNCTION("""COMPUTED_VALUE"""),"Canxi") -> Canxi | C23: =IFERROR(__xludf.DUMMYFUNCTION("""COMPUTED_VALUE"""),"Viên") -> Viên | D23: =IFERROR(__xludf.DUMMYFUNCTION("""COMPUTED_VALUE"""),230.0) -> 230
A24: =IFERROR(__xludf.DUMMYFUNCTION("""COMPUTED_VALUE"""),"CXT") -> CXT | B24: =IFERROR(__xludf.DUMMYFUNCTION("""COMPUTED_VALUE"""),"Canxi tiêm") -> Canxi tiêm | C24: =IFERROR(__xludf.DUMMYFUNCTION("""COMPUTED_VALUE"""),"mL") -> mL | D24: =IFERROR(__xludf.DUMMYFUNCTION("""COMPUTED_VALUE"""),425.0) -> 425
A25: =IFERROR(__xludf.DUMMYFUNCTION("""COMPUTED_VALUE"""),"CSTAN") -> CSTAN | B25: =IFERROR(__xludf.DUMMYFUNCTION("""COMPUTED_VALUE"""),"CasTran an thần") -> CasTran an thần | C25: =IFERROR(__xludf.DUMMYFUNCTION("""COMPUTED_VALUE"""),"mL") -> mL | D25: =IFERROR(__xludf.DUMMYFUNCTION("""COMPUTED_VALUE"""),1200.0) -> 1200
A26: =IFERROR(__xludf.DUMMYFUNCTION("""COMPUTED_VALUE"""),"CTZ") -> CTZ | B26: =IFERROR(__xludf.DUMMYFUNCTION("""COMPUTED_VALUE"""),"Ceftriazone_Cefuroxim (KS pha tiêm)") -> Ceftriazone_Cefuroxim (KS pha tiêm) | C26: =IFERROR(__xludf.DUMMYFUNCTION("""COMPUTED_VALUE"""),"Gam") -> Gam | D26: =IFERROR(__xludf.DUMMYFUNCTION("""COMPUTED_VALUE"""),20000.0) -> 20000
A27: =IFERROR(__xludf.DUMMYFUNCTION("""COMPUTED_VALUE"""),"CF500") -> CF500 | B27: =IFERROR(__xludf.DUMMYFUNCTION("""COMPUTED_VALUE"""),"Cephalexin 500") -> Cephalexin 500 | C27: =IFERROR(__xludf.DUMMYFUNCTION("""COMPUTED_VALUE"""),"Viên") -> Viên | D27: =IFERROR(__xludf.DUMMYFUNCTION("""COMPUTED_VALUE"""),1200.0) -> 1200
A28: =IFERROR(__xludf.DUMMYFUNCTION("""COMPUTED_VALUE"""),"CTRZ") -> CTRZ | B28: =IFERROR(__xludf.DUMMYFUNCTION("""COMPUTED_VALUE"""),"Cetirizin") -> Cetirizin | C28: =IFERROR(__xludf.DUMMYFUNCTION("""COMPUTED_VALUE"""),"Viên") -> Viên | D28: =IFERROR(__xludf.DUMMYFUNCTION("""COMPUTED_VALUE"""),200.0) -> 200
A29: =IFERROR(__xludf.DUMMYFUNCTION("""COMPUTED_VALUE"""),"CDTT") -> CDTT | B29: =IFERROR(__xludf.DUMMYFUNCTION("""COMPUTED_VALUE"""),"Chai đựng thuốc tắm") -> Chai đựng thuốc tắm | C29: =IFERROR(__xludf.DUMMYFUNCTION("""COMPUTED_VALUE"""),"Chai") -> Chai | D29: =IFERROR(__xludf.DUMMYFUNCTION("""COMPUTED_VALUE"""),1200.0) -> 1200
A30: =IFERROR(__xludf.DUMMYFUNCTION("""COMPUTED_VALUE"""),"CKCG2/0") -> CKCG2/0 | B30: =IFERROR(__xludf.DUMMYFUNCTION("""COMPUTED_VALUE"""),"Chỉ catgut 2/0") -> Chỉ catgut 2/0 | C30: =IFERROR(__xludf.DUMMYFUNCTION("""COMPUTED_VALUE"""),"Sợi") -> Sợi | D30: =IFERROR(__xludf.DUMMYFUNCTION("""COMPUTED_VALUE"""),10000.0) -> 10000
A31: =IFERROR(__xludf.DUMMYFUNCTION("""COMPUTED_VALUE"""),"CKCG3/0") -> CKCG3/0 | B31: =IFERROR(__xludf.DUMMYFUNCTION("""COMPUTED_VALUE"""),"Chỉ catgut 3/0") -> Chỉ catgut 3/0 | C31: =IFERROR(__xludf.DUMMYFUNCTION("""COMPUTED_VALUE"""),"Sợi") -> Sợi | D31: =IFERROR(__xludf.DUMMYFUNCTION("""COMPUTED_VALUE"""),10000.0) -> 10000
A32: =IFERROR(__xludf.DUMMYFUNCTION("""COMPUTED_VALUE"""),"CKCG4/0") -> CKCG4/0 | B32: =IFERROR(__xludf.DUMMYFUNCTION("""COMPUTED_VALUE"""),"Chỉ catgut 4/0") -> Chỉ catgut 4/0 | C32: =IFERROR(__xludf.DUMMYFUNCTION("""COMPUTED_VALUE"""),"Sợi") -> Sợi | D32: =IFERROR(__xludf.DUMMYFUNCTION("""COMPUTED_VALUE"""),10000.0) -> 10000
A33: =IFERROR(__xludf.DUMMYFUNCTION("""COMPUTED_VALUE"""),"CKCGKK") -> CKCGKK | B33: =IFERROR(__xludf.DUMMYFUNCTION("""COMPUTED_VALUE"""),"Chỉ catgut không kim") -> Chỉ catgut không kim | C33: =IFERROR(__xludf.DUMMYFUNCTION("""COMPUTED_VALUE"""),"Sợi") -> Sợi | D33: =IFERROR(__xludf.DUMMYFUNCTION("""COMPUTED_VALUE"""),2000.0) -> 2000
A34: =IFERROR(__xludf.DUMMYFUNCTION("""COMPUTED_VALUE"""),"CKKTD") -> CKKTD | B34: =IFERROR(__xludf.DUMMYFUNCTION("""COMPUTED_VALUE"""),"Chỉ khâu không tiêu dù") -> Chỉ khâu không tiêu dù | C34: =IFERROR(__xludf.DUMMYFUNCTION("""COMPUTED_VALUE"""),"Mét") -> Mét | D34: =IFERROR(__xludf.DUMMYFUNCTION("""COMPUTED_VALUE"""),600.0) -> 600
A35: =IFERROR(__xludf.DUMMYFUNCTION("""COMPUTED_VALUE"""),"VCRKK3/0") -> VCRKK3/0 | B35: =IFERROR(__xludf.DUMMYFUNCTION("""COMPUTED_VALUE"""),"Chỉ khâu Vicryl không kim 3/0") -> Chỉ khâu Vicryl không kim 3/0 | C35: =IFERROR(__xludf.DUMMYFUNCTION("""COMPUTED_VALUE"""),"Sợi") -> Sợi | D35: =IFERROR(__xludf.DUMMYFUNCTION("""COMPUTED_VALUE"""),4875.0) -> 4875
A36: =IFERROR(__xludf.DUMMYFUNCTION("""COMPUTED_VALUE"""),"CKKT3/0KK") -> CKKT3/0KK | B36: =IFERROR(__xludf.DUMMYFUNCTION("""COMPUTED_VALUE"""),"Chỉ không tiêu 3/0 không kim") -> Chỉ không tiêu 3/0 không kim | C36: =IFERROR(__xludf.DUMMYFUNCTION("""COMPUTED_VALUE"""),"Sợi") -> Sợi | D36: =IFERROR(__xludf.DUMMYFUNCTION("""COMPUTED_VALUE"""),2000.0) -> 2000
A37: =IFERROR(__xludf.DUMMYFUNCTION("""COMPUTED_VALUE"""),"CKNL10/0") -> CKNL10/0 | B37: =IFERROR(__xludf.DUMMYFUNCTION("""COMPUTED_VALUE"""),"Chỉ nilon 10/0") -> Chỉ nilon 10/0 | C37: =IFERROR(__xludf.DUMMYFUNCTION("""COMPUTED_VALUE"""),"Sợi") -> Sợi | D37: =IFERROR(__xludf.DUMMYFUNCTION("""COMPUTED_VALUE"""),60000.0) -> 60000
A38: =IFERROR(__xludf.DUMMYFUNCTION("""COMPUTED_VALUE"""),"CKNL2/0") -> CKNL2/0 | B38: =IFERROR(__xludf.DUMMYFUNCTION("""COMPUTED_VALUE"""),"Chỉ nilon 2/0") -> Chỉ nilon 2/0 | C38: =IFERROR(__xludf.DUMMYFUNCTION("""COMPUTED_VALUE"""),"Sợi") -> Sợi | D38: =IFERROR(__xludf.DUMMYFUNCTION("""COMPUTED_VALUE"""),10000.0) -> 10000
A39: =IFERROR(__xludf.DUMMYFUNCTION("""COMPUTED_VALUE"""),"CKNL3/0") -> CKNL3/0 | B39: =IFERROR(__xludf.DUMMYFUNCTION("""COMPUTED_VALUE"""),"Chỉ nilon 3/0") -> Chỉ nilon 3/0 | C39: =IFERROR(__xludf.DUMMYFUNCTION("""COMPUTED_VALUE"""),"Sợi") -> Sợi | D39: =IFERROR(__xludf.DUMMYFUNCTION("""COMPUTED_VALUE"""),10000.0) -> 10000
A40: =IFERROR(__xludf.DUMMYFUNCTION("""COMPUTED_VALUE"""),"CKNL4/0") -> CKNL4/0 | B40: =IFERROR(__xludf.DUMMYFUNCTION("""COMPUTED_VALUE"""),"Chỉ nilon 4/0") -> Chỉ nilon 4/0 | C40: =IFERROR(__xludf.DUMMYFUNCTION("""COMPUTED_VALUE"""),"Sợi") -> Sợi | D40: =IFERROR(__xludf.DUMMYFUNCTION("""COMPUTED_VALUE"""),8333.0) -> 8333
A41: =IFERROR(__xludf.DUMMYFUNCTION("""COMPUTED_VALUE"""),"CKNL5/0") -> CKNL5/0 | B41: =IFERROR(__xludf.DUMMYFUNCTION("""COMPUTED_VALUE"""),"Chỉ nilon 5/0") -> Chỉ nilon 5/0 | C41: =IFERROR(__xludf.DUMMYFUNCTION("""COMPUTED_VALUE"""),"Sợi") -> Sợi | D41: =IFERROR(__xludf.DUMMYFUNCTION("""COMPUTED_VALUE"""),60000.0) -> 60000
A42: =IFERROR(__xludf.DUMMYFUNCTION("""COMPUTED_VALUE"""),"CKNL7/0") -> CKNL7/0 | B42: =IFERROR(__xludf.DUMMYFUNCTION("""COMPUTED_VALUE"""),"Chỉ nilon 7/0") -> Chỉ nilon 7/0 | C42: =IFERROR(__xludf.DUMMYFUNCTION("""COMPUTED_VALUE"""),"Sợi") -> Sợi | D42: =IFERROR(__xludf.DUMMYFUNCTION("""COMPUTED_VALUE"""),60000.0) -> 60000
A43: =IFERROR(__xludf.DUMMYFUNCTION("""COMPUTED_VALUE"""),"CKTVCR0") -> CKTVCR0 | B43: =IFERROR(__xludf.DUMMYFUNCTION("""COMPUTED_VALUE"""),"Chỉ tiêu vircyl 0") -> Chỉ tiêu vircyl 0 | C43: =IFERROR(__xludf.DUMMYFUNCTION("""COMPUTED_VALUE"""),"Sợi") -> Sợi | D43: =IFERROR(__xludf.DUMMYFUNCTION("""COMPUTED_VALUE"""),20000.0) -> 20000
A44: =IFERROR(__xludf.DUMMYFUNCTION("""COMPUTED_VALUE"""),"CKTVCR1") -> CKTVCR1 | B44: =IFERROR(__xludf.DUMMYFUNCTION("""COMPUTED_VALUE"""),"Chỉ tiêu vircyl 1") -> Chỉ tiêu vircyl 1 | C44: =IFERROR(__xludf.DUMMYFUNCTION("""COMPUTED_VALUE"""),"Sợi") -> Sợi | D44: =IFERROR(__xludf.DUMMYFUNCTION("""COMPUTED_VALUE"""),20000.0) -> 20000
A45: =IFERROR(__xludf.DUMMYFUNCTION("""COMPUTED_VALUE"""),"CKTVCR2") -> CKTVCR2 | B45: =IFERROR(__xludf.DUMMYFUNCTION("""COMPUTED_VALUE"""),"Chỉ tiêu vircyl 2") -> Chỉ tiêu vircyl 2 | C45: =IFERROR(__xludf.DUMMYFUNCTION("""COMPUTED_VALUE"""),"Sợi") -> Sợi | D45: =IFERROR(__xludf.DUMMYFUNCTION("""COMPUTED_VALUE"""),20000.0) -> 20000
A46: =IFERROR(__xludf.DUMMYFUNCTION("""COMPUTED_VALUE"""),"CKTVCR2/0") -> CKTVCR2/0 | B46: =IFERROR(__xludf.DUMMYFUNCTION("""COMPUTED_VALUE"""),"Chỉ tiêu vircyl 2/0") -> Chỉ tiêu vircyl 2/0 | C46: =IFERROR(__xludf.DUMMYFUNCTION("""COMPUTED_VALUE"""),"Sợi") -> Sợi | D46: =IFERROR(__xludf.DUMMYFUNCTION("""COMPUTED_VALUE"""),20000.0) -> 20000
A47: =IFERROR(__xludf.DUMMYFUNCTION("""COMPUTED_VALUE"""),"CKTVCR3/0") -> CKTVCR3/0 | B47: =IFERROR(__xludf.DUMMYFUNCTION("""COMPUTED_VALUE"""),"Chỉ tiêu vircyl 3/0") -> Chỉ tiêu vircyl 3/0 | C47: =IFERROR(__xludf.DUMMYFUNCTION("""COMPUTED_VALUE"""),"Sợi") -> Sợi | D47: =IFERROR(__xludf.DUMMYFUNCTION("""COMPUTED_VALUE"""),20000.0) -> 20000
A48: =IFERROR(__xludf.DUMMYFUNCTION("""COMPUTED_VALUE"""),"CKTVCR4/0") -> CKTVCR4/0 | B48: =IFERROR(__xludf.DUMMYFUNCTION("""COMPUTED_VALUE"""),"Chỉ tiêu vircyl 4/0") -> Chỉ tiêu vircyl 4/0 | C48: =IFERROR(__xludf.DUMMYFUNCTION("""COMPUTED_VALUE"""),"Sợi") -> Sợi | D48: =IFERROR(__xludf.DUMMYFUNCTION("""COMPUTED_VALUE"""),20000.0) -> 20000
A49: =IFERROR(__xludf.DUMMYFUNCTION("""COMPUTED_VALUE"""),"CKTVCR6/0") -> CKTVCR6/0 | B49: =IFERROR(__xludf.DUMMYFUNCTION("""COMPUTED_VALUE"""),"Chỉ tiêu vircyl 6/0") -> Chỉ tiêu vircyl 6/0 | C49: =IFERROR(__xludf.DUMMYFUNCTION("""COMPUTED_VALUE"""),"Sợi") -> Sợi | D49: =IFERROR(__xludf.DUMMYFUNCTION("""COMPUTED_VALUE"""),20000.0) -> 20000
A50: =IFERROR(__xludf.DUMMYFUNCTION("""COMPUTED_VALUE"""),"CHDX") -> CHDX | B50: =IFERROR(__xludf.DUMMYFUNCTION("""COMPUTED_VALUE"""),"Chlorhexidine") -> Chlorhexidine | C50: =IFERROR(__xludf.DUMMYFUNCTION("""COMPUTED_VALUE"""),"ml") -> ml | D50: =IFERROR(__xludf.DUMMYFUNCTION("""COMPUTED_VALUE"""),145.0) -> 145
A51: =IFERROR(__xludf.DUMMYFUNCTION("""COMPUTED_VALUE"""),"CHL") -> CHL | B51: =IFERROR(__xludf.DUMMYFUNCTION("""COMPUTED_VALUE"""),"Choliver") -> Choliver | C51: =IFERROR(__xludf.DUMMYFUNCTION("""COMPUTED_VALUE"""),"Viên") -> Viên | D51: =IFERROR(__xludf.DUMMYFUNCTION("""COMPUTED_VALUE"""),900.0) -> 900
A52: =IFERROR(__xludf.DUMMYFUNCTION("""COMPUTED_VALUE"""),"CHMS") -> CHMS | B52: =IFERROR(__xludf.DUMMYFUNCTION("""COMPUTED_VALUE"""),"Chymosin") -> Chymosin | C52: =IFERROR(__xludf.DUMMYFUNCTION("""COMPUTED_VALUE"""),"mL") -> mL | D52: =IFERROR(__xludf.DUMMYFUNCTION("""COMPUTED_VALUE"""),600.0) -> 600
A53: =IFERROR(__xludf.DUMMYFUNCTION("""COMPUTED_VALUE"""),"CMTD300") -> CMTD300 | B53: =IFERROR(__xludf.DUMMYFUNCTION("""COMPUTED_VALUE"""),"Cimetidine 300") -> Cimetidine 300 | C53: =IFERROR(__xludf.DUMMYFUNCTION("""COMPUTED_VALUE"""),"Viên") -> Viên | D53: =IFERROR(__xludf.DUMMYFUNCTION("""COMPUTED_VALUE"""),900.0) -> 900
A54: =IFERROR(__xludf.DUMMYFUNCTION("""COMPUTED_VALUE"""),"CPR500") -> CPR500 | B54: =IFERROR(__xludf.DUMMYFUNCTION("""COMPUTED_VALUE"""),"Ciprofloxacine 500") -> Ciprofloxacine 500 | C54: =IFERROR(__xludf.DUMMYFUNCTION("""COMPUTED_VALUE"""),"Viên") -> Viên | D54: =IFERROR(__xludf.DUMMYFUNCTION("""COMPUTED_VALUE"""),720.0) -> 720
A55: =IFERROR(__xludf.DUMMYFUNCTION("""COMPUTED_VALUE"""),"CLDMC150") -> CLDMC150 | B55: =IFERROR(__xludf.DUMMYFUNCTION("""COMPUTED_VALUE"""),"Clindamycin 150 mg") -> Clindamycin 150 mg | C55: =IFERROR(__xludf.DUMMYFUNCTION("""COMPUTED_VALUE"""),"Viên") -> Viên | D55: =IFERROR(__xludf.DUMMYFUNCTION("""COMPUTED_VALUE"""),1600.0) -> 1600
A56: =IFERROR(__xludf.DUMMYFUNCTION("""COMPUTED_VALUE"""),"CLRMB") -> CLRMB | B56: =IFERROR(__xludf.DUMMYFUNCTION("""COMPUTED_VALUE"""),"Cloramin B") -> Cloramin B | C56: =IFERROR(__xludf.DUMMYFUNCTION("""COMPUTED_VALUE"""),"Gam") -> Gam | D56: =IFERROR(__xludf.DUMMYFUNCTION("""COMPUTED_VALUE"""),200.0) -> 200
A57: =IFERROR(__xludf.DUMMYFUNCTION("""COMPUTED_VALUE"""),"CLPLRM4") -> CLPLRM4 | B57: =IFERROR(__xludf.DUMMYFUNCTION("""COMPUTED_VALUE"""),"Clorpheniramin 4mg") -> Clorpheniramin 4mg | C57: =IFERROR(__xludf.DUMMYFUNCTION("""COMPUTED_VALUE"""),"Viên") -> Viên | D57: =IFERROR(__xludf.DUMMYFUNCTION("""COMPUTED_VALUE"""),85.0) -> 85
A58: =IFERROR(__xludf.DUMMYFUNCTION("""COMPUTED_VALUE"""),"C90") -> C90 | B58: =IFERROR(__xludf.DUMMYFUNCTION("""COMPUTED_VALUE"""),"Cồn 90") -> Cồn 90 | C58: =IFERROR(__xludf.DUMMYFUNCTION("""COMPUTED_VALUE"""),"mL") -> mL | D58: =IFERROR(__xludf.DUMMYFUNCTION("""COMPUTED_VALUE"""),35.0) -> 35
A59: =IFERROR(__xludf.DUMMYFUNCTION("""COMPUTED_VALUE"""),"CPVD") -> CPVD | B59: =IFERROR(__xludf.DUMMYFUNCTION("""COMPUTED_VALUE"""),"Cồn povidone") -> Cồn povidone | C59: =IFERROR(__xludf.DUMMYFUNCTION("""COMPUTED_VALUE"""),"mL") -> mL | D59: =IFERROR(__xludf.DUMMYFUNCTION("""COMPUTED_VALUE"""),110.0) -> 110
A60: =IFERROR(__xludf.DUMMYFUNCTION("""COMPUTED_VALUE"""),"CTD") -> CTD | B60: =IFERROR(__xludf.DUMMYFUNCTION("""COMPUTED_VALUE"""),"Cồn tuyệt đối") -> Cồn tuyệt đối | C60: =IFERROR(__xludf.DUMMYFUNCTION("""COMPUTED_VALUE"""),"mL") -> mL | D60: =IFERROR(__xludf.DUMMYFUNCTION("""COMPUTED_VALUE"""),85.0) -> 85
A61: =IFERROR(__xludf.DUMMYFUNCTION("""COMPUTED_VALUE"""),"DPT11") -> DPT11 | B61: =IFERROR(__xludf.DUMMYFUNCTION("""COMPUTED_VALUE"""),"Dao phẫu thuật 11") -> Dao phẫu thuật 11 | C61: =IFERROR(__xludf.DUMMYFUNCTION("""COMPUTED_VALUE"""),"Cái") -> Cái | D61: =IFERROR(__xludf.DUMMYFUNCTION("""COMPUTED_VALUE"""),950.0) -> 950
A62: =IFERROR(__xludf.DUMMYFUNCTION("""COMPUTED_VALUE"""),"DPT12") -> DPT12 | B62: =IFERROR(__xludf.DUMMYFUNCTION("""COMPUTED_VALUE"""),"Dao phẫu thuật 12") -> Dao phẫu thuật 12 | C62: =IFERROR(__xludf.DUMMYFUNCTION("""COMPUTED_VALUE"""),"Cái") -> Cái | D62: =IFERROR(__xludf.DUMMYFUNCTION("""COMPUTED_VALUE"""),950.0) -> 950
A63: =IFERROR(__xludf.DUMMYFUNCTION("""COMPUTED_VALUE"""),"DPT15") -> DPT15 | B63: =IFERROR(__xludf.DUMMYFUNCTION("""COMPUTED_VALUE"""),"Dao phẫu thuật 15") -> Dao phẫu thuật 15 | C63: =IFERROR(__xludf.DUMMYFUNCTION("""COMPUTED_VALUE"""),"Cái") -> Cái | D63: =IFERROR(__xludf.DUMMYFUNCTION("""COMPUTED_VALUE"""),950.0) -> 950
A64: =IFERROR(__xludf.DUMMYFUNCTION("""COMPUTED_VALUE"""),"DPT21") -> DPT21 | B64: =IFERROR(__xludf.DUMMYFUNCTION("""COMPUTED_VALUE"""),"Dao phẫu thuật 21") -> Dao phẫu thuật 21 | C64: =IFERROR(__xludf.DUMMYFUNCTION("""COMPUTED_VALUE"""),"Cái") -> Cái | D64: =IFERROR(__xludf.DUMMYFUNCTION("""COMPUTED_VALUE"""),950.0) -> 950
A65: =IFERROR(__xludf.DUMMYFUNCTION("""COMPUTED_VALUE"""),"DTD") -> DTD | B65: =IFERROR(__xludf.DUMMYFUNCTION("""COMPUTED_VALUE"""),"Dây truyền dịch") -> Dây truyền dịch | C65: =IFERROR(__xludf.DUMMYFUNCTION("""COMPUTED_VALUE"""),"Cái") -> Cái | D65: =IFERROR(__xludf.DUMMYFUNCTION("""COMPUTED_VALUE"""),15000.0) -> 15000
A66: =IFERROR(__xludf.DUMMYFUNCTION("""COMPUTED_VALUE"""),"DTM") -> DTM | B66: =IFERROR(__xludf.DUMMYFUNCTION("""COMPUTED_VALUE"""),"Dây truyền máu") -> Dây truyền máu | C66: =IFERROR(__xludf.DUMMYFUNCTION("""COMPUTED_VALUE"""),"Cái") -> Cái | D66: =IFERROR(__xludf.DUMMYFUNCTION("""COMPUTED_VALUE"""),4000.0) -> 4000
A67: =IFERROR(__xludf.DUMMYFUNCTION("""COMPUTED_VALUE"""),"DPK") -> DPK | B67: =IFERROR(__xludf.DUMMYFUNCTION("""COMPUTED_VALUE"""),"Deparkin") -> Deparkin | C67: =IFERROR(__xludf.DUMMYFUNCTION("""COMPUTED_VALUE"""),"Viên") -> Viên | D67: =IFERROR(__xludf.DUMMYFUNCTION("""COMPUTED_VALUE"""),2500.0) -> 2500
A68: =IFERROR(__xludf.DUMMYFUNCTION("""COMPUTED_VALUE"""),"DXS") -> DXS | B68: =IFERROR(__xludf.DUMMYFUNCTION("""COMPUTED_VALUE"""),"Dexasone") -> Dexasone | C68: =IFERROR(__xludf.DUMMYFUNCTION("""COMPUTED_VALUE"""),"mL") -> mL | D68: =IFERROR(__xludf.DUMMYFUNCTION("""COMPUTED_VALUE"""),250.0) -> 250
A69: =IFERROR(__xludf.DUMMYFUNCTION("""COMPUTED_VALUE"""),"DVB") -> DVB | B69: =IFERROR(__xludf.DUMMYFUNCTION("""COMPUTED_VALUE"""),"Diệt ve bột") -> Diệt ve bột | C69: =IFERROR(__xludf.DUMMYFUNCTION("""COMPUTED_VALUE"""),"Gam") -> Gam | D69: =IFERROR(__xludf.DUMMYFUNCTION("""COMPUTED_VALUE"""),2000.0) -> 2000
A70: =IFERROR(__xludf.DUMMYFUNCTION("""COMPUTED_VALUE"""),"DVX") -> DVX | B70: =IFERROR(__xludf.DUMMYFUNCTION("""COMPUTED_VALUE"""),"Diệt ve xanh") -> Diệt ve xanh | C70: =IFERROR(__xludf.DUMMYFUNCTION("""COMPUTED_VALUE"""),"mL") -> mL | D70: =IFERROR(__xludf.DUMMYFUNCTION("""COMPUTED_VALUE"""),641.6666666666666) -> 641.66667
A71: =IFERROR(__xludf.DUMMYFUNCTION("""COMPUTED_VALUE"""),"DOC") -> DOC | B71: =IFERROR(__xludf.DUMMYFUNCTION("""COMPUTED_VALUE"""),"DOC") -> DOC | C71: =IFERROR(__xludf.DUMMYFUNCTION("""COMPUTED_VALUE"""),"mL") -> mL | D71: =IFERROR(__xludf.DUMMYFUNCTION("""COMPUTED_VALUE"""),1100.0) -> 1100
A72: =IFERROR(__xludf.DUMMYFUNCTION("""COMPUTED_VALUE"""),"DRMT") -> DRMT | B72: =IFERROR(__xludf.DUMMYFUNCTION("""COMPUTED_VALUE"""),"Doramectin") -> Doramectin | C72: =IFERROR(__xludf.DUMMYFUNCTION("""COMPUTED_VALUE"""),"mL") -> mL | D72: =IFERROR(__xludf.DUMMYFUNCTION("""COMPUTED_VALUE"""),6600.0) -> 6600
A73: =IFERROR(__xludf.DUMMYFUNCTION("""COMPUTED_VALUE"""),"DXL100") -> DXL100 | B73: =IFERROR(__xludf.DUMMYFUNCTION("""COMPUTED_VALUE"""),"Doxycycline 100mg") -> Doxycycline 100mg | C73: =IFERROR(__xludf.DUMMYFUNCTION("""COMPUTED_VALUE"""),"Viên") -> Viên | D73: =IFERROR(__xludf.DUMMYFUNCTION("""COMPUTED_VALUE"""),900.0) -> 900
A74: =IFERROR(__xludf.DUMMYFUNCTION("""COMPUTED_VALUE"""),"DPL") -> DPL | B74: =IFERROR(__xludf.DUMMYFUNCTION("""COMPUTED_VALUE"""),"Duphalac") -> Duphalac | C74: =IFERROR(__xludf.DUMMYFUNCTION("""COMPUTED_VALUE"""),"Gói") -> Gói | D74: =IFERROR(__xludf.DUMMYFUNCTION("""COMPUTED_VALUE"""),4750.0) -> 4750
A75: =IFERROR(__xludf.DUMMYFUNCTION("""COMPUTED_VALUE"""),"FLDX") -> FLDX | B75: =IFERROR(__xludf.DUMMYFUNCTION("""COMPUTED_VALUE"""),"Flodixine") -> Flodixine | C75: =IFERROR(__xludf.DUMMYFUNCTION("""COMPUTED_VALUE"""),"mL") -> mL | D75: =IFERROR(__xludf.DUMMYFUNCTION("""COMPUTED_VALUE"""),1150.0) -> 1150
A76: =IFERROR(__xludf.DUMMYFUNCTION("""COMPUTED_VALUE"""),"FLFNC") -> FLFNC | B76: =IFERROR(__xludf.DUMMYFUNCTION("""COMPUTED_VALUE"""),"Flofenicol") -> Flofenicol | C76: =IFERROR(__xludf.DUMMYFUNCTION("""COMPUTED_VALUE"""),"mL") -> mL | D76: =IFERROR(__xludf.DUMMYFUNCTION("""COMPUTED_VALUE"""),1000.0) -> 1000
A77: =IFERROR(__xludf.DUMMYFUNCTION("""COMPUTED_VALUE"""),"FRCMT") -> FRCMT | B77: =IFERROR(__xludf.DUMMYFUNCTION("""COMPUTED_VALUE"""),"Furosemid 40 mg tiêm") -> Furosemid 40 mg tiêm | C77: =IFERROR(__xludf.DUMMYFUNCTION("""COMPUTED_VALUE"""),"Ống") -> Ống | D77: =IFERROR(__xludf.DUMMYFUNCTION("""COMPUTED_VALUE"""),3400.0) -> 3400
A78: =IFERROR(__xludf.DUMMYFUNCTION("""COMPUTED_VALUE"""),"FRCMU") -> FRCMU | B78: =IFERROR(__xludf.DUMMYFUNCTION("""COMPUTED_VALUE"""),"Furosemid 40 mg uống") -> Furosemid 40 mg uống | C78: =IFERROR(__xludf.DUMMYFUNCTION("""COMPUTED_VALUE"""),"Viên") -> Viên | D78: =IFERROR(__xludf.DUMMYFUNCTION("""COMPUTED_VALUE"""),500.0) -> 500
A79: =IFERROR(__xludf.DUMMYFUNCTION("""COMPUTED_VALUE"""),"GPT") -> GPT | B79: =IFERROR(__xludf.DUMMYFUNCTION("""COMPUTED_VALUE"""),"Gạc phẫu thuật") -> Gạc phẫu thuật | C79: =IFERROR(__xludf.DUMMYFUNCTION("""COMPUTED_VALUE"""),"Hộp") -> Hộp | D79: =IFERROR(__xludf.DUMMYFUNCTION("""COMPUTED_VALUE"""),300000.0) -> 300000
A80: =IFERROR(__xludf.DUMMYFUNCTION("""COMPUTED_VALUE"""),"GPTOB") -> GPTOB | B80: =IFERROR(__xludf.DUMMYFUNCTION("""COMPUTED_VALUE"""),"Gạc phẫu thuật ổ bụng") -> Gạc phẫu thuật ổ bụng | C80: =IFERROR(__xludf.DUMMYFUNCTION("""COMPUTED_VALUE"""),"Gói") -> Gói | D80: =IFERROR(__xludf.DUMMYFUNCTION("""COMPUTED_VALUE"""),8000.0) -> 8000
A81: =IFERROR(__xludf.DUMMYFUNCTION("""COMPUTED_VALUE"""),"GTPT") -> GTPT | B81: =IFERROR(__xludf.DUMMYFUNCTION("""COMPUTED_VALUE"""),"Găng tay phẫu thuật") -> Găng tay phẫu thuật | C81: =IFERROR(__xludf.DUMMYFUNCTION("""COMPUTED_VALUE"""),"Đôi") -> Đôi | D81: =IFERROR(__xludf.DUMMYFUNCTION("""COMPUTED_VALUE"""),5400.0) -> 5400
A82: =IFERROR(__xludf.DUMMYFUNCTION("""COMPUTED_VALUE"""),"GTT") -> GTT | B82: =IFERROR(__xludf.DUMMYFUNCTION("""COMPUTED_VALUE"""),"Găng tay thường") -> Găng tay thường | C82: =IFERROR(__xludf.DUMMYFUNCTION("""COMPUTED_VALUE"""),"Hộp") -> Hộp | D82: =IFERROR(__xludf.DUMMYFUNCTION("""COMPUTED_VALUE"""),65000.0) -> 65000
A83: =IFERROR(__xludf.DUMMYFUNCTION("""COMPUTED_VALUE"""),"GSA") -> GSA | B83: =IFERROR(__xludf.DUMMYFUNCTION("""COMPUTED_VALUE"""),"Gel siêu âm") -> Gel siêu âm | C83: =IFERROR(__xludf.DUMMYFUNCTION("""COMPUTED_VALUE"""),"Gam") -> Gam | D83: =IFERROR(__xludf.DUMMYFUNCTION("""COMPUTED_VALUE"""),30.0) -> 30
A84: =IFERROR(__xludf.DUMMYFUNCTION("""COMPUTED_VALUE"""),"GTMC4") -> GTMC4 | B84: =IFERROR(__xludf.DUMMYFUNCTION("""COMPUTED_VALUE"""),"Gentamycin 4%") -> Gentamycin 4% | C84: =IFERROR(__xludf.DUMMYFUNCTION("""COMPUTED_VALUE"""),"mL") -> mL | D84: =IFERROR(__xludf.DUMMYFUNCTION("""COMPUTED_VALUE"""),250.0) -> 250
A85: =IFERROR(__xludf.DUMMYFUNCTION("""COMPUTED_VALUE"""),"GI") -> GI | B85: =IFERROR(__xludf.DUMMYFUNCTION("""COMPUTED_VALUE"""),"Giấy in") -> Giấy in | C85: =IFERROR(__xludf.DUMMYFUNCTION("""COMPUTED_VALUE"""),"Cuộn") -> Cuộn | D85: =IFERROR(__xludf.DUMMYFUNCTION("""COMPUTED_VALUE"""),5280.0) -> 5280
A86: =IFERROR(__xludf.DUMMYFUNCTION("""COMPUTED_VALUE"""),"GL5") -> GL5 | B86: =IFERROR(__xludf.DUMMYFUNCTION("""COMPUTED_VALUE"""),"Glucose 5%") -> Glucose 5% | C86: =IFERROR(__xludf.DUMMYFUNCTION("""COMPUTED_VALUE"""),"Chai") -> Chai | D86: =IFERROR(__xludf.DUMMYFUNCTION("""COMPUTED_VALUE"""),12250.0) -> 12250
A87: =IFERROR(__xludf.DUMMYFUNCTION("""COMPUTED_VALUE"""),"HTX") -> HTX | B87: =IFERROR(__xludf.DUMMYFUNCTION("""COMPUTED_VALUE"""),"Hantox") -> Hantox | C87: =IFERROR(__xludf.DUMMYFUNCTION("""COMPUTED_VALUE"""),"mL") -> mL | D87: =IFERROR(__xludf.DUMMYFUNCTION("""COMPUTED_VALUE"""),500.0) -> 500
A88: =IFERROR(__xludf.DUMMYFUNCTION("""COMPUTED_VALUE"""),"HCMSL1") -> HCMSL1 | B88: =IFERROR(__xludf.DUMMYFUNCTION("""COMPUTED_VALUE"""),"HC Diluent") -> HC Diluent | C88: =IFERROR(__xludf.DUMMYFUNCTION("""COMPUTED_VALUE"""),"Hộp") -> Hộp | D88: =IFERROR(__xludf.DUMMYFUNCTION("""COMPUTED_VALUE"""),900000.0) -> 900000
A89: =IFERROR(__xludf.DUMMYFUNCTION("""COMPUTED_VALUE"""),"HCMSL3") -> HCMSL3 | B89: =IFERROR(__xludf.DUMMYFUNCTION("""COMPUTED_VALUE"""),"HC Ez cleaner") -> HC Ez cleaner | C89: =IFERROR(__xludf.DUMMYFUNCTION("""COMPUTED_VALUE"""),"Chai") -> Chai | D89: =IFERROR(__xludf.DUMMYFUNCTION("""COMPUTED_VALUE"""),600000.0) -> 600000
A90: =IFERROR(__xludf.DUMMYFUNCTION("""COMPUTED_VALUE"""),"HCMSL2") -> HCMSL2 | B90: =IFERROR(__xludf.DUMMYFUNCTION("""COMPUTED_VALUE"""),"HC Lyse") -> HC Lyse | C90: =IFERROR(__xludf.DUMMYFUNCTION("""COMPUTED_VALUE"""),"Chai") -> Chai | D90: =IFERROR(__xludf.DUMMYFUNCTION("""COMPUTED_VALUE"""),900000.0) -> 900000
A91: =IFERROR(__xludf.DUMMYFUNCTION("""COMPUTED_VALUE"""),"HISANTI") -> HISANTI | B91: =IFERROR(__xludf.DUMMYFUNCTION("""COMPUTED_VALUE"""),"Hisanti (chlopheramin)") -> Hisanti (chlopheramin) | C91: =IFERROR(__xludf.DUMMYFUNCTION("""COMPUTED_VALUE"""),"mL") -> mL | D91: =IFERROR(__xludf.DUMMYFUNCTION("""COMPUTED_VALUE"""),817.0) -> 817
A92: =IFERROR(__xludf.DUMMYFUNCTION("""COMPUTED_VALUE"""),"IMC") -> IMC | B92: =IFERROR(__xludf.DUMMYFUNCTION("""COMPUTED_VALUE"""),"Imochem 120 (imidocard)") -> Imochem 120 (imidocard) | C92: =IFERROR(__xludf.DUMMYFUNCTION("""COMPUTED_VALUE"""),"mL") -> mL | D92: =IFERROR(__xludf.DUMMYFUNCTION("""COMPUTED_VALUE"""),10100.0) -> 10100
A93: =IFERROR(__xludf.DUMMYFUNCTION("""COMPUTED_VALUE"""),"ISL") -> ISL | B93: =IFERROR(__xludf.DUMMYFUNCTION("""COMPUTED_VALUE"""),"Insulin") -> Insulin | C93: =IFERROR(__xludf.DUMMYFUNCTION("""COMPUTED_VALUE"""),"mL") -> mL | D93: =IFERROR(__xludf.DUMMYFUNCTION("""COMPUTED_VALUE"""),1500.0) -> 1500
A94: =IFERROR(__xludf.DUMMYFUNCTION("""COMPUTED_VALUE"""),"IVMT") -> IVMT | B94: =IFERROR(__xludf.DUMMYFUNCTION("""COMPUTED_VALUE"""),"Ivermectin") -> Ivermectin | C94: =IFERROR(__xludf.DUMMYFUNCTION("""COMPUTED_VALUE"""),"mL") -> mL | D94: =IFERROR(__xludf.DUMMYFUNCTION("""COMPUTED_VALUE"""),1300.0) -> 1300
A95: =IFERROR(__xludf.DUMMYFUNCTION("""COMPUTED_VALUE"""),"KALI10") -> KALI10 | B95: =IFERROR(__xludf.DUMMYFUNCTION("""COMPUTED_VALUE"""),"Kali clorid 10%") -> Kali clorid 10% | C95: =IFERROR(__xludf.DUMMYFUNCTION("""COMPUTED_VALUE"""),"Ống") -> Ống | D95: =IFERROR(__xludf.DUMMYFUNCTION("""COMPUTED_VALUE"""),4500.0) -> 4500
A96: =IFERROR(__xludf.DUMMYFUNCTION("""COMPUTED_VALUE"""),"KDVT") -> KDVT | B96: =IFERROR(__xludf.DUMMYFUNCTION("""COMPUTED_VALUE"""),"Keo dán vết thương") -> Keo dán vết thương | C96: =IFERROR(__xludf.DUMMYFUNCTION("""COMPUTED_VALUE"""),"Cuộn") -> Cuộn | D96: =IFERROR(__xludf.DUMMYFUNCTION("""COMPUTED_VALUE"""),120000.0) -> 120000
A97: =IFERROR(__xludf.DUMMYFUNCTION("""COMPUTED_VALUE"""),"KG") -> KG | B97: =IFERROR(__xludf.DUMMYFUNCTION("""COMPUTED_VALUE"""),"Keo giấy") -> Keo giấy | C97: =IFERROR(__xludf.DUMMYFUNCTION("""COMPUTED_VALUE"""),"Cuộn") -> Cuộn | D97: =IFERROR(__xludf.DUMMYFUNCTION("""COMPUTED_VALUE"""),6000.0) -> 6000
A98: =IFERROR(__xludf.DUMMYFUNCTION("""COMPUTED_VALUE"""),"KUG") -> KUG | B98: =IFERROR(__xludf.DUMMYFUNCTION("""COMPUTED_VALUE"""),"Keo urgo") -> Keo urgo | C98: =IFERROR(__xludf.DUMMYFUNCTION("""COMPUTED_VALUE"""),"Cuộn") -> Cuộn | D98: =IFERROR(__xludf.DUMMYFUNCTION("""COMPUTED_VALUE"""),18000.0) -> 18000
A99: =IFERROR(__xludf.DUMMYFUNCTION("""COMPUTED_VALUE"""),"KTM") -> KTM | B99: =IFERROR(__xludf.DUMMYFUNCTION("""COMPUTED_VALUE"""),"Ketamin") -> Ketamin | C99: =IFERROR(__xludf.DUMMYFUNCTION("""COMPUTED_VALUE"""),"mL") -> mL | D99: =IFERROR(__xludf.DUMMYFUNCTION("""COMPUTED_VALUE"""),30000.0) -> 30000
A100: =IFERROR(__xludf.DUMMYFUNCTION("""COMPUTED_VALUE"""),"KTCNZ") -> KTCNZ | B100: =IFERROR(__xludf.DUMMYFUNCTION("""COMPUTED_VALUE"""),"Ketoconazone") -> Ketoconazone | C100: =IFERROR(__xludf.DUMMYFUNCTION("""COMPUTED_VALUE"""),"Viên") -> Viên | D100: =IFERROR(__xludf.DUMMYFUNCTION("""COMPUTED_VALUE"""),2300.0) -> 2300
...

Sheet NH ngoài giờ
A1: Ca | B1: Nội dung thực hiện | C1: Chi phí | D1: Số lượng | E1: Thành tiền | F1: Tổng thu | G1: NV tiếp nhận
A2: Trần Phú | B2: Phẫu Thuật Viêm tử cung | C2: 1800 | D2: 1 | E2: =C2*D2 -> 1800 | F2: 1800 | G2: Tuấn , Trà
A3: 1209 | B3: Phẫu thuật cắt lưỡi | C3: 600 | D3: 1 | E3: =C3*D3 -> 600 | F3: 600 | G3: Tuấn, Ánh
A4: 1224 | B4: Siêu âm | C4: 100 | D4: 1 | E4: =C4*D4 -> 100 | F4: 230 | G4: Tuấn
B5: Chích thuốc | C5: 130 | D5: 1 | E5: =C5*D5 -> 130
A6: 1235 | B6: chụp phim | C6: 150 | D6: 2 | E6: =C6*D6 -> 300 | F6: 750 | G6: Tuấn , Ánh , Trà
B7: siêu âm | C7: 200 | D7: 1 | E7: =C7*D7 -> 200
B8: Truyền dịch | C8: 250 | D8: 1 | E8: =C8*D8 -> 250
A9: 1240 | B9: chụp phim | C9: 150 | D9: 2 | E9: =C9*D9 -> 300 | F9: 400 | G9: Tuấn , Ánh
B10: Ngoài giờ | C10: 100 | D10: 1 | E10: =C10*D10 -> 100
A11: 1242 | B11: chích thuốc+xử lý vết thương | C11: 200 | D11: 1 | E11: =C11*D11 -> 200 | F11: 200 | G11: Tuấn
A12: 1247 | B12: Cấp cứu ngộ độc | C12: 600 | D12: 1 | E12: =C12*D12 -> 600 | F12: 600 | G12: Tuấn
A13: 1256 | B13: Lưu chăm sóc đêm | C13: 100 | D13: 1 | E13: =C13*D13 -> 100 | F13: 100 | G13: Ánh
E14: =C14*D14 -> 0
E15: =C15*D15 -> 0
E16: =C16*D16 -> 0
E17: =C17*D17 -> 0
E18: =C18*D18 -> 0
E19: =C19*D19 -> 0
E20: =C20*D20 -> 0
E21: =C21*D21 -> 0
